Workbook

Sheet 入出金合計表 【第18期2026年6月～】 
B1: 2025年5月末残 | C1: ='入出金合計表 【第17期2025年6月～】'!C391 -> -13412076
C2: ２０２6年６月‐２０２7年５月残高
C3: 残高日次 | D3: 入金合計 | E3: 金融機関関連 | F3: 保険関連 | G3: お客様関連 | H3: 出金合計 | I3: 金融機関関連 | J3: 買掛関連 | K3: 経費関連
B4: 44348 | C4: =SUM(C1+D4-H4) -> -14248572 | D4: =E4+F4+G4 -> 0 | E4: ='入金明細【18期】 '!D3 -> 0 | F4: ='入金明細【18期】 '!M3 -> 0 | G4: ='入金明細【18期】 '!T3 -> 0 | H4: =I4+J4+K4 -> 836496 | I4: ='出金明細【18期】'!D3 -> 0 | J4: ='出金明細【17期】'!M3 -> 0 | K4: ='出金明細【18期】'!AD3 -> 836496
B5: 44349 | C5: =SUM(C4+D5-H5) -> -14248572 | D5: =E5+F5+G5 -> 0 | E5: ='入金明細【18期】 '!D4 -> 0 | F5: ='入金明細【18期】 '!M4 -> 0 | G5: ='入金明細【18期】 '!T4 -> 0 | H5: =I5+J5+K5 -> 0 | I5: ='出金明細【18期】'!D4 -> 0 | J5: ='出金明細【18期】'!M4 -> 0 | K5: ='出金明細【18期】'!AD4 -> 0
B6: 45446 | C6: =SUM(C5+D6-H6) -> -14248572 | D6: =E6+F6+G6 -> 0 | E6: ='入金明細【18期】 '!D5 -> 0 | F6: ='入金明細【18期】 '!M5 -> 0 | G6: ='入金明細【18期】 '!T5 -> 0 | H6: =I6+J6+K6 -> 0 | I6: ='出金明細【18期】'!D5 -> 0 | J6: ='出金明細【18期】'!M5 -> 0 | K6: ='出金明細【18期】'!AD5 -> 0
B7: 44351 | C7: =SUM(C6+D7-H7) -> -14248572 | D7: =E7+F7+G7 -> 0 | E7: ='入金明細【18期】 '!D6 -> 0 | F7: ='入金明細【18期】 '!M6 -> 0 | G7: ='入金明細【18期】 '!T6 -> 0 | H7: =I7+J7+K7 -> 0 | I7: ='出金明細【18期】'!D6 -> 0 | J7: ='出金明細【18期】'!M6 -> 0 | K7: ='出金明細【18期】'!AD6 -> 0
B8: 44352 | C8: =SUM(C7+D8-H8) -> -14409372 | D8: =E8+F8+G8 -> 0 | E8: ='入金明細【18期】 '!D7 -> 0 | F8: ='入金明細【18期】 '!M7 -> 0 | G8: ='入金明細【18期】 '!T7 -> 0 | H8: =I8+J8+K8 -> 160800 | I8: ='出金明細【18期】'!D7 -> 0 | J8: ='出金明細【18期】'!M7 -> 0 | K8: ='出金明細【18期】'!AD7 -> 160800
B9: 44353 | C9: =SUM(C8+D9-H9) -> -14409372 | D9: =E9+F9+G9 -> 0 | E9: ='入金明細【18期】 '!D8 -> 0 | F9: ='入金明細【18期】 '!M8 -> 0 | G9: ='入金明細【18期】 '!T8 -> 0 | H9: =I9+J9+K9 -> 0 | I9: ='出金明細【18期】'!D8 -> 0 | J9: ='出金明細【18期】'!M8 -> 0 | K9: ='出金明細【18期】'!AD8 -> 0
B10: 44354 | C10: =SUM(C9+D10-H10) -> -14409372 | D10: =E10+F10+G10 -> 0 | E10: ='入金明細【18期】 '!D9 -> 0 | F10: ='入金明細【18期】 '!M9 -> 0 | G10: ='入金明細【18期】 '!T9 -> 0 | H10: =I10+J10+K10 -> 0 | I10: ='出金明細【18期】'!D9 -> 0 | J10: ='出金明細【18期】'!M9 -> 0 | K10: ='出金明細【18期】'!AD9 -> 0
B11: 44355 | C11: =SUM(C10+D11-H11) -> -14409372 | D11: =E11+F11+G11 -> 0 | E11: ='入金明細【18期】 '!D10 -> 0 | F11: ='入金明細【18期】 '!M10 -> 0 | G11: ='入金明細【18期】 '!T10 -> 0 | H11: =I11+J11+K11 -> 0 | I11: ='出金明細【18期】'!D10 -> 0 | J11: ='出金明細【18期】'!M10 -> 0 | K11: ='出金明細【18期】'!AD10 -> 0
B12: 44356 | C12: =SUM(C11+D12-H12) -> -18115461 | D12: =E12+F12+G12 -> 0 | E12: ='入金明細【18期】 '!D11 -> 0 | F12: ='入金明細【18期】 '!M11 -> 0 | G12: ='入金明細【18期】 '!T11 -> 0 | H12: =I12+J12+K12 -> 3706089 | I12: ='出金明細【18期】'!D11 -> 0 | J12: ='出金明細【18期】'!M11 -> 0 | K12: ='出金明細【18期】'!AD11 -> 3706089
B13: 44357 | C13: =SUM(C12+D13-H13) -> -18115461 | D13: =E13+F13+G13 -> 0 | E13: ='入金明細【18期】 '!D12 -> 0 | F13: ='入金明細【18期】 '!M12 -> 0 | G13: ='入金明細【18期】 '!T12 -> 0 | H13: =I13+J13+K13 -> 0 | I13: ='出金明細【18期】'!D12 -> 0 | J13: ='出金明細【18期】'!M12 -> 0 | K13: ='出金明細【18期】'!AD12 -> 0
B14: 44358 | C14: =SUM(C13+D14-H14) -> -18115461 | D14: =E14+F14+G14 -> 0 | E14: ='入金明細【18期】 '!D13 -> 0 | F14: ='入金明細【18期】 '!M13 -> 0 | G14: ='入金明細【18期】 '!T13 -> 0 | H14: =I14+J14+K14 -> 0 | I14: ='出金明細【18期】'!D13 -> 0 | J14: ='出金明細【18期】'!M13 -> 0 | K14: ='出金明細【18期】'!AD13 -> 0
B15: 44359 | C15: =SUM(C14+D15-H15) -> -18115461 | D15: =E15+F15+G15 -> 0 | E15: ='入金明細【18期】 '!D14 -> 0 | F15: ='入金明細【18期】 '!M14 -> 0 | G15: ='入金明細【18期】 '!T14 -> 0 | H15: =I15+J15+K15 -> 0 | I15: ='出金明細【18期】'!D14 -> 0 | J15: ='出金明細【18期】'!M14 -> 0 | K15: ='出金明細【18期】'!AD14 -> 0
B16: 44360 | C16: =SUM(C15+D16-H16) -> -18115461 | D16: =E16+F16+G16 -> 0 | E16: ='入金明細【18期】 '!D15 -> 0 | F16: ='入金明細【18期】 '!M15 -> 0 | G16: ='入金明細【18期】 '!T15 -> 0 | H16: =I16+J16+K16 -> 0 | I16: ='出金明細【18期】'!D15 -> 0 | J16: ='出金明細【18期】'!M15 -> 0 | K16: ='出金明細【18期】'!AD15 -> 0
... B33: 44377 | C33: =SUM(C32+D33-H33) -> -27736909 | D33: =E33+F33+G33 -> 0 | E33: ='入金明細【18期】 '!D32 -> 0 | F33: ='入金明細【18期】 '!M32 -> 0 | G33: ='入金明細【18期】 '!T32 -> 0 | H33: =I33+J33+K33 -> 2470488 | I33: ='出金明細【18期】'!D32 -> 2470488 | J33: ='出金明細【18期】'!M32 -> 0 | K33: ='出金明細【18期】'!AD32 -> 0
B34: 6月合計 | C34: =SUM(D34-H34) -> -14324833 | D34: =E34+F34+G34 -> 0 | E34: =SUM(E4:E33) -> 0 | F34: =SUM(F4:F33) -> 0 | G34: =SUM(G4:G33) -> 0 | H34: =SUM(H4:H33) -> 14324833 | I34: =SUM(I4:I33) -> 5269520 | J34: =SUM(J4:J33) -> 1845000 | K34: =SUM(K4:K33) -> 7210313
B35: 累計 | C35: =SUM(D35-H35) -> -14324833 | D35: =E35+F35+G35 -> 0 | E35: =E2+E34 -> 0 | F35: =F2+F34 -> 0 | G35: =G2+G34 -> 0 | H35: =H2+H34 -> 14324833 | I35: =I2+I34 -> 5269520 | J35: =J2+J34 -> 1845000 | K35: =K2+K34 -> 7210313
B36: 44378 | C36: =SUM(C33+D36-H36) -> -27819105 | D36: =E36+F36+G36 -> 0 | E36: ='入金明細【18期】 '!D35 -> 0 | F36: ='入金明細【18期】 '!M35 -> 0 | G36: ='入金明細【18期】 '!T35 -> 0 | H36: =I36+J36+K36 -> 82196 | I36: ='出金明細【18期】'!D35 -> 0 | J36: ='出金明細【18期】'!M35 -> 0 | K36: ='出金明細【18期】'!AD35 -> 82196
B37: 45109 | C37: =SUM(C36+D37-H37) -> -27848585 | D37: =E37+F37+G37 -> 0 | E37: ='入金明細【18期】 '!D36 -> 0 | F37: ='入金明細【18期】 '!M36 -> 0 | G37: ='入金明細【18期】 '!T36 -> 0 | H37: =I37+J37+K37 -> 29480 | I37: ='出金明細【18期】'!D36 -> 0 | J37: ='出金明細【18期】'!M36 -> 0 | K37: ='出金明細【18期】'!AD36 -> 29480
B38: 45110 | C38: =SUM(C37+D38-H38) -> -27848585 | D38: =E38+F38+G38 -> 0 | E38: ='入金明細【18期】 '!D37 -> 0 | F38: ='入金明細【18期】 '!M37 -> 0 | G38: ='入金明細【18期】 '!T37 -> 0 | H38: =I38+J38+K38 -> 0 | I38: ='出金明細【18期】'!D37 -> 0 | J38: ='出金明細【18期】'!M37 -> 0 | K38: ='出金明細【18期】'!AD37 -> 0
B39: 45111 | C39: =SUM(C38+D39-H39) -> -27848585 | D39: =E39+F39+G39 -> 0 | E39: ='入金明細【18期】 '!D38 -> 0 | F39: ='入金明細【18期】 '!M38 -> 0 | G39: ='入金明細【18期】 '!T38 -> 0 | H39: =I39+J39+K39 -> 0 | I39: ='出金明細【18期】'!D38 -> 0 | J39: ='出金明細【18期】'!M38 -> 0 | K39: ='出金明細【18期】'!AD38 -> 0
B40: 45112 | C40: =SUM(C39+D40-H40) -> -27936585 | D40: =E40+F40+G40 -> 0 | E40: ='入金明細【18期】 '!D39 -> 0 | F40: ='入金明細【18期】 '!M39 -> 0 | G40: ='入金明細【18期】 '!T39 -> 0 | H40: =I40+J40+K40 -> 88000 | I40: ='出金明細【18期】'!D39 -> 0 | J40: ='出金明細【18期】'!M39 -> 0 | K40: ='出金明細【18期】'!AD39 -> 88000
B41: 45113 | C41: =SUM(C40+D41-H41) -> -27936585 | D41: =E41+F41+G41 -> 0 | E41: ='入金明細【18期】 '!D40 -> 0 | F41: ='入金明細【18期】 '!M40 -> 0 | G41: ='入金明細【18期】 '!T40 -> 0 | H41: =I41+J41+K41 -> 0 | I41: ='出金明細【18期】'!D40 -> 0 | J41: ='出金明細【18期】'!M40 -> 0 | K41: ='出金明細【18期】'!AD40 -> 0
B42: 45114 | C42: =SUM(C41+D42-H42) -> -27936585 | D42: =E42+F42+G42 -> 0 | E42: ='入金明細【18期】 '!D41 -> 0 | F42: ='入金明細【18期】 '!M41 -> 0 | G42: ='入金明細【18期】 '!T41 -> 0 | H42: =I42+J42+K42 -> 0 | I42: ='出金明細【18期】'!D41 -> 0 | J42: ='出金明細【18期】'!M41 -> 0 | K42: ='出金明細【18期】'!AD41 -> 0
B43: 45115 | C43: =SUM(C42+D43-H43) -> -27936585 | D43: =E43+F43+G43 -> 0 | E43: ='入金明細【18期】 '!D42 -> 0 | F43: ='入金明細【18期】 '!M42 -> 0 | G43: ='入金明細【18期】 '!T42 -> 0 | H43: =I43+J43+K43 -> 0 | I43: ='出金明細【18期】'!D42 -> 0 | J43: ='出金明細【18期】'!M42 -> 0 | K43: ='出金明細【18期】'!AD42 -> 0
B44: 45116 | C44: =SUM(C43+D44-H44) -> -31642674 | D44: =E44+F44+G44 -> 0 | E44: ='入金明細【18期】 '!D43 -> 0 | F44: ='入金明細【18期】 '!M43 -> 0 | G44: ='入金明細【18期】 '!T43 -> 0 | H44: =I44+J44+K44 -> 3706089 | I44: ='出金明細【18期】'!D43 -> 0 | J44: ='出金明細【18期】'!M43 -> 0 | K44: ='出金明細【18期】'!AD43 -> 3706089
B45: 45117 | C45: =SUM(C44+D45-H45) -> -31642674 | D45: =E45+F45+G45 -> 0 | E45: ='入金明細【18期】 '!D44 -> 0 | F45: ='入金明細【18期】 '!M44 -> 0 | G45: ='入金明細【18期】 '!T44 -> 0 | H45: =I45+J45+K45 -> 0 | I45: ='出金明細【18期】'!D44 -> 0 | J45: ='出金明細【18期】'!M44 -> 0 | K45: ='出金明細【18期】'!AD44 -> 0
B46: 45118 | C46: =SUM(C45+D46-H46) -> -31642674 | D46: =E46+F46+G46 -> 0 | E46: ='入金明細【18期】 '!D45 -> 0 | F46: ='入金明細【18期】 '!M45 -> 0 | G46: ='入金明細【18期】 '!T45 -> 0 | H46: =I46+J46+K46 -> 0 | I46: ='出金明細【18期】'!D45 -> 0 | J46: ='出金明細【18期】'!M45 -> 0 | K46: ='出金明細【18期】'!AD45 -> 0
B47: 45119 | C47: =SUM(C46+D47-H47) -> -31642674 | D47: =E47+F47+G47 -> 0 | E47: ='入金明細【18期】 '!D46 -> 0 | F47: ='入金明細【18期】 '!M46 -> 0 | G47: ='入金明細【18期】 '!T46 -> 0 | H47: =I47+J47+K47 -> 0 | I47: ='出金明細【18期】'!D46 -> 0 | J47: ='出金明細【18期】'!M46 -> 0 | K47: ='出金明細【18期】'!AD46 -> 0
B48: 45120 | C48: =SUM(C47+D48-H48) -> -31642674 | D48: =E48+F48+G48 -> 0 | E48: ='入金明細【18期】 '!D47 -> 0 | F48: ='入金明細【18期】 '!M47 -> 0 | G48: ='入金明細【18期】 '!T47 -> 0 | H48: =I48+J48+K48 -> 0 | I48: ='出金明細【18期】'!D47 -> 0 | J48: ='出金明細【18期】'!M47 -> 0 | K48: ='出金明細【18期】'!AD47 -> 0
... B66: 45138 | C66: =SUM(C65+D66-H66) -> -66306775 | D66: =E66+F66+G66 -> 0 | E66: ='入金明細【18期】 '!D65 -> 0 | F66: ='入金明細【18期】 '!M65 -> 0 | G66: ='入金明細【18期】 '!T65 -> 0 | H66: =I66+J66+K66 -> 2470488 | I66: ='出金明細【18期】'!D65 -> 2470488 | J66: ='出金明細【18期】'!M65 -> 0 | K66: ='出金明細【18期】'!AD65 -> 0
B67: 7月合計 | C67: =SUM(D67-H67) -> -38569866 | D67: =SUM(D36:D66) -> 0 | E67: =SUM(E36:E66) -> 0 | F67: =SUM(F36:F66) -> 0 | G67: =SUM(G36:G66) -> 0 | H67: =SUM(H36:H66) -> 38569866 | I67: =SUM(I36:I66) -> 30269520 | J67: =SUM(J36:J66) -> 1895000 | K67: =SUM(K36:K66) -> 6405346
B68: 累計 | C68: =SUM(D68-H68) -> -52894699 | D68: =D35+D67 -> 0 | E68: =E35+E67 -> 0 | F68: =F35+F67 -> 0 | G68: =G35+G67 -> 0 | H68: =H35+H67 -> 52894699 | I68: =I35+I67 -> 35539040 | J68: =J35+J67 -> 3740000 | K68: =K35+K67 -> 13615659
B69: 45139 | C69: =SUM(C66+D69-H69) -> -66388971 | D69: =E69+F69+G69 -> 0 | E69: ='入金明細【18期】 '!D68 -> 0 | F69: ='入金明細【18期】 '!M68 | G69: ='入金明細【18期】 '!T68 -> 0 | H69: =I69+J69+K69 -> 82196 | I69: ='出金明細【18期】'!D68 -> 0 | J69: ='出金明細【18期】'!M68 -> 0 | K69: ='出金明細【18期】'!AD68 -> 82196
B70: 45140 | C70: =SUM(C69+D70-H70) -> -66418451 | D70: =E70+F70+G70 -> 0 | E70: ='入金明細【18期】 '!D69 -> 0 | F70: ='入金明細【18期】 '!M69 | G70: ='入金明細【18期】 '!T69 -> 0 | H70: =I70+J70+K70 -> 29480 | I70: ='出金明細【18期】'!D69 -> 0 | J70: ='出金明細【18期】'!M69 -> 0 | K70: ='出金明細【18期】'!AD69 -> 29480
B71: 45141 | C71: =SUM(C70+D71-H71) -> -66418451 | D71: =E71+F71+G71 -> 0 | E71: ='入金明細【18期】 '!D70 -> 0 | F71: ='入金明細【18期】 '!M70 | G71: ='入金明細【18期】 '!T70 -> 0 | H71: =I71+J71+K71 -> 0 | I71: ='出金明細【18期】'!D70 -> 0 | J71: ='出金明細【18期】'!M70 -> 0 | K71: ='出金明細【18期】'!AD70 -> 0
B72: 45142 | C72: =SUM(C71+D72-H72) -> -66418451 | D72: =E72+F72+G72 -> 0 | E72: ='入金明細【18期】 '!D71 -> 0 | F72: ='入金明細【18期】 '!M71 | G72: ='入金明細【18期】 '!T71 -> 0 | H72: =I72+J72+K72 -> 0 | I72: ='出金明細【18期】'!D71 -> 0 | J72: ='出金明細【18期】'!M71 -> 0 | K72: ='出金明細【18期】'!AD71 -> 0
B73: 45143 | C73: =SUM(C72+D73-H73) -> -66506451 | D73: =E73+F73+G73 -> 0 | E73: ='入金明細【18期】 '!D72 -> 0 | F73: ='入金明細【18期】 '!M72 -> 0 | G73: ='入金明細【18期】 '!T72 -> 0 | H73: =I73+J73+K73 -> 88000 | I73: ='出金明細【18期】'!D72 -> 0 | J73: ='出金明細【18期】'!M72 -> 0 | K73: ='出金明細【18期】'!AD72 -> 88000
B74: 45144 | C74: =SUM(C73+D74-H74) -> -66506451 | D74: =E74+F74+G74 -> 0 | E74: ='入金明細【18期】 '!D73 -> 0 | F74: ='入金明細【18期】 '!M73 -> 0 | G74: ='入金明細【18期】 '!T73 -> 0 | H74: =I74+J74+K74 -> 0 | I74: ='出金明細【18期】'!D73 -> 0 | J74: ='出金明細【18期】'!M73 -> 0 | K74: ='出金明細【18期】'!AD73 -> 0
B75: 45145 | C75: =SUM(C74+D75-H75) -> -66506451 | D75: =E75+F75+G75 -> 0 | E75: ='入金明細【18期】 '!D74 -> 0 | F75: ='入金明細【18期】 '!M74 -> 0 | G75: ='入金明細【18期】 '!T74 -> 0 | H75: =I75+J75+K75 -> 0 | I75: ='出金明細【18期】'!D74 -> 0 | J75: ='出金明細【18期】'!M74 -> 0 | K75: ='出金明細【18期】'!AD74 -> 0
B76: 45146 | C76: =SUM(C75+D76-H76) -> -66506451 | D76: =E76+F76+G76 -> 0 | E76: ='入金明細【18期】 '!D75 -> 0 | F76: ='入金明細【18期】 '!M75 -> 0 | G76: ='入金明細【18期】 '!T75 -> 0 | H76: =I76+J76+K76 -> 0 | I76: ='出金明細【18期】'!D75 -> 0 | J76: ='出金明細【18期】'!M75 -> 0 | K76: ='出金明細【18期】'!AD75 -> 0
B77: 45147 | C77: =SUM(C76+D77-H77) -> -70412540 | D77: =E77+F77+G77 -> 0 | E77: ='入金明細【18期】 '!D76 -> 0 | F77: ='入金明細【18期】 '!M76 -> 0 | G77: ='入金明細【18期】 '!T76 -> 0 | H77: =I77+J77+K77 -> 3906089 | I77: ='出金明細【18期】'!D76 -> 0 | J77: ='出金明細【18期】'!M76 -> 0 | K77: ='出金明細【18期】'!AD76 -> 3906089
B78: 45148 | C78: =SUM(C77+D78-H78) -> -70412540 | D78: =E78+F78+G78 -> 0 | E78: ='入金明細【18期】 '!D77 -> 0 | F78: ='入金明細【18期】 '!M77 -> 0 | G78: ='入金明細【18期】 '!T77 -> 0 | H78: =I78+J78+K78 -> 0 | I78: ='出金明細【18期】'!D77 -> 0 | J78: ='出金明細【18期】'!M77 -> 0 | K78: ='出金明細【18期】'!AD77 -> 0
B79: 45149 | C79: =SUM(C78+D79-H79) -> -70412540 | D79: =E79+F79+G79 -> 0 | E79: ='入金明細【18期】 '!D78 -> 0 | F79: ='入金明細【18期】 '!M78 -> 0 | G79: ='入金明細【18期】 '!T78 -> 0 | H79: =I79+J79+K79 -> 0 | I79: ='出金明細【18期】'!D78 -> 0 | J79: ='出金明細【18期】'!M78 -> 0 | K79: ='出金明細【18期】'!AD78 -> 0
B80: 45150 | C80: =SUM(C79+D80-H80) -> -70412540 | D80: =E80+F80+G80 -> 0 | E80: ='入金明細【18期】 '!D79 -> 0 | F80: ='入金明細【18期】 '!M79 -> 0 | G80: ='入金明細【18期】 '!T79 -> 0 | H80: =I80+J80+K80 -> 0 | I80: ='出金明細【18期】'!D79 -> 0 | J80: ='出金明細【18期】'!M79 -> 0 | K80: ='出金明細【18期】'!AD79 -> 0
B81: 45151 | C81: =SUM(C80+D81-H81) -> -70412540 | D81: =E81+F81+G81 -> 0 | E81: ='入金明細【18期】 '!D80 -> 0 | F81: ='入金明細【18期】 '!M80 -> 0 | G81: ='入金明細【18期】 '!T80 -> 0 | H81: =I81+J81+K81 -> 0 | I81: ='出金明細【18期】'!D80 -> 0 | J81: ='出金明細【18期】'!M80 -> 0 | K81: ='出金明細【18期】'!AD80 -> 0
... B99: 45169 | C99: =SUM(C98+D99-H99) -> -79926641 | D99: =E99+F99+G99 -> 0 | E99: ='入金明細【18期】 '!D98 -> 0 | F99: ='入金明細【18期】 '!M98 -> 0 | G99: ='入金明細【18期】 '!T98 -> 0 | H99: =I99+J99+K99 -> 2470488 | I99: ='出金明細【18期】'!D98 -> 2470488 | J99: ='出金明細【18期】'!M98 -> 0 | K99: ='出金明細【18期】'!AD98 -> 0
B100: 8月合計 | C100: =SUM(D100-H100) -> -13619866 | D100: =SUM(D69:D99) -> 0 | E100: =SUM(E69:E99) -> 0 | F100: =SUM(F69:F99) -> 0 | G100: =SUM(G69:G99) -> 0 | H100: =SUM(H69:H99) -> 13619866 | I100: =SUM(I69:I99) -> 5269520 | J100: =SUM(J69:J99) -> 1745000 | K100: =SUM(K69:K99) -> 6605346
B101: 累計 | C101: =SUM(D101-H101) -> -66514565 | D101: =D68+D100 -> 0 | E101: =E68+E100 -> 0 | F101: =F68+F100 -> 0 | G101: =G68+G100 -> 0 | H101: =H68+H100 -> 66514565 | I101: =I68+I100 -> 40808560 | J101: =J68+J100 -> 5485000 | K101: =K68+K100 -> 20221005
B102: 44440 | C102: =SUM(C99+D102-H102) -> -79926641 | D102: =E102+F102+G102 -> 0 | E102: ='入金明細【18期】 '!D101 -> 0 | F102: ='入金明細【18期】 '!M101 -> 0 | G102: ='入金明細【18期】 '!T101 -> 0 | H102: =I102+J102+K102 -> 0 | I102: ='出金明細【18期】'!D101 -> 0 | J102: ='出金明細【18期】'!M101 -> 0 | K102: ='出金明細【18期】'!AD101 -> 0
B103: 44441 | C103: =SUM(C102+D103-H103) -> -79926641 | D103: =E103+F103+G103 -> 0 | E103: ='入金明細【18期】 '!D102 -> 0 | F103: ='入金明細【18期】 '!M102 -> 0 | G103: ='入金明細【18期】 '!T102 -> 0 | H103: =I103+J103+K103 -> 0 | I103: ='出金明細【18期】'!D102 -> 0 | J103: ='出金明細【18期】'!M102 -> 0 | K103: ='出金明細【18期】'!AD102 -> 0
B104: 44442 | C104: =SUM(C103+D104-H104) -> -79926641 | D104: =E104+F104+G104 -> 0 | E104: ='入金明細【18期】 '!D103 -> 0 | F104: ='入金明細【18期】 '!M103 -> 0 | G104: ='入金明細【18期】 '!T103 -> 0 | H104: =I104+J104+K104 -> 0 | I104: ='出金明細【18期】'!D103 -> 0 | J104: ='出金明細【18期】'!M103 -> 0 | K104: ='出金明細【18期】'!AD103 -> 0
B105: 44443 | C105: =SUM(C104+D105-H105) -> -79926641 | D105: =E105+F105+G105 -> 0 | E105: ='入金明細【18期】 '!D104 -> 0 | F105: ='入金明細【18期】 '!M104 -> 0 | G105: ='入金明細【18期】 '!T104 -> 0 | H105: =I105+J105+K105 -> 0 | I105: ='出金明細【18期】'!D104 -> 0 | J105: ='出金明細【18期】'!M104 -> 0 | K105: ='出金明細【18期】'!AD104 -> 0
B106: 44444 | C106: =SUM(C105+D106-H106) -> -79926641 | D106: =E106+F106+G106 -> 0 | E106: ='入金明細【18期】 '!D105 -> 0 | F106: ='入金明細【18期】 '!M105 -> 0 | G106: ='入金明細【18期】 '!T105 -> 0 | H106: =I106+J106+K106 -> 0 | I106: ='出金明細【18期】'!D105 -> 0 | J106: ='出金明細【18期】'!M105 -> 0 | K106: ='出金明細【18期】'!AD105 -> 0
B107: 44445 | C107: =SUM(C106+D107-H107) -> -79926641 | D107: =E107+F107+G107 -> 0 | E107: ='入金明細【18期】 '!D106 -> 0 | F107: ='入金明細【18期】 '!M106 -> 0 | G107: ='入金明細【18期】 '!T106 -> 0 | H107: =I107+J107+K107 -> 0 | I107: ='出金明細【18期】'!D106 -> 0 | J107: ='出金明細【18期】'!M106 -> 0 | K107: ='出金明細【18期】'!AD106 -> 0
B108: 44446 | C108: =SUM(C107+D108-H108) -> -79926641 | D108: =E108+F108+G108 -> 0 | E108: ='入金明細【18期】 '!D107 -> 0 | F108: ='入金明細【18期】 '!M107 -> 0 | G108: ='入金明細【18期】 '!T107 -> 0 | H108: =I108+J108+K108 -> 0 | I108: ='出金明細【18期】'!D107 -> 0 | J108: ='出金明細【18期】'!M107 -> 0 | K108: ='出金明細【18期】'!AD107 -> 0
B109: 44447 | C109: =SUM(C108+D109-H109) -> -79926641 | D109: =E109+F109+G109 -> 0 | E109: ='入金明細【18期】 '!D108 -> 0 | F109: ='入金明細【18期】 '!M108 -> 0 | G109: ='入金明細【18期】 '!T108 -> 0 | H109: =I109+J109+K109 -> 0 | I109: ='出金明細【18期】'!D108 -> 0 | J109: ='出金明細【18期】'!M108 -> 0 | K109: ='出金明細【18期】'!AD108 -> 0
B110: 44448 | C110: =SUM(C109+D110-H110) -> -79926641 | D110: =E110+F110+G110 -> 0 | E110: ='入金明細【18期】 '!D109 -> 0 | F110: ='入金明細【18期】 '!M109 -> 0 | G110: ='入金明細【18期】 '!T109 -> 0 | H110: =I110+J110+K110 -> 0 | I110: ='出金明細【18期】'!D109 -> 0 | J110: ='出金明細【18期】'!M109 -> 0 | K110: ='出金明細【18期】'!AD109 -> 0
B111: 44449 | C111: =SUM(C110+D111-H111) -> -79926641 | D111: =E111+F111+G111 -> 0 | E111: ='入金明細【18期】 '!D110 -> 0 | F111: ='入金明細【18期】 '!M110 -> 0 | G111: ='入金明細【18期】 '!T110 -> 0 | H111: =I111+J111+K111 -> 0 | I111: ='出金明細【18期】'!D110 -> 0 | J111: ='出金明細【18期】'!M110 -> 0 | K111: ='出金明細【18期】'!AD110 -> 0
B112: 44450 | C112: =SUM(C111+D112-H112) -> -79926641 | D112: =E112+F112+G112 -> 0 | E112: ='入金明細【18期】 '!D111 -> 0 | F112: ='入金明細【18期】 '!M111 -> 0 | G112: ='入金明細【18期】 '!T111 -> 0 | H112: =I112+J112+K112 -> 0 | I112: ='出金明細【18期】'!D111 -> 0 | J112: ='出金明細【18期】'!M111 -> 0 | K112: ='出金明細【18期】'!AD111 -> 0
B113: 44451 | C113: =SUM(C112+D113-H113) -> -79926641 | D113: =E113+F113+G113 -> 0 | E113: ='入金明細【18期】 '!D112 -> 0 | F113: ='入金明細【18期】 '!M112 -> 0 | G113: ='入金明細【18期】 '!T112 -> 0 | H113: =I113+J113+K113 -> 0 | I113: ='出金明細【18期】'!D112 -> 0 | J113: ='出金明細【18期】'!M112 -> 0 | K113: ='出金明細【18期】'!AD112 -> 0
B114: 44452 | C114: =SUM(C113+D114-H114) -> -79926641 | D114: =E114+F114+G114 -> 0 | E114: ='入金明細【18期】 '!D113 -> 0 | F114: ='入金明細【18期】 '!M113 -> 0 | G114: ='入金明細【18期】 '!T113 -> 0 | H114: =I114+J114+K114 -> 0 | I114: ='出金明細【18期】'!D113 -> 0 | J114: ='出金明細【18期】'!M113 -> 0 | K114: ='出金明細【18期】'!AD113 -> 0
... B131: 44469 | C131: =SUM(C130+D131-H131) -> -87141161 | D131: =E131+F131+G131 -> 0 | E131: ='入金明細【18期】 '!D130 -> 0 | F131: ='入金明細【18期】 '!M130 -> 0 | G131: ='入金明細【18期】 '!T130 -> 0 | H131: =I131+J131+K131 -> 2470488 | I131: ='出金明細【18期】'!D130 -> 2470488 | J131: ='出金明細【18期】'!M130 -> 0 | K131: ='出金明細【18期】'!AD130 -> 0
B132: 9月合計 | C132: =SUM(D132-H132) -> -7214520 | D132: =SUM(D102:D131) -> 0 | E132: =SUM(E102:E131) -> 0 | F132: =SUM(F102:F131) -> 0 | G132: =SUM(G102:G131) -> 0 | H132: =SUM(H102:H131) -> 7214520 | I132: =SUM(I102:I131) -> 5269520 | J132: =SUM(J102:J131) -> 1745000 | K132: =SUM(K102:K131) -> 200000
B133: 累計 | C133: =SUM(D133-H133) -> -73729085 | D133: =D101+D132 -> 0 | E133: =E101+E132 -> 0 | F133: =F101+F132 -> 0 | G133: =G101+G132 -> 0 | H133: =H101+H132 -> 73729085 | I133: =I101+I132 -> 46078080 | J133: =J101+J132 -> 7230000 | K133: =K101+K132 -> 20421005
B134: 44470 | C134: =SUM(C131+D134-H134) -> -87141161 | D134: =E134+F134+G134 -> 0 | E134: ='入金明細【18期】 '!D133 -> 0 | F134: ='入金明細【18期】 '!M133 | G134: ='入金明細【18期】 '!T133 -> 0 | H134: =I134+J134+K134 -> 0 | I134: ='出金明細【18期】'!D133 -> 0 | J134: ='出金明細【18期】'!M133 -> 0 | K134: ='出金明細【18期】'!AD133 -> 0
B135: 44471 | C135: =SUM(C134+D135-H135) -> -87141161 | D135: =E135+F135+G135 -> 0 | E135: ='入金明細【18期】 '!D134 -> 0 | F135: ='入金明細【18期】 '!M134 | G135: ='入金明細【18期】 '!T134 -> 0 | H135: =I135+J135+K135 -> 0 | I135: ='出金明細【18期】'!D134 -> 0 | J135: ='出金明細【18期】'!M134 -> 0 | K135: ='出金明細【18期】'!AD134 -> 0
B136: 44472 | C136: =SUM(C135+D136-H136) -> -87141161 | D136: =E136+F136+G136 -> 0 | E136: ='入金明細【18期】 '!D135 -> 0 | F136: ='入金明細【18期】 '!M135 -> 0 | G136: ='入金明細【18期】 '!T135 -> 0 | H136: =I136+J136+K136 -> 0 | I136: ='出金明細【18期】'!D135 -> 0 | J136: ='出金明細【18期】'!M135 -> 0 | K136: ='出金明細【18期】'!AD135 -> 0
B137: 44473 | C137: =SUM(C136+D137-H137) -> -87141161 | D137: =E137+F137+G137 -> 0 | E137: ='入金明細【18期】 '!D136 -> 0 | F137: ='入金明細【18期】 '!M136 -> 0 | G137: ='入金明細【18期】 '!T136 -> 0 | H137: =I137+J137+K137 -> 0 | I137: ='出金明細【18期】'!D136 -> 0 | J137: ='出金明細【18期】'!M136 -> 0 | K137: ='出金明細【18期】'!AD136 -> 0
B138: 44474 | C138: =SUM(C137+D138-H138) -> -87141161 | D138: =E138+F138+G138 -> 0 | E138: ='入金明細【18期】 '!D137 -> 0 | F138: ='入金明細【18期】 '!M137 -> 0 | G138: ='入金明細【18期】 '!T137 -> 0 | H138: =I138+J138+K138 -> 0 | I138: ='出金明細【18期】'!D137 -> 0 | J138: ='出金明細【18期】'!M137 -> 0 | K138: ='出金明細【18期】'!AD137 -> 0
B139: 44475 | C139: =SUM(C138+D139-H139) -> -87141161 | D139: =E139+F139+G139 -> 0 | E139: ='入金明細【18期】 '!D138 -> 0 | F139: ='入金明細【18期】 '!M138 -> 0 | G139: ='入金明細【18期】 '!T138 -> 0 | H139: =I139+J139+K139 -> 0 | I139: ='出金明細【18期】'!D138 -> 0 | J139: ='出金明細【18期】'!M138 -> 0 | K139: ='出金明細【18期】'!AD138 -> 0
B140: 44476 | C140: =SUM(C139+D140-H140) -> -87141161 | D140: =E140+F140+G140 -> 0 | E140: ='入金明細【18期】 '!D139 -> 0 | F140: ='入金明細【18期】 '!M139 -> 0 | G140: ='入金明細【18期】 '!T139 -> 0 | H140: =I140+J140+K140 -> 0 | I140: ='出金明細【18期】'!D139 -> 0 | J140: ='出金明細【18期】'!M139 -> 0 | K140: ='出金明細【18期】'!AD139 -> 0
B141: 44477 | C141: =SUM(C140+D141-H141) -> -87141161 | D141: =E141+F141+G141 -> 0 | E141: ='入金明細【18期】 '!D140 -> 0 | F141: ='入金明細【18期】 '!M140 -> 0 | G141: ='入金明細【18期】 '!T140 -> 0 | H141: =I141+J141+K141 -> 0 | I141: ='出金明細【18期】'!D140 -> 0 | J141: ='出金明細【18期】'!M140 -> 0 | K141: ='出金明細【18期】'!AD140 -> 0
B142: 44478 | C142: =SUM(C141+D142-H142) -> -87141161 | D142: =E142+F142+G142 -> 0 | E142: ='入金明細【18期】 '!D141 -> 0 | F142: ='入金明細【18期】 '!M141 -> 0 | G142: ='入金明細【18期】 '!T141 -> 0 | H142: =I142+J142+K142 -> 0 | I142: ='出金明細【18期】'!D141 -> 0 | J142: ='出金明細【18期】'!M141 -> 0 | K142: ='出金明細【18期】'!AD141 -> 0
B143: 44479 | C143: =SUM(C142+D143-H143) -> -87141161 | D143: =E143+F143+G143 -> 0 | E143: ='入金明細【18期】 '!D142 -> 0 | F143: ='入金明細【18期】 '!M142 -> 0 | G143: ='入金明細【18期】 '!T142 -> 0 | H143: =I143+J143+K143 -> 0 | I143: ='出金明細【18期】'!D142 -> 0 | J143: ='出金明細【18期】'!M142 -> 0 | K143: ='出金明細【18期】'!AD142 -> 0
B144: 44480 | C144: =SUM(C143+D144-H144) -> -87141161 | D144: =E144+F144+G144 -> 0 | E144: ='入金明細【18期】 '!D143 -> 0 | F144: ='入金明細【18期】 '!M143 -> 0 | G144: ='入金明細【18期】 '!T143 -> 0 | H144: =I144+J144+K144 -> 0 | I144: ='出金明細【18期】'!D143 -> 0 | J144: ='出金明細【18期】'!M143 -> 0 | K144: ='出金明細【18期】'!AD143 -> 0
B145: 44481 | C145: =SUM(C144+D145-H145) -> -87141161 | D145: =E145+F145+G145 -> 0 | E145: ='入金明細【18期】 '!D144 -> 0 | F145: ='入金明細【18期】 '!M144 -> 0 | G145: ='入金明細【18期】 '!T144 -> 0 | H145: =I145+J145+K145 -> 0 | I145: ='出金明細【18期】'!D144 -> 0 | J145: ='出金明細【18期】'!M144 -> 0 | K145: ='出金明細【18期】'!AD144 -> 0
B146: 44482 | C146: =SUM(C145+D146-H146) -> -87141161 | D146: =E146+F146+G146 -> 0 | E146: ='入金明細【18期】 '!D145 -> 0 | F146: ='入金明細【18期】 '!M145 -> 0 | G146: ='入金明細【18期】 '!T145 -> 0 | H146: =I146+J146+K146 -> 0 | I146: ='出金明細【18期】'!D145 -> 0 | J146: ='出金明細【18期】'!M145 -> 0 | K146: ='出金明細【18期】'!AD145 -> 0
... B164: 44500 | C164: =SUM(C163+D164-H164) -> -87341161 | D164: =E164+F164+G164 -> 0 | E164: ='入金明細【18期】 '!D163 -> 0 | F164: ='入金明細【18期】 '!M163 -> 0 | G164: ='入金明細【18期】 '!T163 -> 0 | H164: =I164+J164+K164 -> 0 | I164: ='出金明細【18期】'!D163 -> 0 | J164: ='出金明細【18期】'!M163 -> 0 | K164: ='出金明細【18期】'!AD163 -> 0
B165: 10月合計 | C165: =SUM(D165-H165) -> -200000 | D165: =SUM(D134:D164) -> 0 | H165: =SUM(H134:H164) -> 200000
B166: 累計 | C166: =SUM(D166-H166) -> -73929085 | D166: =D133+D165 -> 0 | H166: =H133+H165 -> 73929085
B167: 44501 | C167: =SUM(C164+D167-H167) -> -87341161 | D167: =E167+F167+G167 -> 0 | E167: ='入金明細【18期】 '!D165 -> 0 | F167: ='入金明細【18期】 '!M165 -> 0 | G167: ='入金明細【18期】 '!T165 -> 0 | H167: =I167+J167+K167 -> 0 | I167: ='出金明細【18期】'!D165 -> 0 | J167: ='出金明細【18期】'!M165 -> 0 | K167: ='出金明細【18期】'!AD165 -> 0
B168: 44502 | C168: =SUM(C167+D168-H168) -> -87341161 | D168: =E168+F168+G168 -> 0 | E168: ='入金明細【18期】 '!D166 -> 0 | F168: ='入金明細【18期】 '!M166 -> 0 | G168: ='入金明細【18期】 '!T166 -> 0 | H168: =I168+J168+K168 -> 0 | I168: ='出金明細【18期】'!D166 -> 0 | J168: ='出金明細【18期】'!M166 -> 0 | K168: ='出金明細【18期】'!AD166 -> 0
B169: 44503 | C169: =SUM(C168+D169-H169) -> -87341161 | D169: =E169+F169+G169 -> 0 | E169: ='入金明細【18期】 '!D167 -> 0 | F169: ='入金明細【18期】 '!M167 -> 0 | G169: ='入金明細【18期】 '!T167 -> 0 | H169: =I169+J169+K169 -> 0 | I169: ='出金明細【18期】'!D167 -> 0 | J169: ='出金明細【18期】'!M167 -> 0 | K169: ='出金明細【18期】'!AD167 -> 0
B170: 44504 | C170: =SUM(C169+D170-H170) -> -87341161 | D170: =E170+F170+G170 -> 0 | E170: ='入金明細【18期】 '!D168 -> 0 | F170: ='入金明細【18期】 '!M168 -> 0 | G170: ='入金明細【18期】 '!T168 -> 0 | H170: =I170+J170+K170 -> 0 | I170: ='出金明細【18期】'!D168 -> 0 | J170: ='出金明細【18期】'!M168 -> 0 | K170: ='出金明細【18期】'!AD168 -> 0
B171: 44505 | C171: =SUM(C170+D171-H171) -> -87341161 | D171: =E171+F171+G171 -> 0 | E171: ='入金明細【18期】 '!D169 -> 0 | F171: ='入金明細【18期】 '!M169 -> 0 | G171: ='入金明細【18期】 '!T169 -> 0 | H171: =I171+J171+K171 -> 0 | I171: ='出金明細【18期】'!D169 -> 0 | J171: ='出金明細【18期】'!M169 -> 0 | K171: ='出金明細【18期】'!AD169 -> 0
B172: 44506 | C172: =SUM(C171+D172-H172) -> -87341161 | D172: =E172+F172+G172 -> 0 | E172: ='入金明細【18期】 '!D170 -> 0 | F172: ='入金明細【18期】 '!M170 -> 0 | G172: ='入金明細【18期】 '!T170 -> 0 | H172: =I172+J172+K172 -> 0 | I172: ='出金明細【18期】'!D170 -> 0 | J172: ='出金明細【18期】'!M170 -> 0 | K172: ='出金明細【18期】'!AD170 -> 0
B173: 44507 | C173: =SUM(C172+D173-H173) -> -87341161 | D173: =E173+F173+G173 -> 0 | E173: ='入金明細【18期】 '!D171 -> 0 | F173: ='入金明細【18期】 '!M171 -> 0 | G173: ='入金明細【18期】 '!T171 -> 0 | H173: =I173+J173+K173 -> 0 | I173: ='出金明細【18期】'!D171 -> 0 | J173: ='出金明細【18期】'!M171 -> 0 | K173: ='出金明細【18期】'!AD171 -> 0
B174: 44508 | C174: =SUM(C173+D174-H174) -> -87341161 | D174: =E174+F174+G174 -> 0 | E174: ='入金明細【18期】 '!D172 -> 0 | F174: ='入金明細【18期】 '!M172 -> 0 | G174: ='入金明細【18期】 '!T172 -> 0 | H174: =I174+J174+K174 -> 0 | I174: ='出金明細【18期】'!D172 -> 0 | J174: ='出金明細【18期】'!M172 -> 0 | K174: ='出金明細【18期】'!AD172 -> 0
B175: 44509 | C175: =SUM(C174+D175-H175) -> -87341161 | D175: =E175+F175+G175 -> 0 | E175: ='入金明細【18期】 '!D173 -> 0 | F175: ='入金明細【18期】 '!M173 -> 0 | G175: ='入金明細【18期】 '!T173 -> 0 | H175: =I175+J175+K175 -> 0 | I175: ='出金明細【18期】'!D173 -> 0 | J175: ='出金明細【18期】'!M173 -> 0 | K175: ='出金明細【18期】'!AD173 -> 0
B176: 44510 | C176: =SUM(C175+D176-H176) -> -87341161 | D176: =E176+F176+G176 -> 0 | E176: ='入金明細【18期】 '!D174 -> 0 | F176: ='入金明細【18期】 '!M174 -> 0 | G176: ='入金明細【18期】 '!T174 -> 0 | H176: =I176+J176+K176 -> 0 | I176: ='出金明細【18期】'!D174 -> 0 | J176: ='出金明細【18期】'!M174 -> 0 | K176: ='出金明細【18期】'!AD174 -> 0
B177: 44511 | C177: =SUM(C176+D177-H177) -> -87341161 | D177: =E177+F177+G177 -> 0 | E177: ='入金明細【18期】 '!D175 -> 0 | F177: ='入金明細【18期】 '!M175 -> 0 | G177: ='入金明細【18期】 '!T175 -> 0 | H177: =I177+J177+K177 -> 0 | I177: ='出金明細【18期】'!D175 -> 0 | J177: ='出金明細【18期】'!M175 -> 0 | K177: ='出金明細【18期】'!AD175 -> 0
B178: 44512 | C178: =SUM(C177+D178-H178) -> -87341161 | D178: =E178+F178+G178 -> 0 | E178: ='入金明細【18期】 '!D176 -> 0 | F178: ='入金明細【18期】 '!M176 -> 0 | G178: ='入金明細【18期】 '!T176 -> 0 | H178: =I178+J178+K178 -> 0 | I178: ='出金明細【18期】'!D176 -> 0 | J178: ='出金明細【18期】'!M176 -> 0 | K178: ='出金明細【18期】'!AD176 -> 0
B179: 44513 | C179: =SUM(C178+D179-H179) -> -87341161 | D179: =E179+F179+G179 -> 0 | E179: ='入金明細【18期】 '!D177 -> 0 | F179: ='入金明細【18期】 '!M177 -> 0 | G179: ='入金明細【18期】 '!T177 -> 0 | H179: =I179+J179+K179 -> 0 | I179: ='出金明細【18期】'!D177 -> 0 | J179: ='出金明細【18期】'!M177 -> 0 | K179: ='出金明細【18期】'!AD177 -> 0
... B196: 44530 | C196: =SUM(C195+D196-H196) -> -87541161 | D196: =E196+F196+G196 -> 0 | E196: ='入金明細【18期】 '!D194 -> 0 | F196: ='入金明細【18期】 '!M194 -> 0 | G196: ='入金明細【18期】 '!T194 -> 0 | H196: =I196+J196+K196 -> 0 | I196: ='出金明細【18期】'!D194 -> 0 | J196: ='出金明細【18期】'!M194 -> 0 | K196: ='出金明細【18期】'!AD194 -> 0
B197: 1１月合計 | C197: =SUM(D197-H197) -> -200000 | D197: =SUM(D167:D196) -> 0 | H197: =SUM(H167:H196) -> 200000
B198: 累計 | C198: =SUM(D198-H198) -> -74129085 | D198: =D166+D197 -> 0 | H198: =H166+H197 -> 74129085
B199: 44531 | C199: =SUM(C196+D199-H199) -> -87541161 | D199: =E199+F199+G199 -> 0 | E199: ='入金明細【18期】 '!D196 -> 0 | F199: ='入金明細【18期】 '!M196 -> 0 | G199: ='入金明細【18期】 '!T196 -> 0 | H199: =I199+J199+K199 -> 0 | I199: ='出金明細【18期】'!D196 -> 0 | J199: ='出金明細【18期】'!M196 -> 0 | K199: ='出金明細【18期】'!AD196 -> 0
...

Sheet 入金明細【18期】 
C1: ２０２5年６月‐２０２6年５月入金
C2: 入金日次 | D2: 金融小計 | E2: 金融機関関連 | M2: 保険小計 | N2: 保険関連 | T2: お客様小計 | U2: お客様関連
B3: 44348 | C3: =D3+M3+T3 -> 0 | D3: =F3+H3+J3+L3 -> 0 | M3: =O3+Q3+S3 -> 0 | T3: =V3+X3+Z3+AB3+AD3+AF3+AH3+AJ3+AV3+AL3+AN3+AP3+AR3+'入金明細【18期】 '!AT3 -> 0
B4: 44349 | C4: =D4+M4+T4 -> 0 | D4: =F4+H4+J4+L4 -> 0 | M4: =O4+Q4+S4 -> 0 | T4: =V4+X4+Z4+AB4+AD4+AF4+AH4+AJ4+AV4+AL4+AN4+AP4+AR4+AT4 -> 0
B5: 45446 | C5: =D5+M5+T5 -> 0 | D5: =F5+H5+J5+L5 -> 0 | M5: =O5+Q5+S5 -> 0 | T5: =V5+X5+Z5+AB5+AD5+AF5+AH5+AJ5+AV5+AL5+AN5+AP5+AR5+AT5 -> 0
B6: 44351 | C6: =D6+M6+T6 -> 0 | D6: =F6+H6+J6+L6 -> 0 | M6: =O6+Q6+S6 -> 0 | T6: =V6+X6+Z6+AB6+AD6+AF6+AH6+AJ6+AV6+AL6+AN6+AP6+AR6+AT6 -> 0
B7: 44352 | C7: =D7+M7+T7 -> 0 | D7: =F7+H7+J7+L7 -> 0 | M7: =O7+Q7+S7 -> 0 | T7: =V7+X7+Z7+AB7+AD7+AF7+AH7+AJ7+AV7+AL7+AN7+AP7+AR7+AT7 -> 0
B8: 44353 | C8: =D8+M8+T8 -> 0 | D8: =F8+H8+J8+L8 -> 0 | M8: =O8+Q8+S8 -> 0 | T8: =V8+X8+Z8+AB8+AD8+AF8+AH8+AJ8+AV8+AL8+AN8+AP8+AR8+AT8 -> 0
B9: 44354 | C9: =D9+M9+T9 -> 0 | D9: =F9+H9+J9+L9 -> 0 | M9: =O9+Q9+S9 -> 0 | T9: =V9+X9+Z9+AB9+AD9+AF9+AH9+AJ9+AV9+AL9+AN9+AP9+AR9+AT9 -> 0
B10: 45816 | C10: =D10+M10+T10 -> 0 | D10: =F10+H10+J10+L10 -> 0 | M10: =O10+Q10+S10 -> 0 | T10: =V10+X10+Z10+AB10+AD10+AF10+AH10+AJ10+AV10+AL10+AN10+AP10+AR10+AT10 -> 0
B11: 44356 | C11: =D11+M11+T11 -> 0 | D11: =F11+H11+J11+L11 -> 0 | M11: =O11+Q11+S11 -> 0 | T11: =V11+X11+Z11+AB11+AD11+AF11+AH11+AJ11+AV11+AL11+AN11+AP11+AR11+AT11 -> 0
B12: 44357 | C12: =D12+M12+T12 -> 0 | D12: =F12+H12+J12+L12 -> 0 | M12: =O12+Q12+S12 -> 0 | T12: =V12+X12+Z12+AB12+AD12+AF12+AH12+AJ12+AV12+AL12+AN12+AP12+AR12+AT12 -> 0
B13: 44358 | C13: =D13+M13+T13 -> 0 | D13: =F13+H13+J13+L13 -> 0 | M13: =O13+Q13+S13 -> 0 | T13: =V13+X13+Z13+AB13+AD13+AF13+AH13+AJ13+AV13+AL13+AN13+AP13+AR13+AT13 -> 0
B14: 44359 | C14: =D14+M14+T14 -> 0 | D14: =F14+H14+J14+L14 -> 0 | M14: =O14+Q14+S14 -> 0 | T14: =V14+X14+Z14+AB14+AD14+AF14+AH14+AJ14+AV14+AL14+AN14+AP14+AR14+AT14 -> 0
B15: 44360 | C15: =D15+M15+T15 -> 0 | D15: =F15+H15+J15+L15 -> 0 | M15: =O15+Q15+S15 -> 0 | T15: =V15+X15+Z15+AB15+AD15+AF15+AH15+AJ15+AV15+AL15+AN15+AP15+AR15+AT15 -> 0
... B32: 44377 | C32: =D32+M32+T32 -> 0 | D32: =F32+H32+J32+L32 -> 0 | M32: =O32+Q32+S32 -> 0 | T32: =V32+X32+Z32+AB32+AD32+AF32+AH32+AJ32+AV32+AL32+AN32+AP32+AR32+AT32 -> 0
B33: ６月合計 | C33: =D33+M33+T33 -> 0 | D33: =SUM(D2:D32) -> 0 | M33: =SUM(M2:M32) -> 0 | T33: =SUM(T3:T32) -> 0
B34: 未確定 | C34: =D34+M34+T34 -> 0 | T34: =V34+X34+Z34+AB34+AD34+AF34+AH34+AJ34+AV34 -> 0
B35: 44378 | C35: =D35+M35+T35 -> 0 | D35: =F35+H35+J35+L35 -> 0 | M35: =O35+Q35+S35 -> 0 | T35: =V35+X35+Z35+AB35+AD35+AF35+AH35+AJ35+AV35+AL35+AN35+AP35+AR35+AT35 -> 0
B36: 45109 | C36: =D36+M36+T36 -> 0 | D36: =F36+H36+J36+L36 -> 0 | M36: =O36+Q36+S36 -> 0 | T36: =V36+X36+Z36+AB36+AD36+AF36+AH36+AJ36+AV36+AL36+AN36+AP36+AR36+AT36 -> 0
B37: 45110 | C37: =D37+M37+T37 -> 0 | D37: =F37+H37+J37+L37 -> 0 | M37: =O37+Q37+S37 -> 0 | T37: =V37+X37+Z37+AB37+AD37+AF37+AH37+AJ37+AV37+AL37+AN37+AP37+AR37+AT37 -> 0
B38: 45111 | C38: =D38+M38+T38 -> 0 | D38: =F38+H38+J38+L38 -> 0 | M38: =O38+Q38+S38 -> 0 | T38: =V38+X38+Z38+AB38+AD38+AF38+AH38+AJ38+AV38+AL38+AN38+AP38+AR38+AT38 -> 0
B39: 45112 | C39: =D39+M39+T39 -> 0 | D39: =F39+H39+J39+L39 -> 0 | M39: =O39+Q39+S39 -> 0 | T39: =V39+X39+Z39+AB39+AD39+AF39+AH39+AJ39+AV39+AL39+AN39+AP39+AR39+AT39 -> 0
B40: 45113 | C40: =D40+M40+T40 -> 0 | D40: =F40+H40+J40+L40 -> 0 | M40: =O40+Q40+S40 -> 0 | T40: =V40+X40+Z40+AB40+AD40+AF40+AH40+AJ40+AV40+AL40+AN40+AP40+AR40+AT40 -> 0
B41: 45114 | C41: =D41+M41+T41 -> 0 | D41: =F41+H41+J41+L41 -> 0 | M41: =O41+Q41+S41 -> 0 | T41: =V41+X41+Z41+AB41+AD41+AF41+AH41+AJ41+AV41+AL41+AN41+AP41+AR41+AT41 -> 0
B42: 45115 | C42: =D42+M42+T42 -> 0 | D42: =F42+H42+J42+L42 -> 0 | M42: =O42+Q42+S42 -> 0 | T42: =V42+X42+Z42+AB42+AD42+AF42+AH42+AJ42+AV42+AL42+AN42+AP42+AR42+AT42 -> 0
B43: 45116 | C43: =D43+M43+T43 -> 0 | D43: =F43+H43+J43+L43 -> 0 | M43: =O43+Q43+S43 -> 0 | T43: =V43+X43+Z43+AB43+AD43+AF43+AH43+AJ43+AV43+AL43+AN43+AP43+AR43+AT43 -> 0
B44: 45117 | C44: =D44+M44+T44 -> 0 | D44: =F44+H44+J44+L44 -> 0 | M44: =O44+Q44+S44 -> 0 | T44: =V44+X44+Z44+AB44+AD44+AF44+AH44+AJ44+AV44+AL44+AN44+AP44+AR44+AT44 -> 0
B45: 45118 | C45: =D45+M45+T45 -> 0 | D45: =F45+H45+J45+L45 -> 0 | M45: =O45+Q45+S45 -> 0 | T45: =V45+X45+Z45+AB45+AD45+AF45+AH45+AJ45+AV45+AL45+AN45+AP45+AR45+AT45 -> 0
B46: 45119 | C46: =D46+M46+T46 -> 0 | D46: =F46+H46+J46+L46 -> 0 | M46: =O46+Q46+S46 -> 0 | T46: =V46+X46+Z46+AB46+AD46+AF46+AH46+AJ46+AV46+AL46+AN46+AP46+AR46+AT46 -> 0
... B65: 45138 | C65: =D65+M65+T65 -> 0 | D65: =F65+H65+J65+L65 -> 0 | M65: =O65+Q65+S65 -> 0 | T65: =V65+X65+Z65+AB65+AD65+AF65+AH65+AJ65+AV65+AL65+AN65+AP65+AR65+AT65 -> 0
B66: ７月合計 | C66: =D66+M66+T66 -> 0 | D66: =SUM(D35:D65) -> 0 | M66: =SUM(M35:M65) -> 0 | T66: =SUM(T35:T65) -> 0
B67: 未確定 | C67: =D67+M67+T67 -> 0 | T67: =V67+X67+Z67+AB67+AD67+AF67+AH67+AJ67+AV67 -> 0
B68: 45139 | C68: =D68+M68+T68 -> 0 | D68: =F68+H68+J68+L68 -> 0 | M68: =O68 | T68: =V68+X68+Z68+AB68+AD68+AF68+AH68+AJ68+AV68 -> 0
B69: 45140 | C69: =D69+M69+T69 -> 0 | D69: =F69+H69+J69+L69 -> 0 | M69: =O69 | T69: =V69+X69+Z69+AB69+AD69+AF69+AH69+AJ69+AV69 -> 0
B70: 45141 | C70: =D70+M70+T70 -> 0 | D70: =F70+H70+J70+L70 -> 0 | M70: =O70 | T70: =V70+X70+Z70+AB70+AD70+AF70+AH70+AJ70+AV70 -> 0
B71: 45142 | C71: =D71+M71+T71 -> 0 | D71: =F71+H71+J71+L71 -> 0 | M71: =O71 | T71: =V71+X71+Z71+AB71+AD71+AF71+AH71+AJ71+AV71 -> 0
B72: 45143 | C72: =D72+M72+T72 -> 0 | D72: =F72+H72+J72+L72 -> 0 | M72: =O72+Q72 -> 0 | T72: =V72+X72+Z72+AB72+AD72+AF72+AH72+AJ72+AV72 -> 0
B73: 45144 | C73: =D73+M73+T73 -> 0 | D73: =F73+H73+J73+L73 -> 0 | M73: =O73+Q73 -> 0 | T73: =V73+X73+Z73+AB73+AD73+AF73+AH73+AJ73+AV73 -> 0
B74: 45145 | C74: =D74+M74+T74 -> 0 | D74: =F74+H74+J74+L74 -> 0 | M74: =O74+Q74 -> 0 | T74: =V74+X74+Z74+AB74+AD74+AF74+AH74+AJ74+AV74 -> 0
B75: 45146 | C75: =D75+M75+T75 -> 0 | D75: =F75+H75+J75+L75 -> 0 | M75: =O75+Q75 -> 0 | T75: =V75+X75+Z75+AB75+AD75+AF75+AH75+AJ75+AV75 -> 0
B76: 45147 | C76: =D76+M76+T76 -> 0 | D76: =F76+H76+J76+L76 -> 0 | M76: =O76+Q76 -> 0 | T76: =V76+X76+Z76+AB76+AD76+AF76+AH76+AJ76+AV76 -> 0
B77: 45148 | C77: =D77+M77+T77 -> 0 | D77: =F77+H77+J77+L77 -> 0 | M77: =O77+Q77 -> 0 | T77: =V77+X77+Z77+AB77+AD77+AF77+AH77+AJ77+AV77 -> 0
B78: 45149 | C78: =D78+M78+T78 -> 0 | D78: =F78+H78+J78+L78 -> 0 | M78: =O78+Q78 -> 0 | T78: =V78+X78+Z78+AB78+AD78+AF78+AH78+AJ78+AV78 -> 0
B79: 45150 | C79: =D79+M79+T79 -> 0 | D79: =F79+H79+J79+L79 -> 0 | M79: =O79+Q79 -> 0 | T79: =V79+X79+Z79+AB79+AD79+AF79+AH79+AJ79+AV79 -> 0
B80: 45151 | C80: =D80+M80+T80 -> 0 | D80: =F80+H80+J80+L80 -> 0 | M80: =O80+Q80 -> 0 | T80: =V80+X80+Z80+AB80+AD80+AF80+AH80+AJ80+AV80 -> 0
B81: 45152 | C81: =D81+M81+T81 -> 0 | D81: =F81+H81+J81+L81 -> 0 | M81: =O81+Q81 -> 0 | T81: =V81+X81+Z81+AB81+AD81+AF81+AH81+AJ81+AV81 -> 0
B82: 45153 | C82: =D82+M82+T82 -> 0 | D82: =F82+H82+J82+L82 -> 0 | M82: =O82+Q82 -> 0 | T82: =V82+X82+Z82+AB82+AD82+AF82+AH82+AJ82+AV82 -> 0
B83: 45154 | C83: =D83+M83+T83 -> 0 | D83: =F83+H83+J83+L83 -> 0 | M83: =O83+Q83 -> 0 | T83: =V83+X83+Z83+AB83+AD83+AF83+AH83+AJ83+AV83 -> 0
... B98: 45169 | C98: =D98+M98+T98 -> 0 | D98: =F98+H98+J98+L98 -> 0 | M98: =O98+Q98 -> 0 | T98: =V98+X98+Z98+AB98+AD98+AF98+AH98+AJ98+AV98 -> 0
B99: ８月合計 | C99: =D99+M99+T99 -> 0 | D99: =SUM(D68:D98) -> 0 | M99: =SUM(M68:M98) -> 0 | T99: =SUM(T68:T98) -> 0
B100: 未確定
B101: 44440 | C101: =D101+M101+T101 -> 0 | D101: =F101+H101+J101+L101 -> 0 | M101: =O101+Q101+S101 -> 0 | T101: =V101+X101+Z101+AB101+AD101+AF101+AH101+AJ101+AV101 -> 0
B102: 44441 | C102: =D102+M102+T102 -> 0 | D102: =F102+H102+J102+L102 -> 0 | M102: =O102+Q102+S102 -> 0 | T102: =V102+X102+Z102+AB102+AD102+AF102+AH102+AJ102+AV102 -> 0
B103: 44442 | C103: =D103+M103+T103 -> 0 | D103: =F103+H103+J103+L103 -> 0 | M103: =O103+Q103+S103 -> 0 | T103: =V103+X103+Z103+AB103+AD103+AF103+AH103+AJ103+AV103 -> 0
B104: 44443 | C104: =D104+M104+T104 -> 0 | D104: =F104+H104+J104+L104 -> 0 | M104: =O104+Q104+S104 -> 0 | T104: =V104+X104+Z104+AB104+AD104+AF104+AH104+AJ104+AV104 -> 0
B105: 44444 | C105: =D105+M105+T105 -> 0 | D105: =F105+H105+J105+L105 -> 0 | M105: =O105+Q105+S105 -> 0 | T105: =V105+X105+Z105+AB105+AD105+AF105+AH105+AJ105+AV105 -> 0
B106: 44445 | C106: =D106+M106+T106 -> 0 | D106: =F106+H106+J106+L106 -> 0 | M106: =O106+Q106+S106 -> 0 | T106: =V106+X106+Z106+AB106+AD106+AF106+AH106+AJ106+AV106 -> 0
B107: 44446 | C107: =D107+M107+T107 -> 0 | D107: =F107+H107+J107+L107 -> 0 | M107: =O107+Q107+S107 -> 0 | T107: =V107+X107+Z107+AB107+AD107+AF107+AH107+AJ107+AV107 -> 0
B108: 44447 | C108: =D108+M108+T108 -> 0 | D108: =F108+H108+J108+L108 -> 0 | M108: =O108+Q108+S108 -> 0 | T108: =V108+X108+Z108+AB108+AD108+AF108+AH108+AJ108+AV108 -> 0
B109: 44448 | C109: =D109+M109+T109 -> 0 | D109: =F109+H109+J109+L109 -> 0 | M109: =O109+Q109+S109 -> 0 | T109: =V109+X109+Z109+AB109+AD109+AF109+AH109+AJ109+AV109 -> 0
B110: 44449 | C110: =D110+M110+T110 -> 0 | D110: =F110+H110+J110+L110 -> 0 | M110: =O110+Q110+S110 -> 0 | T110: =V110+X110+Z110+AB110+AD110+AF110+AH110+AJ110+AV110 -> 0
B111: 44450 | C111: =D111+M111+T111 -> 0 | D111: =F111+H111+J111+L111 -> 0 | M111: =O111+Q111+S111 -> 0 | T111: =V111+X111+Z111+AB111+AD111+AF111+AH111+AJ111+AV111 -> 0
B112: 44451 | C112: =D112+M112+T112 -> 0 | D112: =F112+H112+J112+L112 -> 0 | M112: =O112+Q112+S112 -> 0 | T112: =V112+X112+Z112+AB112+AD112+AF112+AH112+AJ112+AV112 -> 0
... B129: 44468 | C129: =D129+M129+T129 -> 0 | D129: =F129+H129+J129+L129 -> 0 | M129: =O129+Q129+S129 -> 0 | T129: =V129+X129+Z129+AB129+AD129+AF129+AH129+AJ129+AV129 -> 0
B130: 44469 | C130: =D130+M130+T130 -> 0 | D130: =F130+H130+J130+L130 -> 0 | M130: =O130+Q130+S130 -> 0 | T130: =V130+X130+Z130+AB130+AD130+AF130+AH130+AJ130+AV130+AL130 -> 0
B131: 9月合計 | C131: =D131+M131+T131 -> 0 | D131: =SUM(D101:D130) -> 0 | M131: =SUM(M101:M130) -> 0 | T131: =SUM(T101:T130) -> 0
B132: 未確定 | C132: =D132+M132+T132 -> 0
B133: 44470 | C133: =D133+M133+T133 -> 0 | D133: =F133+H133+J133+L133 -> 0 | M133: =O133 | T133: =V133+X133+Z133+AB133+AD133+AF133+AH133+AJ133+AV133 -> 0
B134: 44471 | C134: =D134+M134+T134 -> 0 | D134: =F134+H134+J134+L134 -> 0 | M134: =O134 | T134: =V134+X134+Z134+AB134+AD134+AF134+AH134+AJ134+AV134 -> 0
B135: 44472 | C135: =D135+M135+T135 -> 0 | D135: =F135+H135+J135+L135 -> 0 | M135: =O135+Q135+S135 -> 0 | T135: =V135+X135+Z135+AB135+AD135+AF135+AH135+AJ135+AV135 -> 0
B136: 44473 | C136: =D136+M136+T136 -> 0 | D136: =F136+H136+J136+L136 -> 0 | M136: =O136+Q136+S136 -> 0 | T136: =V136+X136+Z136+AB136+AD136+AF136+AH136+AJ136+AV136 -> 0
B137: 44474 | C137: =D137+M137+T137 -> 0 | D137: =F137+H137+J137+L137 -> 0 | M137: =O137+Q137+S137 -> 0 | T137: =V137+X137+Z137+AB137+AD137+AF137+AH137+AJ137+AV137 -> 0
B138: 44475 | C138: =D138+M138+T138 -> 0 | D138: =F138+H138+J138+L138 -> 0 | M138: =O138+Q138+S138 -> 0 | T138: =V138+X138+Z138+AB138+AD138+AF138+AH138+AJ138+AV138 -> 0
B139: 44476 | C139: =D139+M139+T139 -> 0 | D139: =F139+H139+J139+L139 -> 0 | M139: =O139+Q139+S139 -> 0 | T139: =V139+X139+Z139+AB139+AD139+AF139+AH139+AJ139+AV139 -> 0
B140: 44477 | C140: =D140+M140+T140 -> 0 | D140: =F140+H140+J140+L140 -> 0 | M140: =O140+Q140+S140 -> 0 | T140: =V140+X140+Z140+AB140+AD140+AF140+AH140+AJ140+AV140 -> 0
B141: 44478 | C141: =D141+M141+T141 -> 0 | D141: =F141+H141+J141+L141 -> 0 | M141: =O141+Q141 -> 0 | T141: =V141+X141+Z141+AB141+AD141+AF141+AH141+AJ141+AV141 -> 0
B142: 44479 | C142: =D142+M142+T142 -> 0 | D142: =F142+H142+J142+L142 -> 0 | M142: =O142+Q142 -> 0 | T142: =V142+X142+Z142+AB142+AD142+AF142+AH142+AJ142+AV142 -> 0
B143: 44480 | C143: =D143+M143+T143 -> 0 | D143: =F143+H143+J143+L143 -> 0 | M143: =O143+Q143 -> 0 | T143: =V143+X143+Z143+AB143+AD143+AF143+AH143+AJ143+AV143 -> 0
B144: 44481 | C144: =D144+M144+T144 -> 0 | D144: =F144+H144+J144+L144 -> 0 | M144: =O144+Q144 -> 0 | T144: =V144+X144+Z144+AB144+AD144+AF144+AH144+AJ144+AV144 -> 0
B145: 44482 | C145: =D145+M145+T145 -> 0 | D145: =F145+H145+J145+L145 -> 0 | M145: =O145+Q145 -> 0 | T145: =V145+X145+Z145+AB145+AD145+AF145+AH145+AJ145+AV145 -> 0
B146: 44483 | C146: =D146+M146+T146 -> 0 | D146: =F146+H146+J146+L146 -> 0 | M146: =O146+Q146 -> 0 | T146: =V146+X146+Z146+AB146+AD146+AF146+AH146+AJ146+AV146 -> 0
B147: 44484 | C147: =D147+M147+T147 -> 0 | D147: =F147+H147+J147+L147 -> 0 | M147: =O147+Q147 -> 0 | T147: =V147+X147+Z147+AB147+AD147+AF147+AH147+AJ147+AV147 -> 0
B148: 44485 | C148: =D148+M148+T148 -> 0 | D148: =F148+H148+J148+L148 -> 0 | M148: =O148+Q148+S148 -> 0 | T148: =V148+X148+Z148+AB148+AD148+AF148+AH148+AJ148+AV148 -> 0
B149: 44486 | C149: =D149+M149+T149 -> 0 | D149: =F149+H149+J149+L149 -> 0 | M149: =O149+Q149+S149 -> 0 | T149: =V149+X149+Z149+AB149+AD149+AF149+AH149+AJ149+AV149 -> 0
B150: 44487 | C150: =D150+M150+T150 -> 0 | D150: =F150+H150+J150+L150 -> 0 | M150: =O150+Q150 -> 0 | T150: =V150+X150+Z150+AB150+AD150+AF150+AH150+AJ150+AV150 -> 0
B151: 44488 | C151: =D151+M151+T151 -> 0 | D151: =F151+H151+J151+L151 -> 0 | M151: =O151+Q151 -> 0 | T151: =V151+X151+Z151+AB151+AD151+AF151+AH151+AJ151+AV151 -> 0
B152: 44489 | C152: =D152+M152+T152 -> 0 | D152: =F152+H152+J152+L152 -> 0 | M152: =O152+Q152 -> 0 | T152: =V152+X152+Z152+AB152+AD152+AF152+AH152+AJ152+AV152 -> 0
B153: 44490 | C153: =D153+M153+T153 -> 0 | D153: =F153+H153+J153+L153 -> 0 | M153: =O153+Q153 -> 0 | T153: =V153+X153+Z153+AB153+AD153+AF153+AH153+AJ153+AV153 -> 0
B154: 44491 | C154: =D154+M154+T154 -> 0 | D154: =F154+H154+J154+L154 -> 0 | M154: =O154+Q154 -> 0 | T154: =V154+X154+Z154+AB154+AD154+AF154+AH154+AJ154+AV154 -> 0
B155: 44492 | C155: =D155+M155+T155 -> 0 | D155: =F155+H155+J155+L155 -> 0 | M155: =O155+Q155 -> 0 | T155: =V155+X155+Z155+AB155+AD155+AF155+AH155+AJ155+AV155 -> 0
B156: 44493 | C156: =D156+M156+T156 -> 0 | D156: =F156+H156+J156+L156 -> 0 | M156: =O156+Q156 -> 0 | T156: =V156+X156+Z156+AB156+AD156+AF156+AH156+AJ156+AV156 -> 0
B157: 44494 | C157: =D157+M157+T157 -> 0 | D157: =F157+H157+J157+L157 -> 0 | M157: =O157+Q157 -> 0 | T157: =V157+X157+Z157+AB157+AD157+AF157+AH157+AJ157+AV157 -> 0
B158: 44495 | C158: =D158+M158+T158 -> 0 | D158: =F158+H158+J158+L158 -> 0 | M158: =O158+Q158 -> 0 | T158: =V158+X158+Z158+AB158+AD158+AF158+AH158+AJ158+AV158 -> 0
B159: 44496 | C159: =D159+M159+T159 -> 0 | D159: =F159+H159+J159+L159 -> 0 | M159: =O159+Q159 -> 0 | T159: =V159+X159+Z159+AB159+AD159+AF159+AH159+AJ159+AV159 -> 0
B160: 44497 | C160: =D160+M160+T160 -> 0 | D160: =F160+H160+J160+L160 -> 0 | M160: =O160+Q160 -> 0 | T160: =V160+X160+Z160+AB160+AD160+AF160+AH160+AJ160+AV160 -> 0
B161: 44498 | C161: =D161+M161+T161 -> 0 | D161: =F161+H161+J161+L161 -> 0 | M161: =O161+Q161 -> 0 | T161: =V161+X161+Z161+AB161+AD161+AF161+AH161+AJ161+AV161 -> 0
B162: 44499 | C162: =D162+M162+T162 -> 0 | D162: =F162+H162+J162+L162 -> 0 | M162: =O162+Q162 -> 0 | T162: =V162+X162+Z162+AB162+AD162+AF162+AH162+AJ162+AV162 -> 0
B163: 44500 | C163: =D163+M163+T163 -> 0 | D163: =F163+H163+J163+L163 -> 0 | M163: =O163+Q163 -> 0 | T163: =V163+X163+Z163+AD163+AF163+AH163+AJ163+AV163+AL163+AN163+AP163+AR163+AT163+AV163+AB163 -> 0
B164: 10月合計 | C164: =D164+M164+T164 -> 0 | D164: =SUM(D134:D163) -> 0 | M164: =SUM(M133:M163) -> 0 | T164: =SUM(T134:T163) -> 0
...

Sheet 出金明細【18期】
C1: ２０２6年６月‐２０２7年５月出金
C2: 出金日次 | D2: 金融小計 | M2: 買掛小計 | AD2: 経費小計
B3: 44348 | C3: =D3+M3+AD3 -> 836496 | D3: =F3+H3+J3+L3 -> 0 | M3: =O3+Q3+S3+U3+W3+Y3+AA3+AC3 -> 0 | AD3: =AF3+AH3+AJ3+AL3+AN3+AP3+AR3+AT3+AV3+AX3+AZ3+BB3+BD3+BF3+BH3+BJ3+BL3+BN3+BP3+BR3+BT3+BV3+BX3+BZ3+CB3+CD3 -> 836496 | AE3: も）ﾄﾖﾀﾌｧｲﾅﾝｽ | AF3: 82196 | AG3: 自動車税 | AH3: 754300
B4: 44349 | C4: =D4+M4+AD4 -> 0 | D4: =F4+H4+J4+L4 -> 0 | M4: =O4+Q4+S4+U4+W4+Y4+AA4+AC4 -> 0 | AD4: =AF4+AH4+AJ4+AL4+AN4+AP4+AR4+AT4+AV4+AX4+AZ4+BB4+BD4+BF4+BH4+BJ4+BL4+BN4+BP4+BR4+BT4+BV4+BX4+BZ4+CB4+CD4 -> 0
B5: 45446 | C5: =D5+M5+AD5 -> 0 | D5: =F5+H5+J5+L5 -> 0 | M5: =O5+Q5+S5+U5+W5+Y5+AA5+AC5 -> 0 | AD5: =AF5+AH5+AJ5+AL5+AN5+AP5+AR5+AT5+AV5+AX5+AZ5+BB5+BD5+BF5+BH5+BJ5+BL5+BN5+BP5+BR5+BT5+BV5+BX5+BZ5+CB5+CD5 -> 0
B6: 44351 | C6: =D6+M6+AD6 -> 0 | D6: =F6+H6+J6+L6 -> 0 | M6: =O6+Q6+S6+U6+W6+Y6+AA6+AC6 -> 0 | AD6: =AF6+AH6+AJ6+AL6+AN6+AP6+AR6+AT6+AV6+AX6+AZ6+BB6+BD6+BF6+BH6+BJ6+BL6+BN6+BP6+BR6+BT6+BV6+BX6+BZ6+CB6+CD6 -> 0
B7: 44352 | C7: =D7+M7+AD7 -> 160800 | D7: =F7+H7+J7+L7 -> 0 | M7: =O7+Q7+S7+U7+W7+Y7+AA7+AC7 -> 0 | AD7: =AF7+AH7+AJ7+AL7+AN7+AP7+AR7+AT7+AV7+AX7+AZ7+BB7+BD7+BF7+BH7+BJ7+BL7+BN7+BP7+BR7+BT7+BV7+BX7+BZ7+CB7+CD7 -> 160800 | AE7: 笠)未来経営 | AF7: 88000 | AG7: 住民税 | AH7: 72800
B8: 44353 | C8: =D8+M8+AD8 -> 0 | D8: =F8+H8+J8+L8 -> 0 | M8: =O8+Q8+S8+U8+W8+Y8+AA8+AC8 -> 0 | AD8: =AF8+AH8+AJ8+AL8+AN8+AP8+AR8+AT8+AV8+AX8+AZ8+BB8+BD8+BF8+BH8+BJ8+BL8+BN8+BP8+BR8+BT8+BV8+BX8+BZ8+CB8+CD8 -> 0
B9: 44354 | C9: =D9+M9+AD9 -> 0 | D9: =F9+H9+J9+L9 -> 0 | M9: =O9+Q9+S9+U9+W9+Y9+AA9+AC9 -> 0 | AD9: =AF9+AH9+AJ9+AL9+AN9+AP9+AR9+AT9+AV9+AX9+AZ9+BB9+BD9+BF9+BH9+BJ9+BL9+BN9+BP9+BR9+BT9+BV9+BX9+BZ9+CB9+CD9 -> 0
B10: 45816 | C10: =D10+M10+AD10 -> 0 | D10: =F10+H10+J10+L10 -> 0 | M10: =O10+Q10+S10+U10+W10+Y10+AA10+AC10 -> 0 | AD10: =AF10+AH10+AJ10+AL10+AN10+AP10+AR10+AT10+AV10+AX10+AZ10+BB10+BD10+BF10+BH10+BJ10+BL10+BN10+BP10+BR10+BT10+BV10+BX10+BZ10+CB10+CD10 -> 0
B11: 44356 | C11: =D11+M11+AD11 -> 3706089 | D11: =F11+H11+J11+L11 -> 0 | M11: =O11+Q11+S11+U11+W11+Y11+AA11+AC11 -> 0 | AD11: =AF11+AH11+AJ11+AL11+AN11+AP11+AR11+AT11+AV11+AX11+AZ11+BB11+BD11+BF11+BH11+BJ11+BL11+BN11+BP11+BR11+BT11+BV11+BX11+BZ11+CB11+CD11 -> 3706089 | AE11: 銚子部長 | AF11: 100000 | AG11: 笠）ﾀﾞｲﾅｰｽﾞ | AH11: 177132 | AI11: も)整備ﾀﾞｲﾅｰｽｶｰﾄﾞ・ﾄﾗｽﾄｸﾗﾌﾞ | AJ11: 593649 | AK11: も)ﾀﾞｲﾅｰｽｶｰﾄﾞ・ﾄﾗｽﾄｸﾗﾌﾞ | AL11: 455500 | AM11: 田中賢治様 | AN11: 14600 | AO11: 給与 | AP11: 1123735 | AQ11: 高田自動車 | AR11: 512973 | AS11: 大中誠二 | AT11: =600000+128500 -> 728500
B12: 44357 | C12: =D12+M12+AD12 -> 0 | D12: =F12+H12+J12+L12 -> 0 | M12: =O12+Q12+S12+U12+W12+Y12+AA12+AC12 -> 0 | AD12: =AF12+AH12+AJ12+AL12+AN12+AP12+AR12+AT12+AV12+AX12+AZ12+BB12+BD12+BF12+BH12+BJ12+BL12+BN12+BP12+BR12+BT12+BV12+BX12+BZ12+CB12+CD12 -> 0
B13: 44358 | C13: =D13+M13+AD13 -> 0 | D13: =F13+H13+J13+L13 -> 0 | M13: =O13+Q13+S13+U13+W13+Y13+AA13+AC13 -> 0 | AD13: =AF13+AH13+AJ13+AL13+AN13+AP13+AR13+AT13+AV13+AX13+AZ13+BB13+BD13+BF13+BH13+BJ13+BL13+BN13+BP13+BR13+BT13+BV13+BX13+BZ13+CB13+CD13 -> 0
B14: 44359 | C14: =D14+M14+AD14 -> 0 | D14: =F14+H14+J14+L14 -> 0 | M14: =O14+Q14+S14+U14+W14+Y14+AA14+AC14 -> 0 | AD14: =AF14+AH14+AJ14+AL14+AN14+AP14+AR14+AT14+AV14+AX14+AZ14+BB14+BD14+BF14+BH14+BJ14+BL14+BN14+BP14+BR14+BT14+BV14+BX14+BZ14+CB14+CD14 -> 0
B15: 44360 | C15: =D15+M15+AD15 -> 0 | D15: =F15+H15+J15+L15 -> 0 | M15: =O15+Q15+S15+U15+W15+Y15+AA15+AC15 -> 0 | AD15: =AF15+AH15+AJ15+AL15+AN15+AP15+AR15+AT15+AV15+AX15+AZ15+BB15+BD15+BF15+BH15+BJ15+BL15+BN15+BP15+BR15+BT15+BV15+BX15+BZ15+CB15+CD15 -> 0
B16: 44361 | C16: =D16+M16+AD16 -> 0 | D16: =F16+H16+J16+L16 -> 0 | M16: =O16+Q16+S16+U16+W16+Y16+AA16+AC16 -> 0 | AD16: =AF16+AH16+AJ16+AL16+AN16+AP16+AR16+AT16+AV16+AX16+AZ16+BB16+BD16+BF16+BH16+BJ16+BL16+BN16+BP16+BR16+BT16+BV16+BX16+BZ16+CB16+CD16 -> 0
B17: 44362 | C17: =D17+M17+AD17 -> 0 | D17: =F17+H17+J17+L17 -> 0 | M17: =O17+Q17+S17+U17+W17+Y17+AA17+AC17 -> 0 | AD17: =AF17+AH17+AJ17+AL17+AN17+AP17+AR17+AT17+AV17+AX17+AZ17+BB17+BD17+BF17+BH17+BJ17+BL17+BN17+BP17+BR17+BT17+BV17+BX17+BZ17+CB17+CD17 -> 0
B18: 44363 | C18: =D18+M18+AD18 -> 0 | D18: =F18+H18+J18+L18 -> 0 | M18: =O18+Q18+S18+U18+W18+Y18+AA18+AC18 -> 0 | AD18: =AF18+AH18+AJ18+AL18+AN18+AP18+AR18+AT18+AV18+AX18+AZ18+BB18+BD18+BF18+BH18+BJ18+BL18+BN18+BP18+BR18+BT18+BV18+BX18+BZ18+CB18+CD18 -> 0
B19: 44364 | C19: =D19+M19+AD19 -> 0 | D19: =F19+H19+J19+L19 -> 0 | M19: =O19+Q19+S19+U19+W19+Y19+AA19+AC19 -> 0 | AD19: =AF19+AH19+AJ19+AL19+AN19+AP19+AR19+AT19+AV19+AX19+AZ19+BB19+BD19+BF19+BH19+BJ19+BL19+BN19+BP19+BR19+BT19+BV19+BX19+BZ19+CB19+CD19 -> 0
B20: 44365 | C20: =D20+M20+AD20 -> 0 | D20: =F20+H20+J20+L20 -> 0 | M20: =O20+Q20+S20+U20+W20+Y20+AA20+AC20 -> 0 | AD20: =AF20+AH20+AJ20+AL20+AN20+AP20+AR20+AT20+AV20+AX20+AZ20+BB20+BD20+BF20+BH20+BJ20+BL20+BN20+BP20+BR20+BT20+BV20+BX20+BZ20+CB20+CD20 -> 0
B21: 44366 | C21: =D21+M21+AD21 -> 0 | D21: =F21+H21+J21+L21 -> 0 | M21: =O21+Q21+S21+U21+W21+Y21+AA21+AC21 -> 0 | AD21: =AF21+AH21+AJ21+AL21+AN21+AP21+AR21+AT21+AV21+AX21+AZ21+BB21+BD21+BF21+BH21+BJ21+BL21+BN21+BP21+BR21+BT21+BV21+BX21+BZ21+CB21+CD21 -> 0
B22: 44367 | C22: =D22+M22+AD22 -> 0 | D22: =F22+H22+J22+L22 -> 0 | M22: =O22+Q22+S22+U22+W22+Y22+AA22+AC22 -> 0 | AD22: =AF22+AH22+AJ22+AL22+AN22+AP22+AR22+AT22+AV22+AX22+AZ22+BB22+BD22+BF22+BH22+BJ22+BL22+BN22+BP22+BR22+BT22+BV22+BX22+BZ22+CB22+CD22 -> 0
B23: 44368 | C23: =D23+M23+AD23 -> 33000 | D23: =F23+H23+J23+L23 -> 0 | M23: =O23+Q23+S23+U23+W23+Y23+AA23+AC23 -> 0 | AD23: =AF23+AH23+AJ23+AL23+AN23+AP23+AR23+AT23+AV23+AX23+AZ23+BB23+BD23+BF23+BH23+BJ23+BL23+BN23+BP23+BR23+BT23+BV23+BX23+BZ23+CB23+CD23 -> 33000 | AE23: 笠）㈱ﾌﾟﾛﾄｺｰﾎﾟﾚｰｼｮﾝ | AF23: 33000
B24: 44369 | C24: =D24+M24+AD24 -> 34302 | D24: =F24+H24+J24+L24 -> 0 | M24: =O24+Q24+S24+U24+W24+Y24+AA24+AC24 -> 0 | AD24: =AF24+AH24+AJ24+AL24+AN24+AP24+AR24+AT24+AV24+AX24+AZ24+BB24+BD24+BF24+BH24+BJ24+BL24+BN24+BP24+BR24+BT24+BV24+BX24+BZ24+CB24+CD24 -> 34302 | AE24: も）ｷｬﾉﾝ | AF24: 12160 | AG24: も)水道料J&LR | AH24: 3630 | AI24: 広）本社水道代引落 | AJ24: 4202 | AK24: も)本社水道代引落 | AL24: 14310
B25: 44370 | C25: =D25+M25+AD25 -> 39003 | D25: =F25+H25+J25+L25 -> 0 | M25: =O25+Q25+S25+U25+W25+Y25+AA25+AC25 -> 0 | AD25: =AF25+AH25+AJ25+AL25+AN25+AP25+AR25+AT25+AV25+AX25+AZ25+BB25+BD25+BF25+BH25+BJ25+BL25+BN25+BP25+BR25+BT25+BV25+BX25+BZ25+CB25+CD25 -> 39003 | AE25: 三井住友車両保険対人対物17.520円＋販売車車両保険8.894円 | AF25: 39003
B26: 44371 | C26: =D26+M26+AD26 -> 0 | D26: =F26+H26+J26+L26 -> 0 | M26: =O26+Q26+S26+U26+W26+Y26+AA26+AC26 -> 0 | AD26: =AF26+AH26+AJ26+AL26+AN26+AP26+AR26+AT26+AV26+AX26+AZ26+BB26+BD26+BF26+BH26+BJ26+BL26+BN26+BP26+BR26+BT26+BV26+BX26+BZ26+CB26+CD26 -> 0
B27: 44372 | C27: =D27+M27+AD27 -> 2049400 | D27: =F27+H27+J27+L27 -> 0 | M27: =O27+Q27+S27+U27+W27+Y27+AA27+AC27 -> 1845000 | N27: ﾌﾚｯﾁｪ・ﾎﾞｽｺ | O27: 55000 | P27: SoleilﾏｾﾗﾃｨMC20賃貸借2024.9.1～2026.8.31 | Q27: 220000 | R27: 橋本商事（裕太郎さん） | S27: 1570000 | AD27: =AF27+AH27+AJ27+AL27+AN27+AP27+AR27+AT27+AV27+AX27+AZ27+BB27+BD27+BF27+BH27+BJ27+BL27+BN27+BP27+BR27+BT27+BV27+BX27+BZ27+CB27+CD27 -> 204400 | AE27: も）㈱ﾕﾆﾏｯﾄﾗｲﾌ | AF27: 4400 | AG27: 一真ｸﾞﾚｶｰﾚGT（毎月25）2026.4.1～2027.4.30 | AH27: 200000
B28: 44373 | C28: =D28+M28+AD28 -> 536158 | D28: =F28+H28+J28+L28 -> 0 | M28: =O28+Q28+S28+U28+W28+Y28+AA28+AC28 -> 0 | AD28: =AF28+AH28+AJ28+AL28+AN28+AP28+AR28+AT28+AV28+AX28+AZ28+BB28+BD28+BF28+BH28+BJ28+BL28+BN28+BP28+BR28+BT28+BV28+BX28+BZ28+CB28+CD28 -> 536158 | AE28: 笠)カープレミアクラブディーラー ゴールド会員費 | AF28: 33000 | AG28: 広）ｿﾌﾄﾊﾞﾝｸ | AH28: 44360 | AI28: も）ｶｰｾﾌﾞﾝﾃﾞｼﾞﾌｨｰﾙﾄﾞｲﾝｽﾏｰﾄｼｽﾃﾑ | AJ28: 4620 | AK28: も）まるとく本社ｺﾋﾟｰ機 | AL28: 1829 | AM28: も）ﾁｭｰﾘｯﾋ生命 | AN28: 6015 | AO28: も）ｵﾘｺｶｰｻｺﾋﾟｰ機 | AP28: 27293 | AQ28: も）あんしん生命 | AR28: 58201 | AS28: も）三和地所 | AT28: 67440 | AU28: も)ｵﾘｺJCM | AV28: 99000 | AW28: も)引落中国新聞 | AX28: 3900 | AY28: 笠）三井損害保険 | AZ28: 172790 | BA28: 中)USS月会費 | BB28: 12980 | BC28: も）㈱ﾕﾆﾏｯﾄﾗｲﾌ | BD28: 4730
B29: 44374 | C29: =D29+M29+AD29 -> 0 | D29: =F29+H29+J29+L29 -> 0 | M29: =O29+Q29+S29+U29+W29+Y29+AA29+AC29 -> 0 | AD29: =AF29+AH29+AJ29+AL29+AN29+AP29+AR29+AT29+AV29+AX29+AZ29+BB29+BD29+BF29+BH29+BJ29+BL29+BN29+BP29+BR29+BT29+BV29+BX29+BZ29+CB29+CD29 -> 0
B30: 44375 | C30: =D30+M30+AD30 -> 378785 | D30: =F30+H30+J30+L30 -> 378785 | E30: 笠信ｼｮｳｶﾝｷﾝ | F30: 378785 | M30: =O30+Q30+S30+U30+W30+Y30+AA30+AC30 -> 0 | AD30: =AF30+AH30+AJ30+AL30+AN30+AP30+AR30+AT30+AV30+AX30+AZ30+BB30+BD30+BF30+BH30+BJ30+BL30+BN30+BP30+BR30+BT30+BV30+BX30+BZ30+CB30+CD30 -> 0
B31: 44376 | C31: =D31+M31+AD31 -> 4080312 | D31: =F31+H31+J31+L31 -> 2420247 | E31: 笠信ｼｮｳｶﾝｷﾝ | F31: 1764948 | G31: も)支払利息 | H31: 33698 | I31: 笠信ｼｮｳｶﾞｼ | J31: 517560 | K31: 笠信貸付利息 | L31: 104041 | M31: =O31+Q31+S31+U31+W31+Y31+AA31+AC31 -> 0 | AD31: =AF31+AH31+AJ31+AL31+AN31+AP31+AR31+AT31+AV31+AX31+AZ31+BB31+BD31+BF31+BH31+BJ31+BL31+BN31+BP31+BR31+BT31+BV31+BX31+BZ31+CB31+CD31 -> 1660065 | AE31: 笠）福山年金事務所 | AF31: 467620 | AG31: も)ﾋﾞｰﾌｨｰﾙﾄﾞ | AH31: 2200 | AI31: 吉野ｶﾞﾚｰｼﾞ | AJ31: 165000 | AK31: ウツミ屋証券 | AL31: 160000 | AM31: 月末支払（経費） | AN31: 865245
B32: 44377 | C32: =D32+M32+AD32 -> 2470488 | D32: =F32+H32+J32+L32 -> 2470488 | E32: 笠信ｼｮｳｶﾞｼ | F32: 391779 | G32: 笠信ｼｮｳｶﾞｼ | H32: 1699552 | I32: 笠信1500万円借入 | J32: 149842 | K32: 笠信5000利息分 | L32: 229315 | M32: =O32+Q32+S32+U32+W32+Y32+AA32+AC32 -> 0 | AD32: =AF32+AH32+AJ32+AL32+AN32+AP32+AR32+AT32+AV32+AX32+AZ32+BB32+BD32+BF32+BH32+BJ32+BL32+BN32+BP32+BR32+BT32+BV32+BX32+BZ32+CB32+CD32 -> 0
B33: ６月合計 | C33: =D33+M33+AD33 -> 14324833 | D33: =SUM(D3:D32) -> 5269520 | M33: =SUM(M3:M32) -> 1845000 | AD33: =SUM(AD3:AD32) -> 7210313
B34: 未確定
B35: 44378 | C35: =D35+M35+AD35 -> 82196 | D35: =F35+H35+J35+L35 -> 0 | M35: =O35+Q35+S35+U35+W35+Y35+AA35+AC35 -> 0 | AD35: =AF35+AH35+AJ35+AL35+AN35+AP35+AR35+AT35+AV35+AX35+AZ35+BB35+BD35+BF35+BH35+BJ35+BL35+BN35+BP35+BR35+BT35+BV35+BX35+BZ35+CB35+CD35 -> 82196 | AE35: も）ﾄﾖﾀﾌｧｲﾅﾝｽ | AF35: 82196
B36: 45109 | C36: =D36+M36+AD36 -> 29480 | D36: =F36+H36+J36+L36 -> 0 | M36: =O36+Q36+S36+U36+W36+Y36+AA36+AC36 -> 0 | AD36: =AF36+AH36+AJ36+AL36+AN36+AP36+AR36+AT36+AV36+AX36+AZ36+BB36+BD36+BF36+BH36+BJ36+BL36+BN36+BP36+BR36+BT36+BV36+BX36+BZ36+CB36+CD36 -> 29480 | AE36: 三井住友FL（SM） | AF36: 29480
B37: 45110 | C37: =D37+M37+AD37 -> 0 | D37: =F37+H37+J37+L37 -> 0 | M37: =O37+Q37+S37+U37+W37+Y37+AA37+AC37 -> 0 | AD37: =AF37+AH37+AJ37+AL37+AN37+AP37+AR37+AT37+AV37+AX37+AZ37+BB37+BD37+BF37+BH37+BJ37+BL37+BN37+BP37+BR37+BT37+BV37+BX37+BZ37+CB37+CD37 -> 0
B38: 45111 | C38: =D38+M38+AD38 -> 0 | D38: =F38+H38+J38+L38 -> 0 | M38: =O38+Q38+S38+U38+W38+Y38+AA38+AC38 -> 0 | AD38: =AF38+AH38+AJ38+AL38+AN38+AP38+AR38+AT38+AV38+AX38+AZ38+BB38+BD38+BF38+BH38+BJ38+BL38+BN38+BP38+BR38+BT38+BV38+BX38+BZ38+CB38+CD38 -> 0
B39: 45112 | C39: =D39+M39+AD39 -> 88000 | D39: =F39+H39+J39+L39 -> 0 | M39: =O39+Q39+S39+U39+W39+Y39+AA39+AC39 -> 0 | AD39: =AF39+AH39+AJ39+AL39+AN39+AP39+AR39+AT39+AV39+AX39+AZ39+BB39+BD39+BF39+BH39+BJ39+BL39+BN39+BP39+BR39+BT39+BV39+BX39+BZ39+CB39+CD39 -> 88000 | AE39: 笠)未来経営 | AF39: 88000
B40: 45113 | C40: =D40+M40+AD40 -> 0 | D40: =F40+H40+J40+L40 -> 0 | M40: =O40+Q40+S40+U40+W40+Y40+AA40+AC40 -> 0 | AD40: =AF40+AH40+AJ40+AL40+AN40+AP40+AR40+AT40+AV40+AX40+AZ40+BB40+BD40+BF40+BH40+BJ40+BL40+BN40+BP40+BR40+BT40+BV40+BX40+BZ40+CB40+CD40 -> 0
B41: 45114 | C41: =D41+M41+AD41 -> 0 | D41: =F41+H41+J41+L41 -> 0 | M41: =O41+Q41+S41+U41+W41+Y41+AA41+AC41 -> 0 | AD41: =AF41+AH41+AJ41+AL41+AN41+AP41+AR41+AT41+AV41+AX41+AZ41+BB41+BD41+BF41+BH41+BJ41+BL41+BN41+BP41+BR41+BT41+BV41+BX41+BZ41+CB41+CD41 -> 0
B42: 45115 | C42: =D42+M42+AD42 -> 0 | D42: =F42+H42+J42+L42 -> 0 | M42: =O42+Q42+S42+U42+W42+Y42+AA42+AC42 -> 0 | AD42: =AF42+AH42+AJ42+AL42+AN42+AP42+AR42+AT42+AV42+AX42+AZ42+BB42+BD42+BF42+BH42+BJ42+BL42+BN42+BP42+BR42+BT42+BV42+BX42+BZ42+CB42+CD42 -> 0
B43: 45116 | C43: =D43+M43+AD43 -> 3706089 | D43: =F43+H43+J43+L43 -> 0 | M43: =O43+Q43+S43+U43+W43+Y43+AA43+AC43 -> 0 | AD43: =AF43+AH43+AJ43+AL43+AN43+AP43+AR43+AT43+AV43+AX43+AZ43+BB43+BD43+BF43+BH43+BJ43+BL43+BN43+BP43+BR43+BT43+BV43+BX43+BZ43+CB43+CD43 -> 3706089 | AE43: 銚子部長 | AF43: 100000 | AG43: 笠）ﾀﾞｲﾅｰｽﾞ | AH43: 177132 | AI43: も)整備ﾀﾞｲﾅｰｽｶｰﾄﾞ・ﾄﾗｽﾄｸﾗﾌﾞ | AJ43: 593649 | AK43: も)ﾀﾞｲﾅｰｽｶｰﾄﾞ・ﾄﾗｽﾄｸﾗﾌﾞ | AL43: 455500 | AM43: 田中賢治様 | AN43: 14600 | AO43: 給与 | AP43: 1123735 | AQ43: 高田自動車 | AR43: 512973 | AS43: 大中誠二 | AT43: 728500
B44: 45117 | C44: =D44+M44+AD44 -> 0 | D44: =F44+H44+J44+L44 -> 0 | M44: =O44+Q44+S44+U44+W44+Y44+AA44+AC44 -> 0 | AD44: =AF44+AH44+AJ44+AL44+AN44+AP44+AR44+AT44+AV44+AX44+AZ44+BB44+BD44+BF44+BH44+BJ44+BL44+BN44+BP44+BR44+BT44+BV44+BX44+BZ44+CB44+CD44 -> 0
B45: 45118 | C45: =D45+M45+AD45 -> 0 | D45: =F45+H45+J45+L45 -> 0 | M45: =O45+Q45+S45+U45+W45+Y45+AA45+AC45 -> 0 | AD45: =AF45+AH45+AJ45+AL45+AN45+AP45+AR45+AT45+AV45+AX45+AZ45+BB45+BD45+BF45+BH45+BJ45+BL45+BN45+BP45+BR45+BT45+BV45+BX45+BZ45+CB45+CD45 -> 0
B46: 45119 | C46: =D46+M46+AD46 -> 0 | D46: =F46+H46+J46+L46 -> 0 | M46: =O46+Q46+S46+U46+W46+Y46+AA46+AC46 -> 0 | AD46: =AF46+AH46+AJ46+AL46+AN46+AP46+AR46+AT46+AV46+AX46+AZ46+BB46+BD46+BF46+BH46+BJ46+BL46+BN46+BP46+BR46+BT46+BV46+BX46+BZ46+CB46+CD46 -> 0
B47: 45120 | C47: =D47+M47+AD47 -> 0 | D47: =F47+H47+J47+L47 -> 0 | M47: =O47+Q47+S47+U47+W47+Y47+AA47+AC47 -> 0 | AD47: =AF47+AH47+AJ47+AL47+AN47+AP47+AR47+AT47+AV47+AX47+AZ47+BB47+BD47+BF47+BH47+BJ47+BL47+BN47+BP47+BR47+BT47+BV47+BX47+BZ47+CB47+CD47 -> 0
B48: 45121 | C48: =D48+M48+AD48 -> 0 | D48: =F48+H48+J48+L48 -> 0 | M48: =O48+Q48+S48+U48+W48+Y48+AA48+AC48 -> 0 | AD48: =AF48+AH48+AJ48+AL48+AN48+AP48+AR48+AT48+AV48+AX48+AZ48+BB48+BD48+BF48+BH48+BJ48+BL48+BN48+BP48+BR48+BT48+BV48+BX48+BZ48+CB48+CD48 -> 0
B49: 45122 | C49: =D49+M49+AD49 -> 0 | D49: =F49+H49+J49+L49 -> 0 | M49: =O49+Q49+S49+U49+W49+Y49+AA49+AC49 -> 0 | AD49: =AF49+AH49+AJ49+AL49+AN49+AP49+AR49+AT49+AV49+AX49+AZ49+BB49+BD49+BF49+BH49+BJ49+BL49+BN49+BP49+BR49+BT49+BV49+BX49+BZ49+CB49+CD49 -> 0
B50: 45123 | C50: =D50+M50+AD50 -> 0 | D50: =F50+H50+J50+L50 -> 0 | M50: =O50+Q50+S50+U50+W50+Y50+AA50+AC50 -> 0 | AD50: =AF50+AH50+AJ50+AL50+AN50+AP50+AR50+AT50+AV50+AX50+AZ50+BB50+BD50+BF50+BH50+BJ50+BL50+BN50+BP50+BR50+BT50+BV50+BX50+BZ50+CB50+CD50 -> 0
B51: 45124 | C51: =D51+M51+AD51 -> 0 | D51: =F51+H51+J51+L51 -> 0 | M51: =O51+Q51+S51+U51+W51+Y51+AA51+AC51 -> 0 | AD51: =AF51+AH51+AJ51+AL51+AN51+AP51+AR51+AT51+AV51+AX51+AZ51+BB51+BD51+BF51+BH51+BJ51+BL51+BN51+BP51+BR51+BT51+BV51+BX51+BZ51+CB51+CD51 -> 0
B52: 45125 | C52: =D52+M52+AD52 -> 0 | D52: =F52+H52+J52+L52 -> 0 | M52: =O52+Q52+S52+U52+W52+Y52+AA52+AC52 -> 0 | AD52: =AF52+AH52+AJ52+AL52+AN52+AP52+AR52+AT52+AV52+AX52+AZ52+BB52+BD52+BF52+BH52+BJ52+BL52+BN52+BP52+BR52+BT52+BV52+BX52+BZ52+CB52+CD52 -> 0
B53: 45126 | C53: =D53+M53+AD53 -> 19525 | D53: =F53+H53+J53+L53 -> 0 | M53: =O53+Q53+S53+U53+W53+Y53+AA53+AC53 -> 0 | AD53: =AF53+AH53+AJ53+AL53+AN53+AP53+AR53+AT53+AV53+AX53+AZ53+BB53+BD53+BF53+BH53+BJ53+BL53+BN53+BP53+BR53+BT53+BV53+BX53+BZ53+CB53+CD53 -> 19525 | AE53: も)水道料J&LR | AF53: 3630 | AG53: 広）本社水道代引落 | AH53: 4521 | AI53: も)本社水道代引落 | AJ53: 11374
B54: 45127 | C54: =D54+M54+AD54 -> 0 | D54: =F54+H54+J54+L54 -> 0 | M54: =O54+Q54+S54+U54+W54+Y54+AA54+AC54 -> 0 | AD54: =AF54+AH54+AJ54+AL54+AN54+AP54+AR54+AT54+AV54+AX54+AZ54+BB54+BD54+BF54+BH54+BJ54+BL54+BN54+BP54+BR54+BT54+BV54+BX54+BZ54+CB54+CD54 -> 0
B55: 45128 | C55: =D55+M55+AD55 -> 33000 | D55: =F55+H55+J55+L55 -> 0 | M55: =O55+Q55+S55+U55+W55+Y55+AA55+AC55 -> 0 | AD55: =AF55+AH55+AJ55+AL55+AN55+AP55+AR55+AT55+AV55+AX55+AZ55+BB55+BD55+BF55+BH55+BJ55+BL55+BN55+BP55+BR55+BT55+BV55+BX55+BZ55+CB55+CD55 -> 33000 | AE55: 笠）㈱ﾌﾟﾛﾄｺｰﾎﾟﾚｰｼｮﾝ | AF55: 33000
B56: 45129 | C56: =D56+M56+AD56 -> 12160 | D56: =F56+H56+J56+L56 -> 0 | M56: =O56+Q56+S56+U56+W56+Y56+AA56+AC56 -> 0 | AD56: =AF56+AH56+AJ56+AL56+AN56+AP56+AR56+AT56+AV56+AX56+AZ56+BB56+BD56+BF56+BH56+BJ56+BL56+BN56+BP56+BR56+BT56+BV56+BX56+BZ56+CB56+CD56 -> 12160 | AE56: も）ｷｬﾉﾝ | AF56: 12160
B57: 45130 | C57: =D57+M57+AD57 -> 39003 | D57: =F57+H57+J57+L57 -> 0 | M57: =O57+Q57+S57+U57+W57+Y57+AA57+AC57 -> 0 | AD57: =AF57+AH57+AJ57+AL57+AN57+AP57+AR57+AT57+AV57+AX57+AZ57+BB57+BD57+BF57+BH57+BJ57+BL57+BN57+BP57+BR57+BT57+BV57+BX57+BZ57+CB57+CD57 -> 39003 | AE57: 三井住友車両保険対人対物17.520円＋販売車車両保険8.894円 | AF57: 39003
B58: 45131 | C58: =D58+M58+AD58 -> 1895000 | D58: =F58+H58+J58+L58 -> 0 | M58: =O58+Q58+S58+U58+W58+Y58+AA58+AC58 -> 1895000 | N58: ﾌﾚｯﾁｪ・ﾎﾞｽｺ | O58: 55000 | P58: SoleilﾏｾﾗﾃｨMC20賃貸借2024.9.1～2026.8.31 | Q58: 220000 | R58: 橋本商事（裕太郎さん） | S58: 1620000 | AD58: =AF58+AH58+AJ58+AL58+AN58+AP58+AR58+AT58+AV58+AX58+AZ58+BB58+BD58+BF58+BH58+BJ58+BL58+BN58+BP58+BR58+BT58+BV58+BX58+BZ58+CB58+CD58 -> 0
B59: 45132 | C59: =D59+M59+AD59 -> 204400 | D59: =F59+H59+J59+L59 -> 0 | M59: =O59+Q59+S59+U59+W59+Y59+AA59+AC59 -> 0 | AD59: =AF59+AH59+AJ59+AL59+AN59+AP59+AR59+AT59+AV59+AX59+AZ59+BB59+BD59+BF59+BH59+BJ59+BL59+BN59+BP59+BR59+BT59+BV59+BX59+BZ59+CB59+CD59 -> 204400 | AE59: も）㈱ﾕﾆﾏｯﾄﾗｲﾌ | AF59: 4400 | AG59: 一真ｸﾞﾚｶｰﾚGT（毎月25）2026.4.1～2027.4.30 | AH59: 200000
B60: 45133 | C60: =D60+M60+AD60 -> 531428 | D60: =F60+H60+J60+L60 -> 0 | M60: =O60+Q60+S60+U60+W60+Y60+AA60+AC60 -> 0 | AD60: =AF60+AH60+AJ60+AL60+AN60+AP60+AR60+AT60+AV60+AX60+AZ60+BB60+BD60+BF60+BH60+BJ60+BL60+BN60+BP60+BR60+BT60+BV60+BX60+BZ60+CB60+CD60 -> 531428 | AE60: 笠)カープレミアクラブディーラー ゴールド会員費 | AF60: 33000 | AG60: 広）ｿﾌﾄﾊﾞﾝｸ | AH60: 44360 | AI60: も）ｶｰｾﾌﾞﾝﾃﾞｼﾞﾌｨｰﾙﾄﾞｲﾝｽﾏｰﾄｼｽﾃﾑ | AJ60: 4620 | AK60: も）引落まるとく本社ｺﾋﾟｰ機 | AL60: 1829 | AM60: も）ﾁｭｰﾘｯﾋ生命 | AN60: 6015 | AO60: も）ｵﾘｺｶｰｻｺﾋﾟｰ機 | AP60: 27293 | AQ60: も）あんしん生命 | AR60: 58201 | AS60: も）三和地所 | AT60: 67440 | AU60: もみじ)ｵﾘｺJCM | AV60: 99000 | AW60: も)引落中国新聞 | AX60: 3900 | AY60: 笠）三井損害保険 | AZ60: 172790 | BA60: 中銀引落)USS月会費 | BB60: 12980
B61: 45134 | C61: =D61+M61+AD61 -> 0 | D61: =F61+H61+J61+L61 -> 0 | M61: =O61+Q61+S61+U61+W61+Y61+AA61+AC61 -> 0 | AD61: =AF61+AH61+AJ61+AL61+AN61+AP61+AR61+AT61+AV61+AX61+AZ61+BB61+BD61+BF61+BH61+BJ61+BL61+BN61+BP61+BR61+BT61+BV61+BX61+BZ61+CB61+CD61 -> 0
B62: 45135 | C62: =D62+M62+AD62 -> 0 | D62: =F62+H62+J62+L62 -> 0 | M62: =O62+Q62+S62+U62+W62+Y62+AA62+AC62 -> 0 | AD62: =AF62+AH62+AJ62+AL62+AN62+AP62+AR62+AT62+AV62+AX62+AZ62+BB62+BD62+BF62+BH62+BJ62+BL62+BN62+BP62+BR62+BT62+BV62+BX62+BZ62+CB62+CD62 -> 0
B63: 45136 | C63: =D63+M63+AD63 -> 27038850 | D63: =F63+H63+J63+L63 -> 25378785 | E63: 笠信ｼｮｳｶﾝｷﾝ | F63: 378785 | G63: 3/10笠信短期借入33,000,000（返済日7/31）残り2,500万 | H63: 25000000 | M63: =O63+Q63+S63+U63+W63+Y63+AA63+AC63 -> 0 | AD63: =AF63+AH63+AJ63+AL63+AN63+AP63+AR63+AT63+AV63+AX63+AZ63+BB63+BD63+BF63+BH63+BJ63+BL63+BN63+BP63+BR63+BT63+BV63+BX63+BZ63+CB63+CD63 -> 1660065 | AE63: 笠）福山年金事務所 | AF63: 467620 | AG63: も)ﾋﾞｰﾌｨｰﾙﾄﾞ | AH63: 2200 | AI63: 吉野ｶﾞﾚｰｼﾞ | AJ63: 165000 | AK63: ウツミ屋証券 | AL63: 160000 | AM63: 月末支払（経費） | AN63: 865245
B64: 45137 | C64: =D64+M64+AD64 -> 2420247 | D64: =F64+H64+J64+L64 -> 2420247 | E64: 笠信ｼｮｳｶﾝｷﾝ | F64: 1764948 | G64: も)支払利息 | H64: 33698 | I64: 笠信ｼｮｳｶﾞｼ | J64: 517560 | K64: 笠信貸付利息 | L64: 104041 | M64: =O64+Q64+S64+U64+W64+Y64+AA64+AC64 -> 0 | AD64: =AF64+AH64+AJ64+AL64+AN64+AP64+AR64+AT64+AV64+AX64+AZ64+BB64+BD64+BF64+BH64+BJ64+BL64+BN64+BP64+BR64+BT64+BV64+BX64+BZ64+CB64+CD64 -> 0
B65: 45138 | C65: =D65+M65+AD65 -> 2470488 | D65: =F65+H65+J65+L65 -> 2470488 | E65: 笠信ｼｮｳｶﾞｼ | F65: 391779 | G65: 笠信ｼｮｳｶﾞｼ | H65: 1699552 | I65: 笠信1500万円借入 | J65: 149842 | K65: 笠信5000利息分 | L65: 229315 | M65: =O65+Q65+S65+U65+W65+Y65+AA65+AC65 -> 0 | AD65: =AF65+AH65+AJ65+AL65+AN65+AP65+AR65+AT65+AV65+AX65+AZ65+BB65+BD65+BF65+BH65+BJ65+BL65+BN65+BP65+BR65+BT65+BV65+BX65+BZ65+CB65+CD65 -> 0
B66: ７月合計 | C66: =SUM(C35:C65) -> 38569866 | D66: =SUM(D35:D65) -> 30269520 | M66: =SUM(M35:M65) -> 1895000 | AD66: =SUM(AD35:AD65) -> 6405346
B67: 未確定
B68: 45139 | C68: =D68+M68+AD68 -> 82196 | D68: =F68+H68+J68+L68 -> 0 | M68: =O68+Q68+S68+U68 -> 0 | AD68: =AF68+AH68+AJ68+AL68+AN68+AP68+AR68+AT68+AV68+AX68+AZ68+BB68+BD68+BF68+BH68+BJ68+BL68+BN68+BP68+BR68+BT68+BV68+BX68+BZ68+CB68 -> 82196 | AE68: も）ﾄﾖﾀﾌｧｲﾅﾝｽ | AF68: 82196
B69: 45140 | C69: =D69+M69+AD69 -> 29480 | D69: =F69+H69+J69+L69 -> 0 | M69: =O69+Q69+S69+U69 -> 0 | AD69: =AF69+AH69+AJ69+AL69+AN69+AP69+AR69+AT69+AV69+AX69+AZ69+BB69+BD69+BF69+BH69+BJ69+BL69+BN69+BP69+BR69+BT69+BV69+BX69+BZ69+CB69 -> 29480 | AE69: 三井住友FL（SM） | AF69: 29480
B70: 45141 | C70: =D70+M70+AD70 -> 0 | D70: =F70+H70+J70+L70 -> 0 | M70: =O70+Q70+S70+U70 -> 0 | AD70: =AF70+AH70+AJ70+AL70+AN70+AP70+AR70+AT70+AV70+AX70+AZ70+BB70+BD70+BF70+BH70+BJ70+BL70+BN70+BP70+BR70+BT70+BV70+BX70+BZ70+CB70 -> 0
B71: 45142 | C71: =D71+M71+AD71 -> 0 | D71: =F71+H71+J71+L71 -> 0 | M71: =O71+Q71+S71+U71 -> 0 | AD71: =AF71+AH71+AJ71+AL71+AN71+AP71+AR71+AT71+AV71+AX71+AZ71+BB71+BD71+BF71+BH71+BJ71+BL71+BN71+BP71+BR71+BT71+BV71+BX71+BZ71+CB71 -> 0
B72: 45143 | C72: =D72+M72+AD72 -> 88000 | D72: =F72+H72+J72+L72 -> 0 | M72: =O72+Q72+S72+U72 -> 0 | AD72: =AF72+AH72+AJ72+AL72+AN72+AP72+AR72+AT72+AV72+AX72+AZ72+BB72+BD72+BF72+BH72+BJ72+BL72+BN72+BP72+BR72+BT72+BV72+BX72+BZ72+CB72 -> 88000 | AE72: 笠)未来経営 | AF72: 88000
B73: 45144 | C73: =D73+M73+AD73 -> 0 | D73: =F73+H73+J73+L73 -> 0 | M73: =O73+Q73+S73+U73 -> 0 | AD73: =AF73+AH73+AJ73+AL73+AN73+AP73+AR73+AT73+AV73+AX73+AZ73+BB73+BD73+BF73+BH73+BJ73+BL73+BN73+BP73+BR73+BT73+BV73+BX73+BZ73+CB73 -> 0
B74: 45145 | C74: =D74+M74+AD74 -> 0 | D74: =F74+H74+J74+L74 -> 0 | M74: =O74+Q74+S74+U74 -> 0 | AD74: =AF74+AH74+AJ74+AL74+AN74+AP74+AR74+AT74+AV74+AX74+AZ74+BB74+BD74+BF74+BH74+BJ74+BL74+BN74+BP74+BR74+BT74+BV74+BX74+BZ74+CB74 -> 0
B75: 45146 | C75: =D75+M75+AD75 -> 0 | D75: =F75+H75+J75+L75 -> 0 | M75: =O75+Q75+S75+U75 -> 0 | AD75: =AF75+AH75+AJ75+AL75+AN75+AP75+AR75+AT75+AV75+AX75+AZ75+BB75+BD75+BF75+BH75+BJ75+BL75+BN75+BP75+BR75+BT75+BV75+BX75+BZ75+CB75 -> 0
B76: 45147 | C76: =D76+M76+AD76 -> 3906089 | D76: =F76+H76+J76+L76 -> 0 | M76: =O76+Q76+S76+U76 -> 0 | AD76: =AF76+AH76+AJ76+AL76+AN76+AP76+AR76+AT76+AV76+AX76+AZ76+BB76+BD76+BF76+BH76+BJ76+BL76+BN76+BP76+BR76+BT76+BV76+BX76+BZ76+CB76 -> 3906089 | AE76: 高田自動車 | AF76: 512973 | AG76: 笠）ﾀﾞｲﾅｰｽﾞ | AH76: 177132 | AI76: も)整備ﾀﾞｲﾅｰｽｶｰﾄﾞ・ﾄﾗｽﾄｸﾗﾌﾞ | AJ76: 593649 | AK76: も)ﾀﾞｲﾅｰｽｶｰﾄﾞ・ﾄﾗｽﾄｸﾗﾌﾞ | AL76: 455500 | AM76: 銚子部長 | AN76: 100000 | AO76: 田中賢治様 | AP76: 214600 | AQ76: 給与 | AR76: 1123735 | AS76: 大中誠二 | AT76: 728500
B77: 45148 | C77: =D77+M77+AD77 -> 0 | D77: =F77+H77+J77+L77 -> 0 | M77: =O77+Q77+S77+U77 -> 0 | AD77: =AF77+AH77+AJ77+AL77+AN77+AP77+AR77+AT77+AV77+AX77+AZ77+BB77+BD77+BF77+BH77+BJ77+BL77+BN77+BP77+BR77+BT77+BV77+BX77+BZ77+CB77 -> 0
B78: 45149 | C78: =D78+M78+AD78 -> 0 | D78: =F78+H78+J78+L78 -> 0 | M78: =O78+Q78+S78+U78 -> 0 | AD78: =AF78+AH78+AJ78+AL78+AN78+AP78+AR78+AT78+AV78+AX78+AZ78+BB78+BD78+BF78+BH78+BJ78+BL78+BN78+BP78+BR78+BT78+BV78+BX78+BZ78+CB78 -> 0
B79: 45150 | C79: =D79+M79+AD79 -> 0 | D79: =F79+H79+J79+L79 -> 0 | M79: =O79+Q79+S79+U79 -> 0 | AD79: =AF79+AH79+AJ79+AL79+AN79+AP79+AR79+AT79+AV79+AX79+AZ79+BB79+BD79+BF79+BH79+BJ79+BL79+BN79+BP79+BR79+BT79+BV79+BX79+BZ79+CB79 -> 0
B80: 45151 | C80: =D80+M80+AD80 -> 0 | D80: =F80+H80+J80+L80 -> 0 | M80: =O80+Q80+S80+U80 -> 0 | AD80: =AF80+AH80+AJ80+AL80+AN80+AP80+AR80+AT80+AV80+AX80+AZ80+BB80+BD80+BF80+BH80+BJ80+BL80+BN80+BP80+BR80+BT80+BV80+BX80+BZ80+CB80 -> 0
B81: 45152 | C81: =D81+M81+AD81 -> 0 | D81: =F81+H81+J81+L81 -> 0 | M81: =O81+Q81+S81+U81 -> 0 | AD81: =AF81+AH81+AJ81+AL81+AN81+AP81+AR81+AT81+AV81+AX81+AZ81+BB81+BD81+BF81+BH81+BJ81+BL81+BN81+BP81+BR81+BT81+BV81+BX81+BZ81+CB81 -> 0
B82: 45153 | C82: =D82+M82+AD82 -> 0 | D82: =F82+H82+J82+L82 -> 0 | M82: =O82+Q82+S82+U82 -> 0 | AD82: =AF82+AH82+AJ82+AL82+AN82+AP82+AR82+AT82+AV82+AX82+AZ82+BB82+BD82+BF82+BH82+BJ82+BL82+BN82+BP82+BR82+BT82+BV82+BX82+BZ82+CB82 -> 0
B83: 45154 | C83: =D83+M83+AD83 -> 0 | D83: =F83+H83+J83+L83 -> 0 | M83: =O83+Q83+S83+U83 -> 0 | AD83: =AF83+AH83+AJ83+AL83+AN83+AP83+AR83+AT83+AV83+AX83+AZ83+BB83+BD83+BF83+BH83+BJ83+BL83+BN83+BP83+BR83+BT83+BV83+BX83+BZ83+CB83 -> 0
B84: 45155 | C84: =D84+M84+AD84 -> 0 | D84: =F84+H84+J84+L84 -> 0 | M84: =O84+Q84+S84+U84 -> 0 | AD84: =AF84+AH84+AJ84+AL84+AN84+AP84+AR84+AT84+AV84+AX84+AZ84+BB84+BD84+BF84+BH84+BJ84+BL84+BN84+BP84+BR84+BT84+BV84+BX84+BZ84+CB84 -> 0
B85: 45156 | C85: =D85+M85+AD85 -> 0 | D85: =F85+H85+J85+L85 -> 0 | M85: =O85+Q85+S85+U85 -> 0 | AD85: =AF85+AH85+AJ85+AL85+AN85+AP85+AR85+AT85+AV85+AX85+AZ85+BB85+BD85+BF85+BH85+BJ85+BL85+BN85+BP85+BR85+BT85+BV85+BX85+BZ85+CB85 -> 0
B86: 45157 | C86: =D86+M86+AD86 -> 19525 | D86: =F86+H86+J86+L86 -> 0 | M86: =O86+Q86+S86+U86 -> 0 | AD86: =AF86+AH86+AJ86+AL86+AN86+AP86+AR86+AT86+AV86+AX86+AZ86+BB86+BD86+BF86+BH86+BJ86+BL86+BN86+BP86+BR86+BT86+BV86+BX86+BZ86+CB86 -> 19525 | AE86: も)水道料J&LR | AF86: 3630 | AG86: 広）本社水道代引落 | AH86: 4521 | AI86: も)本社水道代引落 | AJ86: 11374
B87: 45158 | C87: =D87+M87+AD87 -> 0 | D87: =F87+H87+J87+L87 -> 0 | M87: =O87+Q87+S87+U87 -> 0 | AD87: =AF87+AH87+AJ87+AL87+AN87+AP87+AR87+AT87+AV87+AX87+AZ87+BB87+BD87+BF87+BH87+BJ87+BL87+BN87+BP87+BR87+BT87+BV87+BX87+BZ87+CB87 -> 0
B88: 45159 | C88: =D88+M88+AD88 -> 33000 | D88: =F88+H88+J88+L88 -> 0 | M88: =O88+Q88+S88+U88 -> 0 | AD88: =AF88+AH88+AJ88+AL88+AN88+AP88+AR88+AT88+AV88+AX88+AZ88+BB88+BD88+BF88+BH88+BJ88+BL88+BN88+BP88+BR88+BT88+BV88+BX88+BZ88+CB88 -> 33000 | AE88: 笠）㈱ﾌﾟﾛﾄｺｰﾎﾟﾚｰｼｮﾝ | AF88: 33000
B89: 45160 | C89: =D89+M89+AD89 -> 12160 | D89: =F89+H89+J89+L89 -> 0 | M89: =O89+Q89+S89+U89 -> 0 | AD89: =AF89+AH89+AJ89+AL89+AN89+AP89+AR89+AT89+AV89+AX89+AZ89+BB89+BD89+BF89+BH89+BJ89+BL89+BN89+BP89+BR89+BT89+BV89+BX89+BZ89+CB89 -> 12160 | AE89: も）ｷｬﾉﾝ | AF89: 12160
B90: 45161 | C90: =D90+M90+AD90 -> 39003 | D90: =F90+H90+J90+L90 -> 0 | M90: =O90+Q90+S90+U90 -> 0 | AD90: =AF90+AH90+AJ90+AL90+AN90+AP90+AR90+AT90+AV90+AX90+AZ90+BB90+BD90+BF90+BH90+BJ90+BL90+BN90+BP90+BR90+BT90+BV90+BX90+BZ90+CB90 -> 39003 | AE90: 三井住友車両保険対人対物17.520円＋販売車車両保険8.894円 | AF90: 39003
B91: 45162 | C91: =D91+M91+AD91 -> 0 | D91: =F91+H91+J91+L91 -> 0 | M91: =O91+Q91+S91+U91 -> 0 | AD91: =AF91+AH91+AJ91+AL91+AN91+AP91+AR91+AT91+AV91+AX91+AZ91+BB91+BD91+BF91+BH91+BJ91+BL91+BN91+BP91+BR91+BT91+BV91+BX91+BZ91+CB91 -> 0
B92: 45163 | C92: =D92+M92+AD92 -> 1949400 | D92: =F92+H92+J92+L92 -> 0 | M92: =O92+Q92+S92+U92 -> 1745000 | N92: ﾌﾚｯﾁｪ・ﾎﾞｽｺ | O92: 55000 | P92: SoleilﾏｾﾗﾃｨMC20賃貸借2024.9.1～2026.8.31 | Q92: 220000 | R92: 橋本商事（裕太郎さん） | S92: 1470000 | AD92: =AF92+AH92+AJ92+AL92+AN92+AP92+AR92+AT92+AV92+AX92+AZ92+BB92+BD92+BF92+BH92+BJ92+BL92+BN92+BP92+BR92+BT92+BV92+BX92+BZ92+CB92 -> 204400 | AE92: も）㈱ﾕﾆﾏｯﾄﾗｲﾌ | AF92: 4400 | AG92: 一真ｸﾞﾚｶｰﾚGT（毎月25）2026.4.1～2027.4.30 | AH92: 200000
B93: 45164 | C93: =D93+M93+AD93 -> 531428 | D93: =F93+H93+J93+L93 -> 0 | M93: =O93+Q93+S93+U93 -> 0 | AD93: =AF93+AH93+AJ93+AL93+AN93+AP93+AR93+AT93+AV93+AX93+AZ93+BB93+BD93+BF93+BH93+BJ93+BL93+BN93+BP93+BR93+BT93+BV93+BX93+BZ93+CB93 -> 531428 | AE93: 笠)カープレミアクラブディーラー ゴールド会員費 | AF93: 33000 | AG93: 広）ｿﾌﾄﾊﾞﾝｸ | AH93: 44360 | AI93: も）ｶｰｾﾌﾞﾝﾃﾞｼﾞﾌｨｰﾙﾄﾞｲﾝｽﾏｰﾄｼｽﾃﾑ | AJ93: 4620 | AK93: も）引落まるとく本社ｺﾋﾟｰ機 | AL93: 1829 | AM93: も）ﾁｭｰﾘｯﾋ生命 | AN93: 6015 | AO93: も）ｵﾘｺｶｰｻｺﾋﾟｰ機 | AP93: 27293 | AQ93: も）あんしん生命 | AR93: 58201 | AS93: も）三和地所 | AT93: 67440 | AU93: もみじ)ｵﾘｺJCM | AV93: 99000 | AW93: も)引落中国新聞 | AX93: 3900 | AY93: 笠）三井損害保険 | AZ93: 172790 | BA93: 中銀引落)USS月会費 | BB93: 12980
B94: 45165 | C94: =D94+M94+AD94 -> 0 | D94: =F94+H94+J94+L94 -> 0 | M94: =O94+Q94+S94+U94 -> 0 | AD94: =AF94+AH94+AJ94+AL94+AN94+AP94+AR94+AT94+AV94+AX94+AZ94+BB94+BD94+BF94+BH94+BJ94+BL94+BN94+BP94+BR94+BT94+BV94+BX94+BZ94+CB94 -> 0
B95: 45166 | C95: =D95+M95+AD95 -> 0 | D95: =F95+H95+J95+L95 -> 0 | M95: =O95+Q95+S95+U95 -> 0 | AD95: =AF95+AH95+AJ95+AL95+AN95+AP95+AR95+AT95+AV95+AX95+AZ95+BB95+BD95+BF95+BH95+BJ95+BL95+BN95+BP95+BR95+BT95+BV95+BX95+BZ95+CB95 -> 0
B96: 45167 | C96: =D96+M96+AD96 -> 2038850 | D96: =F96+H96+J96+L96 -> 378785 | E96: 笠信ｼｮｳｶﾝｷﾝ | F96: 378785 | M96: =O96+Q96+S96+U96+W96 -> 0 | AD96: =AF96+AH96+AJ96+AL96+AN96+AP96+AR96+AT96+AV96+AX96+AZ96+BB96+BD96+BF96+BH96+BJ96+BL96+BN96+BP96+BR96+BT96+BV96+BX96+BZ96+CB96 -> 1660065 | AE96: 笠）福山年金事務所 | AF96: 467620 | AG96: も)ﾋﾞｰﾌｨｰﾙﾄﾞ | AH96: 2200 | AI96: 吉野ｶﾞﾚｰｼﾞ | AJ96: 165000 | AK96: ウツミ屋証券 | AL96: 160000 | AM96: 月末支払（経費） | AN96: 865245
B97: 45168 | C97: =D97+M97+AD97 -> 2420247 | D97: =F97+H97+J97+L97 -> 2420247 | E97: 笠信ｼｮｳｶﾝｷﾝ | F97: 1764948 | G97: も)支払利息 | H97: 33698 | I97: 笠信ｼｮｳｶﾞｼ | J97: 517560 | K97: 笠信貸付利息 | L97: 104041 | M97: =O97+Q97+S97+U97 -> 0 | AD97: =AF97+AH97+AJ97+AL97+AN97+AP97+AR97+AT97+AV97+AX97+AZ97+BB97+BD97+BF97+BH97+BJ97+BL97+BN97+BP97+BR97+BT97+BV97+BX97+BZ97+CB97 -> 0
B98: 45169 | C98: =D98+M98+AD98 -> 2470488 | D98: =F98+H98+J98+L98 -> 2470488 | E98: 笠信ｼｮｳｶﾞｼ | F98: 391779 | G98: 笠信ｼｮｳｶﾞｼ | H98: 1699552 | I98: 笠信1500万円借入 | J98: 149842 | K98: 笠信5000利息分 | L98: 229315 | M98: =O98+Q98+S98+U98 -> 0 | AD98: =AF98+AH98+AJ98+AL98+AN98+AP98+AR98+AT98+AV98+AX98+AZ98+BB98+BD98+BF98+BH98+BJ98+BL98+BN98+BP98+BR98+BT98+BV98+BX98+BZ98+CB98 -> 0
B99: ８月合計 | C99: =SUM(C68:C98) -> 13619866 | D99: =SUM(D68:D98) -> 5269520 | M99: =SUM(M68:M98) -> 1745000 | AD99: =SUM(AD68:AD98) -> 6605346
B100: 未確定
...

Sheet 入出金合計表 【第17期2025年6月～】
B1: 2024年5月末残 | C1: ='入出金合計表 【第16期2024年6月～】 '!C391 -> 14462720
C2: ２０２5年６月‐２０２6年５月残高
C3: 残高日次 | D3: 入金合計 | E3: 金融機関関連 | F3: 保険関連 | G3: お客様関連 | H3: 出金合計 | I3: 金融機関関連 | J3: 買掛関連 | K3: 経費関連
B4: 44348 | C4: =SUM(C1+D4-H4) -> 12730156 | D4: =E4+F4+G4 -> 0 | E4: ='入金明細【17期】'!D3 -> 0 | F4: ='入金明細【17期】'!M3 -> 0 | G4: ='入金明細【17期】'!T3 -> 0 | H4: =I4+J4+K4 -> 1732564 | I4: ='出金明細【17期】'!D3 -> 1732564 | J4: ='出金明細【17期】'!M3 -> 0 | K4: ='出金明細【17期】'!AD3 -> 0
B5: 44349 | C5: =SUM(C4+D5-H5) -> 6503999 | D5: =E5+F5+G5 -> 0 | E5: ='入金明細【17期】'!D4 -> 0 | F5: ='入金明細【17期】'!M4 -> 0 | G5: ='入金明細【17期】'!T4 -> 0 | H5: =I5+J5+K5 -> 6226157 | I5: ='出金明細【17期】'!D4 -> 3224600 | J5: ='出金明細【17期】'!M4 -> 1043380 | K5: ='出金明細【17期】'!AD4 -> 1958177
B6: 45446 | C6: =SUM(C5+D6-H6) -> 8238989 | D6: =E6+F6+G6 -> 1930350 | E6: ='入金明細【17期】'!D5 -> 600000 | F6: ='入金明細【17期】'!M5 -> 0 | G6: ='入金明細【17期】'!T5 -> 1330350 | H6: =I6+J6+K6 -> 195360 | I6: ='出金明細【17期】'!D5 -> 0 | J6: ='出金明細【17期】'!M5 -> 0 | K6: ='出金明細【17期】'!AD5 -> 195360
B7: 44351 | C7: =SUM(C6+D7-H7) -> 8174199 | D7: =E7+F7+G7 -> 77000 | E7: ='入金明細【17期】'!D6 -> 0 | F7: ='入金明細【17期】'!M6 -> 0 | G7: ='入金明細【17期】'!T6 -> 77000 | H7: =I7+J7+K7 -> 141790 | I7: ='出金明細【17期】'!D6 -> 550 | J7: ='出金明細【17期】'!M6 -> 0 | K7: ='出金明細【17期】'!AD6 -> 141240
B8: 44352 | C8: =SUM(C7+D8-H8) -> 8239979 | D8: =E8+F8+G8 -> 65780 | E8: ='入金明細【17期】'!D7 -> 0 | F8: ='入金明細【17期】'!M7 -> 0 | G8: ='入金明細【17期】'!T7 -> 65780 | H8: =I8+J8+K8 -> 0 | I8: ='出金明細【17期】'!D7 -> 0 | J8: ='出金明細【17期】'!M7 -> 0 | K8: ='出金明細【17期】'!AD7 -> 0
B9: 44353 | C9: =SUM(C8+D9-H9) -> 8239979 | D9: =E9+F9+G9 -> 0 | E9: ='入金明細【17期】'!D8 -> 0 | F9: ='入金明細【17期】'!M8 -> 0 | G9: ='入金明細【17期】'!T8 -> 0 | H9: =I9+J9+K9 -> 0 | I9: ='出金明細【17期】'!D8 -> 0 | J9: ='出金明細【17期】'!M8 -> 0 | K9: ='出金明細【17期】'!AD8 -> 0
B10: 44354 | C10: =SUM(C9+D10-H10) -> 8264979 | D10: =E10+F10+G10 -> 25000 | E10: ='入金明細【17期】'!D9 -> 0 | F10: ='入金明細【17期】'!M9 -> 0 | G10: ='入金明細【17期】'!T9 -> 25000 | H10: =I10+J10+K10 -> 0 | I10: ='出金明細【17期】'!D9 -> 0 | J10: ='出金明細【17期】'!M9 -> 0 | K10: ='出金明細【17期】'!AD9 -> 0
B11: 44355 | C11: =SUM(C10+D11-H11) -> 8261349 | D11: =E11+F11+G11 -> 0 | E11: ='入金明細【17期】'!D10 -> 0 | F11: ='入金明細【17期】'!M10 -> 0 | G11: ='入金明細【17期】'!T10 -> 0 | H11: =I11+J11+K11 -> 3630 | I11: ='出金明細【17期】'!D10 -> 3630 | J11: ='出金明細【17期】'!M10 -> 0 | K11: ='出金明細【17期】'!AD10 -> 0
B12: 44356 | C12: =SUM(C11+D12-H12) -> 8246637 | D12: =E12+F12+G12 -> 248 | E12: ='入金明細【17期】'!D11 -> 248 | F12: ='入金明細【17期】'!M11 -> 0 | G12: ='入金明細【17期】'!T11 -> 0 | H12: =I12+J12+K12 -> 14960 | I12: ='出金明細【17期】'!D11 -> 14960 | J12: ='出金明細【17期】'!M11 -> 0 | K12: ='出金明細【17期】'!AD11 -> 0
B13: 44357 | C13: =SUM(C12+D13-H13) -> 4205693 | D13: =E13+F13+G13 -> 0 | E13: ='入金明細【17期】'!D12 -> 0 | F13: ='入金明細【17期】'!M12 -> 0 | G13: ='入金明細【17期】'!T12 -> 0 | H13: =I13+J13+K13 -> 4040944 | I13: ='出金明細【17期】'!D12 -> 5170 | J13: ='出金明細【17期】'!M12 -> 0 | K13: ='出金明細【17期】'!AD12 -> 4035774
B14: 44358 | C14: =SUM(C13+D14-H14) -> 6215267 | D14: =E14+F14+G14 -> 2009574 | E14: ='入金明細【17期】'!D13 -> 0 | F14: ='入金明細【17期】'!M13 -> 0 | G14: ='入金明細【17期】'!T13 -> 2009574 | H14: =I14+J14+K14 -> 0 | I14: ='出金明細【17期】'!D13 -> 0 | J14: ='出金明細【17期】'!M13 -> 0 | K14: ='出金明細【17期】'!AD13 -> 0
B15: 44359 | C15: =SUM(C14+D15-H15) -> 6189834 | D15: =E15+F15+G15 -> 0 | E15: ='入金明細【17期】'!D14 -> 0 | F15: ='入金明細【17期】'!M14 -> 0 | G15: ='入金明細【17期】'!T14 -> 0 | H15: =I15+J15+K15 -> 25433 | I15: ='出金明細【17期】'!D14 -> 0 | J15: ='出金明細【17期】'!M14 -> 0 | K15: ='出金明細【17期】'!AD14 -> 25433
B16: 44360 | C16: =SUM(C15+D16-H16) -> 8084834 | D16: =E16+F16+G16 -> 1900000 | E16: ='入金明細【17期】'!D15 -> 1900000 | F16: ='入金明細【17期】'!M15 -> 0 | G16: ='入金明細【17期】'!T15 -> 0 | H16: =I16+J16+K16 -> 5000 | I16: ='出金明細【17期】'!D15 -> 0 | J16: ='出金明細【17期】'!M15 -> 0 | K16: ='出金明細【17期】'!AD15 -> 5000
... B33: 44377 | C33: =SUM(C32+D33-H33) -> 7192718 | D33: =E33+F33+G33 -> 16042404 | E33: ='入金明細【17期】'!D32 -> 0 | F33: ='入金明細【17期】'!M32 -> 0 | G33: ='入金明細【17期】'!T32 -> 16042404 | H33: =I33+J33+K33 -> 14510347 | I33: ='出金明細【17期】'!D32 -> 573237 | J33: ='出金明細【17期】'!M32 -> 11891372 | K33: ='出金明細【17期】'!AD32 -> 2045738
B34: 6月合計 | C34: =SUM(D34-H34) -> -7270002 | D34: =E34+F34+G34 -> 38728869 | E34: =SUM(E4:E33) -> 2506615 | F34: =SUM(F4:F33) -> 170634 | G34: =SUM(G4:G33) -> 36051620 | H34: =SUM(H4:H33) -> 45998871 | I34: =SUM(I4:I33) -> 10804885 | J34: =SUM(J4:J33) -> 25520872 | K34: =SUM(K4:K33) -> 9673114
B35: 累計 | C35: =SUM(D35-H35) -> -7270002 | D35: =E35+F35+G35 -> 38728869 | E35: =E2+E34 -> 2506615 | F35: =F2+F34 -> 170634 | G35: =G2+G34 -> 36051620 | H35: =H2+H34 -> 45998871 | I35: =I2+I34 -> 10804885 | J35: =J2+J34 -> 25520872 | K35: =K2+K34 -> 9673114
B36: 44378 | C36: =SUM(C33+D36-H36) -> 7142107 | D36: =E36+F36+G36 -> 0 | E36: ='入金明細【17期】'!D35 -> 0 | F36: ='入金明細【17期】'!M35 -> 0 | G36: ='入金明細【17期】'!T35 -> 0 | H36: =I36+J36+K36 -> 50611 | I36: ='出金明細【17期】'!D35 -> 0 | J36: ='出金明細【17期】'!M35 -> 0 | K36: ='出金明細【17期】'!AD35 -> 50611
B37: 45109 | C37: =SUM(C36+D37-H37) -> 7564107 | D37: =E37+F37+G37 -> 430000 | E37: ='入金明細【17期】'!D36 -> 0 | F37: ='入金明細【17期】'!M36 -> 0 | G37: ='入金明細【17期】'!T36 -> 430000 | H37: =I37+J37+K37 -> 8000 | I37: ='出金明細【17期】'!D36 -> 8000 | J37: ='出金明細【17期】'!M36 -> 0 | K37: ='出金明細【17期】'!AD36 -> 0
B38: 45110 | C38: =SUM(C37+D38-H38) -> 37276587 | D38: =E38+F38+G38 -> 29712480 | E38: ='入金明細【17期】'!D37 -> 12470891 | F38: ='入金明細【17期】'!M37 -> 0 | G38: ='入金明細【17期】'!T37 -> 17241589 | H38: =I38+J38+K38 -> 0 | I38: ='出金明細【17期】'!D37 -> 0 | J38: ='出金明細【17期】'!M37 -> 0 | K38: ='出金明細【17期】'!AD37 -> 0
B39: 45111 | C39: =SUM(C38+D39-H39) -> 31403757 | D39: =E39+F39+G39 -> 0 | E39: ='入金明細【17期】'!D38 -> 0 | F39: ='入金明細【17期】'!M38 -> 0 | G39: ='入金明細【17期】'!T38 -> 0 | H39: =I39+J39+K39 -> 5872830 | I39: ='出金明細【17期】'!D38 -> 0 | J39: ='出金明細【17期】'!M38 -> 5731590 | K39: ='出金明細【17期】'!AD38 -> 141240
B40: 45112 | C40: =SUM(C39+D40-H40) -> 31403757 | D40: =E40+F40+G40 -> 0 | E40: ='入金明細【17期】'!D39 -> 0 | F40: ='入金明細【17期】'!M39 -> 0 | G40: ='入金明細【17期】'!T39 -> 0 | H40: =I40+J40+K40 -> 0 | I40: ='出金明細【17期】'!D39 -> 0 | J40: ='出金明細【17期】'!M39 -> 0 | K40: ='出金明細【17期】'!AD39 -> 0
B41: 45113 | C41: =SUM(C40+D41-H41) -> 31403757 | D41: =E41+F41+G41 -> 0 | E41: ='入金明細【17期】'!D40 -> 0 | F41: ='入金明細【17期】'!M40 -> 0 | G41: ='入金明細【17期】'!T40 -> 0 | H41: =I41+J41+K41 -> 0 | I41: ='出金明細【17期】'!D40 -> 0 | J41: ='出金明細【17期】'!M40 -> 0 | K41: ='出金明細【17期】'!AD40 -> 0
B42: 45114 | C42: =SUM(C41+D42-H42) -> 31402547 | D42: =E42+F42+G42 -> 0 | E42: ='入金明細【17期】'!D41 -> 0 | F42: ='入金明細【17期】'!M41 -> 0 | G42: ='入金明細【17期】'!T41 -> 0 | H42: =I42+J42+K42 -> 1210 | I42: ='出金明細【17期】'!D41 -> 1210 | J42: ='出金明細【17期】'!M41 -> 0 | K42: ='出金明細【17期】'!AD41 -> 0
B43: 45115 | C43: =SUM(C42+D43-H43) -> 31648771 | D43: =E43+F43+G43 -> 354024 | E43: ='入金明細【17期】'!D42 -> 0 | F43: ='入金明細【17期】'!M42 -> 0 | G43: ='入金明細【17期】'!T42 -> 354024 | H43: =I43+J43+K43 -> 107800 | I43: ='出金明細【17期】'!D42 -> 0 | J43: ='出金明細【17期】'!M42 -> 0 | K43: ='出金明細【17期】'!AD42 -> 107800
B44: 45116 | C44: =SUM(C43+D44-H44) -> 31640961 | D44: =E44+F44+G44 -> 0 | E44: ='入金明細【17期】'!D43 -> 0 | F44: ='入金明細【17期】'!M43 -> 0 | G44: ='入金明細【17期】'!T43 -> 0 | H44: =I44+J44+K44 -> 7810 | I44: ='出金明細【17期】'!D43 -> 7810 | J44: ='出金明細【17期】'!M43 -> 0 | K44: ='出金明細【17期】'!AD43 -> 0
B45: 45117 | C45: =SUM(C44+D45-H45) -> 15556117 | D45: =E45+F45+G45 -> 0 | E45: ='入金明細【17期】'!D44 -> 0 | F45: ='入金明細【17期】'!M44 -> 0 | G45: ='入金明細【17期】'!T44 -> 0 | H45: =I45+J45+K45 -> 16084844 | I45: ='出金明細【17期】'!D44 -> 132155 | J45: ='出金明細【17期】'!M44 -> 0 | K45: ='出金明細【17期】'!AD44 -> 15952689
B46: 45118 | C46: =SUM(C45+D46-H46) -> 22281556 | D46: =E46+F46+G46 -> 6855439 | E46: ='入金明細【17期】'!D45 -> 0 | F46: ='入金明細【17期】'!M45 -> 0 | G46: ='入金明細【17期】'!T45 -> 6855439 | H46: =I46+J46+K46 -> 130000 | I46: ='出金明細【17期】'!D45 -> 0 | J46: ='出金明細【17期】'!M45 -> 0 | K46: ='出金明細【17期】'!AD45 -> 130000
B47: 45119 | C47: =SUM(C46+D47-H47) -> 22281556 | D47: =E47+F47+G47 -> 0 | E47: ='入金明細【17期】'!D46 -> 0 | F47: ='入金明細【17期】'!M46 -> 0 | G47: ='入金明細【17期】'!T46 -> 0 | H47: =I47+J47+K47 -> 0 | I47: ='出金明細【17期】'!D46 -> 0 | J47: ='出金明細【17期】'!M46 -> 0 | K47: ='出金明細【17期】'!AD46 -> 0
B48: 45120 | C48: =SUM(C47+D48-H48) -> 22281556 | D48: =E48+F48+G48 -> 0 | E48: ='入金明細【17期】'!D47 -> 0 | F48: ='入金明細【17期】'!M47 -> 0 | G48: ='入金明細【17期】'!T47 -> 0 | H48: =I48+J48+K48 -> 0 | I48: ='出金明細【17期】'!D47 -> 0 | J48: ='出金明細【17期】'!M47 -> 0 | K48: ='出金明細【17期】'!AD47 -> 0
... B66: 45138 | C66: =SUM(C65+D66-H66) -> 41007661 | D66: =E66+F66+G66 -> 23047517 | E66: ='入金明細【17期】'!D65 -> 0 | F66: ='入金明細【17期】'!M65 -> 0 | G66: ='入金明細【17期】'!T65 -> 23047517 | H66: =I66+J66+K66 -> 7015830 | I66: ='出金明細【17期】'!D65 -> 436295 | J66: ='出金明細【17期】'!M65 -> 2251085 | K66: ='出金明細【17期】'!AD65 -> 4328450
B67: 7月合計 | C67: =SUM(D67-H67) -> 33814943 | D67: =SUM(D36:D66) -> 73090986 | E67: =SUM(E36:E66) -> 12470891 | F67: =SUM(F36:F66) -> 233540 | G67: =SUM(G36:G66) -> 60386555 | H67: =SUM(H36:H66) -> 39276043 | I67: =SUM(I36:I66) -> 6086612 | J67: =SUM(J36:J66) -> 8133375 | K67: =SUM(K36:K66) -> 25056056
B68: 累計 | C68: =SUM(D68-H68) -> 26544941 | D68: =D35+D67 -> 111819855 | E68: =E35+E67 -> 14977506 | F68: =F35+F67 -> 404174 | G68: =G35+G67 -> 96438175 | H68: =H35+H67 -> 85274914 | I68: =I35+I67 -> 16891497 | J68: =J35+J67 -> 33654247 | K68: =K35+K67 -> 34729170
B69: 45139 | C69: =SUM(C66+D69-H69) -> 40645816 | D69: =E69+F69+G69 -> 0 | E69: ='入金明細【17期】'!D68 -> 0 | F69: ='入金明細【17期】'!M68 | G69: ='入金明細【17期】'!T68 -> 0 | H69: =I69+J69+K69 -> 361845 | I69: ='出金明細【17期】'!D68 -> 0 | J69: ='出金明細【17期】'!M68 -> 288395 | K69: ='出金明細【17期】'!AD68 -> 73450
B70: 45140 | C70: =SUM(C69+D70-H70) -> 40645816 | D70: =E70+F70+G70 -> 0 | E70: ='入金明細【17期】'!D69 -> 0 | F70: ='入金明細【17期】'!M69 | G70: ='入金明細【17期】'!T69 -> 0 | H70: =I70+J70+K70 -> 0 | I70: ='出金明細【17期】'!D69 -> 0 | J70: ='出金明細【17期】'!M69 -> 0 | K70: ='出金明細【17期】'!AD69 -> 0
B71: 45141 | C71: =SUM(C70+D71-H71) -> 40645816 | D71: =E71+F71+G71 -> 0 | E71: ='入金明細【17期】'!D70 -> 0 | F71: ='入金明細【17期】'!M70 | G71: ='入金明細【17期】'!T70 -> 0 | H71: =I71+J71+K71 -> 0 | I71: ='出金明細【17期】'!D70 -> 0 | J71: ='出金明細【17期】'!M70 -> 0 | K71: ='出金明細【17期】'!AD70 -> 0
B72: 45142 | C72: =SUM(C71+D72-H72) -> 39771747 | D72: =E72+F72+G72 -> 0 | E72: ='入金明細【17期】'!D71 -> 0 | F72: ='入金明細【17期】'!M71 | G72: ='入金明細【17期】'!T71 -> 0 | H72: =I72+J72+K72 -> 874069 | I72: ='出金明細【17期】'!D71 -> 0 | J72: ='出金明細【17期】'!M71 -> 0 | K72: ='出金明細【17期】'!AD71 -> 874069
B73: 45143 | C73: =SUM(C72+D73-H73) -> 39771747 | D73: =E73+F73+G73 -> 0 | E73: ='入金明細【17期】'!D72 -> 0 | F73: ='入金明細【17期】'!M72 -> 0 | G73: ='入金明細【17期】'!T72 -> 0 | H73: =I73+J73+K73 -> 0 | I73: ='出金明細【17期】'!D72 -> 0 | J73: ='出金明細【17期】'!M72 -> 0 | K73: ='出金明細【17期】'!AD72 -> 0
B74: 45144 | C74: =SUM(C73+D74-H74) -> 41833037 | D74: =E74+F74+G74 -> 2061290 | E74: ='入金明細【17期】'!D73 -> 0 | F74: ='入金明細【17期】'!M73 -> 0 | G74: ='入金明細【17期】'!T73 -> 2061290 | H74: =I74+J74+K74 -> 0 | I74: ='出金明細【17期】'!D73 -> 0 | J74: ='出金明細【17期】'!M73 -> 0 | K74: ='出金明細【17期】'!AD73 -> 0
B75: 45145 | C75: =SUM(C74+D75-H75) -> 42135757 | D75: =E75+F75+G75 -> 303930 | E75: ='入金明細【17期】'!D74 -> 0 | F75: ='入金明細【17期】'!M74 -> 0 | G75: ='入金明細【17期】'!T74 -> 303930 | H75: =I75+J75+K75 -> 1210 | I75: ='出金明細【17期】'!D74 -> 1210 | J75: ='出金明細【17期】'!M74 -> 0 | K75: ='出金明細【17期】'!AD74 -> 0
B76: 45146 | C76: =SUM(C75+D76-H76) -> 39018843 | D76: =E76+F76+G76 -> 17650 | E76: ='入金明細【17期】'!D75 -> 0 | F76: ='入金明細【17期】'!M75 -> 0 | G76: ='入金明細【17期】'!T75 -> 17650 | H76: =I76+J76+K76 -> 3134564 | I76: ='出金明細【17期】'!D75 -> 0 | J76: ='出金明細【17期】'!M75 -> 2745129 | K76: ='出金明細【17期】'!AD75 -> 389435
B77: 45147 | C77: =SUM(C76+D77-H77) -> 39018843 | D77: =E77+F77+G77 -> 0 | E77: ='入金明細【17期】'!D76 -> 0 | F77: ='入金明細【17期】'!M76 -> 0 | G77: ='入金明細【17期】'!T76 -> 0 | H77: =I77+J77+K77 -> 0 | I77: ='出金明細【17期】'!D76 -> 0 | J77: ='出金明細【17期】'!M76 -> 0 | K77: ='出金明細【17期】'!AD76 -> 0
B78: 45148 | C78: =SUM(C77+D78-H78) -> 39018843 | D78: =E78+F78+G78 -> 0 | E78: ='入金明細【17期】'!D77 -> 0 | F78: ='入金明細【17期】'!M77 -> 0 | G78: ='入金明細【17期】'!T77 -> 0 | H78: =I78+J78+K78 -> 0 | I78: ='出金明細【17期】'!D77 -> 0 | J78: ='出金明細【17期】'!M77 -> 0 | K78: ='出金明細【17期】'!AD77 -> 0
B79: 45149 | C79: =SUM(C78+D79-H79) -> 39043843 | D79: =E79+F79+G79 -> 25000 | E79: ='入金明細【17期】'!D78 -> 0 | F79: ='入金明細【17期】'!M78 -> 0 | G79: ='入金明細【17期】'!T78 -> 25000 | H79: =I79+J79+K79 -> 0 | I79: ='出金明細【17期】'!D78 -> 0 | J79: ='出金明細【17期】'!M78 -> 0 | K79: ='出金明細【17期】'!AD78 -> 0
B80: 45150 | C80: =SUM(C79+D80-H80) -> 35683068 | D80: =E80+F80+G80 -> 77831 | E80: ='入金明細【17期】'!D79 -> 0 | F80: ='入金明細【17期】'!M79 -> 0 | G80: ='入金明細【17期】'!T79 -> 77831 | H80: =I80+J80+K80 -> 3438606 | I80: ='出金明細【17期】'!D79 -> 19085 | J80: ='出金明細【17期】'!M79 -> 0 | K80: ='出金明細【17期】'!AD79 -> 3419521
B81: 45151 | C81: =SUM(C80+D81-H81) -> 35679108 | D81: =E81+F81+G81 -> 0 | E81: ='入金明細【17期】'!D80 -> 0 | F81: ='入金明細【17期】'!M80 -> 0 | G81: ='入金明細【17期】'!T80 -> 0 | H81: =I81+J81+K81 -> 3960 | I81: ='出金明細【17期】'!D80 -> 3960 | J81: ='出金明細【17期】'!M80 -> 0 | K81: ='出金明細【17期】'!AD80 -> 0
... B99: 45169 | C99: =SUM(C98+D99-H99) -> 30559421 | D99: =E99+F99+G99 -> 0 | E99: ='入金明細【17期】'!D98 -> 0 | F99: ='入金明細【17期】'!M98 -> 0 | G99: ='入金明細【17期】'!T98 -> 0 | H99: =I99+J99+K99 -> 28602 | I99: ='出金明細【17期】'!D98 -> 28602 | J99: ='出金明細【17期】'!M98 -> 0 | K99: ='出金明細【17期】'!AD98 -> 0
B100: 8月合計 | C100: =SUM(D100-H100) -> -10448240 | D100: =SUM(D69:D99) -> 449457225 | E100: =SUM(E69:E99) -> 437162575 | F100: =SUM(F69:F99) -> 243391 | G100: =SUM(G69:G99) -> 12051259 | H100: =SUM(H69:H99) -> 459905465 | I100: =SUM(I69:I99) -> 427502160 | J100: =SUM(J69:J99) -> 25978437 | K100: =SUM(K69:K99) -> 6424868
B101: 累計 | C101: =SUM(D101-H101) -> 16096701 | D101: =D68+D100 -> 561277080 | E101: =E68+E100 -> 452140081 | F101: =F68+F100 -> 647565 | G101: =G68+G100 -> 108489434 | H101: =H68+H100 -> 545180379 | I101: =I68+I100 -> 444393657 | J101: =J68+J100 -> 59632684 | K101: =K68+K100 -> 41154038
B102: 44440 | C102: =SUM(C99+D102-H102) -> 28315122 | D102: =E102+F102+G102 -> 149182 | E102: ='入金明細【17期】'!D101 -> 0 | F102: ='入金明細【17期】'!M101 -> 0 | G102: ='入金明細【17期】'!T101 -> 149182 | H102: =I102+J102+K102 -> 2393481 | I102: ='出金明細【17期】'!D101 -> 1489360 | J102: ='出金明細【17期】'!M101 -> 0 | K102: ='出金明細【17期】'!AD101 -> 904121
B103: 44441 | C103: =SUM(C102+D103-H103) -> 28216031 | D103: =E103+F103+G103 -> 0 | E103: ='入金明細【17期】'!D102 -> 0 | F103: ='入金明細【17期】'!M102 -> 0 | G103: ='入金明細【17期】'!T102 -> 0 | H103: =I103+J103+K103 -> 99091 | I103: ='出金明細【17期】'!D102 -> 0 | J103: ='出金明細【17期】'!M102 -> 20000 | K103: ='出金明細【17期】'!AD102 -> 79091
B104: 44442 | C104: =SUM(C103+D104-H104) -> 28216031 | D104: =E104+F104+G104 -> 0 | E104: ='入金明細【17期】'!D103 -> 0 | F104: ='入金明細【17期】'!M103 -> 0 | G104: ='入金明細【17期】'!T103 -> 0 | H104: =I104+J104+K104 -> 0 | I104: ='出金明細【17期】'!D103 -> 0 | J104: ='出金明細【17期】'!M103 -> 0 | K104: ='出金明細【17期】'!AD103 -> 0
B105: 44443 | C105: =SUM(C104+D105-H105) -> 30239771 | D105: =E105+F105+G105 -> 2348640 | E105: ='入金明細【17期】'!D104 -> 0 | F105: ='入金明細【17期】'!M104 -> 0 | G105: ='入金明細【17期】'!T104 -> 2348640 | H105: =I105+J105+K105 -> 324900 | I105: ='出金明細【17期】'!D104 -> 0 | J105: ='出金明細【17期】'!M104 -> 0 | K105: ='出金明細【17期】'!AD104 -> 324900
B106: 44444 | C106: =SUM(C105+D106-H106) -> 31106699 | D106: =E106+F106+G106 -> 871944 | E106: ='入金明細【17期】'!D105 -> 0 | F106: ='入金明細【17期】'!M105 -> 0 | G106: ='入金明細【17期】'!T105 -> 871944 | H106: =I106+J106+K106 -> 5016 | I106: ='出金明細【17期】'!D105 -> 0 | J106: ='出金明細【17期】'!M105 -> 0 | K106: ='出金明細【17期】'!AD105 -> 5016
B107: 44445 | C107: =SUM(C106+D107-H107) -> 31106699 | D107: =E107+F107+G107 -> 0 | E107: ='入金明細【17期】'!D106 -> 0 | F107: ='入金明細【17期】'!M106 -> 0 | G107: ='入金明細【17期】'!T106 -> 0 | H107: =I107+J107+K107 -> 0 | I107: ='出金明細【17期】'!D106 -> 0 | J107: ='出金明細【17期】'!M106 -> 0 | K107: ='出金明細【17期】'!AD106 -> 0
B108: 44446 | C108: =SUM(C107+D108-H108) -> 31106699 | D108: =E108+F108+G108 -> 0 | E108: ='入金明細【17期】'!D107 -> 0 | F108: ='入金明細【17期】'!M107 -> 0 | G108: ='入金明細【17期】'!T107 -> 0 | H108: =I108+J108+K108 -> 0 | I108: ='出金明細【17期】'!D107 -> 0 | J108: ='出金明細【17期】'!M107 -> 0 | K108: ='出金明細【17期】'!AD107 -> 0
B109: 44447 | C109: =SUM(C108+D109-H109) -> 31105489 | D109: =E109+F109+G109 -> 0 | E109: ='入金明細【17期】'!D108 -> 0 | F109: ='入金明細【17期】'!M108 -> 0 | G109: ='入金明細【17期】'!T108 -> 0 | H109: =I109+J109+K109 -> 1210 | I109: ='出金明細【17期】'!D108 -> 1210 | J109: ='出金明細【17期】'!M108 -> 0 | K109: ='出金明細【17期】'!AD108 -> 0
B110: 44448 | C110: =SUM(C109+D110-H110) -> 31105489 | D110: =E110+F110+G110 -> 0 | E110: ='入金明細【17期】'!D109 -> 0 | F110: ='入金明細【17期】'!M109 -> 0 | G110: ='入金明細【17期】'!T109 -> 0 | H110: =I110+J110+K110 -> 0 | I110: ='出金明細【17期】'!D109 -> 0 | J110: ='出金明細【17期】'!M109 -> 0 | K110: ='出金明細【17期】'!AD109 -> 0
B111: 44449 | C111: =SUM(C110+D111-H111) -> 26281567 | D111: =E111+F111+G111 -> 6000 | E111: ='入金明細【17期】'!D110 -> 0 | F111: ='入金明細【17期】'!M110 -> 0 | G111: ='入金明細【17期】'!T110 -> 6000 | H111: =I111+J111+K111 -> 4829922 | I111: ='出金明細【17期】'!D110 -> 22220 | J111: ='出金明細【17期】'!M110 -> 0 | K111: ='出金明細【17期】'!AD110 -> 4807702
B112: 44450 | C112: =SUM(C111+D112-H112) -> 26244607 | D112: =E112+F112+G112 -> 0 | E112: ='入金明細【17期】'!D111 -> 0 | F112: ='入金明細【17期】'!M111 -> 0 | G112: ='入金明細【17期】'!T111 -> 0 | H112: =I112+J112+K112 -> 36960 | I112: ='出金明細【17期】'!D111 -> 4620 | J112: ='出金明細【17期】'!M111 -> 0 | K112: ='出金明細【17期】'!AD111 -> 32340
B113: 44451 | C113: =SUM(C112+D113-H113) -> 26227758 | D113: =E113+F113+G113 -> 0 | E113: ='入金明細【17期】'!D112 -> 0 | F113: ='入金明細【17期】'!M112 -> 0 | G113: ='入金明細【17期】'!T112 -> 0 | H113: =I113+J113+K113 -> 16849 | I113: ='出金明細【17期】'!D112 -> 0 | J113: ='出金明細【17期】'!M112 -> 0 | K113: ='出金明細【17期】'!AD112 -> 16849
B114: 44452 | C114: =SUM(C113+D114-H114) -> 26227758 | D114: =E114+F114+G114 -> 0 | E114: ='入金明細【17期】'!D113 -> 0 | F114: ='入金明細【17期】'!M113 -> 0 | G114: ='入金明細【17期】'!T113 -> 0 | H114: =I114+J114+K114 -> 0 | I114: ='出金明細【17期】'!D113 -> 0 | J114: ='出金明細【17期】'!M113 -> 0 | K114: ='出金明細【17期】'!AD113 -> 0
... B131: 44469 | C131: =SUM(C130+D131-H131) -> 20634994 | D131: =E131+F131+G131 -> 3273364 | E131: ='入金明細【17期】'!D130 -> 0 | F131: ='入金明細【17期】'!M130 -> 0 | G131: ='入金明細【17期】'!T130 -> 3273364 | H131: =I131+J131+K131 -> 4467306 | I131: ='出金明細【17期】'!D130 -> 1659811 | J131: ='出金明細【17期】'!M130 -> 2805295 | K131: ='出金明細【17期】'!AD130 -> 2200
B132: 9月合計 | C132: =SUM(D132-H132) -> -9924427 | D132: =SUM(D102:D131) -> 10271624 | E132: =SUM(E102:E131) -> 9500 | F132: =SUM(F102:F131) -> 421610 | G132: =SUM(G102:G131) -> 9840514 | H132: =SUM(H102:H131) -> 20196051 | I132: =SUM(I102:I131) -> 7437812 | J132: =SUM(J102:J131) -> 4574892 | K132: =SUM(K102:K131) -> 8183347
B133: 累計 | C133: =SUM(D133-H133) -> 6172274 | D133: =D101+D132 -> 571548704 | E133: =E101+E132 -> 452149581 | F133: =F101+F132 -> 1069175 | G133: =G101+G132 -> 118329948 | H133: =H101+H132 -> 565376430 | I133: =I101+I132 -> 451831469 | J133: =J101+J132 -> 64207576 | K133: =K101+K132 -> 49337385
B134: 44470 | C134: =SUM(C131+D134-H134) -> 20634994 | D134: =E134+F134+G134 -> 0 | E134: ='入金明細【17期】'!D133 -> 0 | F134: ='入金明細【17期】'!M133 | G134: ='入金明細【17期】'!T133 -> 0 | H134: =I134+J134+K134 -> 0 | I134: ='出金明細【17期】'!D133 -> 0 | J134: ='出金明細【17期】'!M133 -> 0 | K134: ='出金明細【17期】'!AD133 -> 0
B135: 44471 | C135: =SUM(C134+D135-H135) -> 20464700 | D135: =E135+F135+G135 -> 0 | E135: ='入金明細【17期】'!D134 -> 0 | F135: ='入金明細【17期】'!M134 | G135: ='入金明細【17期】'!T134 -> 0 | H135: =I135+J135+K135 -> 170294 | J135: ='出金明細【17期】'!M134 -> 0 | K135: ='出金明細【17期】'!AD134 -> 170294
B136: 44472 | C136: =SUM(C135+D136-H136) -> 20640848 | D136: =E136+F136+G136 -> 176148 | E136: ='入金明細【17期】'!D135 -> 0 | F136: ='入金明細【17期】'!M135 -> 0 | G136: ='入金明細【17期】'!T135 -> 176148 | H136: =I136+J136+K136 -> 0 | I136: ='出金明細【17期】'!D135 -> 0 | J136: ='出金明細【17期】'!M135 -> 0 | K136: ='出金明細【17期】'!AD135 -> 0
B137: 44473 | C137: =SUM(C136+D137-H137) -> 20665848 | D137: =E137+F137+G137 -> 25000 | E137: ='入金明細【17期】'!D136 -> 0 | F137: ='入金明細【17期】'!M136 -> 0 | G137: ='入金明細【17期】'!T136 -> 25000 | H137: =I137+J137+K137 -> 0 | I137: ='出金明細【17期】'!D136 -> 0 | J137: ='出金明細【17期】'!M136 -> 0 | K137: ='出金明細【17期】'!AD136 -> 0
B138: 44474 | C138: =SUM(C137+D138-H138) -> 20665848 | D138: =E138+F138+G138 -> 0 | E138: ='入金明細【17期】'!D137 -> 0 | F138: ='入金明細【17期】'!M137 -> 0 | G138: ='入金明細【17期】'!T137 -> 0 | H138: =I138+J138+K138 -> 0 | I138: ='出金明細【17期】'!D137 -> 0 | J138: ='出金明細【17期】'!M137 -> 0 | K138: ='出金明細【17期】'!AD137 -> 0
B139: 44475 | C139: =SUM(C138+D139-H139) -> 20378898 | D139: =E139+F139+G139 -> 0 | E139: ='入金明細【17期】'!D138 -> 0 | F139: ='入金明細【17期】'!M138 -> 0 | G139: ='入金明細【17期】'!T138 -> 0 | H139: =I139+J139+K139 -> 286950 | I139: ='出金明細【17期】'!D138 -> 0 | J139: ='出金明細【17期】'!M138 -> 0 | K139: ='出金明細【17期】'!AD138 -> 286950
B140: 44476 | C140: =SUM(C139+D140-H140) -> 20377688 | D140: =E140+F140+G140 -> 0 | E140: ='入金明細【17期】'!D139 -> 0 | F140: ='入金明細【17期】'!M139 -> 0 | G140: ='入金明細【17期】'!T139 -> 0 | H140: =I140+J140+K140 -> 1210 | I140: ='出金明細【17期】'!D139 -> 1210 | J140: ='出金明細【17期】'!M139 -> 0 | K140: ='出金明細【17期】'!AD139 -> 0
B141: 44477 | C141: =SUM(C140+D141-H141) -> 40377688 | D141: =E141+F141+G141 -> 20000000 | E141: ='入金明細【17期】'!D140 -> 20000000 | F141: ='入金明細【17期】'!M140 -> 0 | G141: ='入金明細【17期】'!T140 -> 0 | H141: =I141+J141+K141 -> 0 | I141: ='出金明細【17期】'!D140 -> 0 | J141: ='出金明細【17期】'!M140 -> 0 | K141: ='出金明細【17期】'!AD140 -> 0
B142: 44478 | C142: =SUM(C141+D142-H142) -> 35986273 | D142: =E142+F142+G142 -> 290510 | E142: ='入金明細【17期】'!D141 -> 0 | F142: ='入金明細【17期】'!M141 -> 0 | G142: ='入金明細【17期】'!T141 -> 290510 | H142: =I142+J142+K142 -> 4681925 | I142: ='出金明細【17期】'!D141 -> 4290 | J142: ='出金明細【17期】'!M141 -> 4629890 | K142: ='出金明細【17期】'!AD141 -> 47745
B143: 44479 | C143: =SUM(C142+D143-H143) -> 11667043 | D143: =E143+F143+G143 -> 1068150 | E143: ='入金明細【17期】'!D142 -> 0 | F143: ='入金明細【17期】'!M142 -> 0 | G143: ='入金明細【17期】'!T142 -> 1068150 | H143: =I143+J143+K143 -> 25387380 | I143: ='出金明細【17期】'!D142 -> 17820 | J143: ='出金明細【17期】'!M142 -> 20985650 | K143: ='出金明細【17期】'!AD142 -> 4383910
B144: 44480 | C144: =SUM(C143+D144-H144) -> 11667043 | D144: =E144+F144+G144 -> 0 | E144: ='入金明細【17期】'!D143 -> 0 | F144: ='入金明細【17期】'!M143 -> 0 | G144: ='入金明細【17期】'!T143 -> 0 | H144: =I144+J144+K144 -> 0 | I144: ='出金明細【17期】'!D143 -> 0 | J144: ='出金明細【17期】'!M143 -> 0 | K144: ='出金明細【17期】'!AD143 -> 0
B145: 44481 | C145: =SUM(C144+D145-H145) -> 11667043 | D145: =E145+F145+G145 -> 0 | E145: ='入金明細【17期】'!D144 -> 0 | F145: ='入金明細【17期】'!M144 -> 0 | G145: ='入金明細【17期】'!T144 -> 0 | H145: =I145+J145+K145 -> 0 | I145: ='出金明細【17期】'!D144 -> 0 | J145: ='出金明細【17期】'!M144 -> 0 | K145: ='出金明細【17期】'!AD144 -> 0
B146: 44482 | C146: =SUM(C145+D146-H146) -> 11667043 | D146: =E146+F146+G146 -> 0 | E146: ='入金明細【17期】'!D145 -> 0 | F146: ='入金明細【17期】'!M145 -> 0 | G146: ='入金明細【17期】'!T145 -> 0 | H146: =I146+J146+K146 -> 0 | I146: ='出金明細【17期】'!D145 -> 0 | J146: ='出金明細【17期】'!M145 -> 0 | K146: ='出金明細【17期】'!AD145 -> 0
B147: 44483 | C147: =SUM(C146+D147-H147) -> 12557043 | D147: =E147+F147+G147 -> 890000 | E147: ='入金明細【17期】'!D146 -> 0 | F147: ='入金明細【17期】'!M146 -> 0 | G147: ='入金明細【17期】'!T146 -> 890000 | H147: =I147+J147+K147 -> 0 | I147: ='出金明細【17期】'!D146 -> 0 | J147: ='出金明細【17期】'!M146 -> 0 | K147: ='出金明細【17期】'!AD146 -> 0
... B164: 44500 | C164: =SUM(C163+D164-H164) -> 11680076 | D164: =E164+F164+G164 -> 2275589 | E164: ='入金明細【17期】'!D163 -> 0 | F164: ='入金明細【17期】'!M163 -> 0 | G164: ='入金明細【17期】'!T163 -> 2275589 | H164: =I164+J164+K164 -> 7937245 | I164: ='出金明細【17期】'!D163 -> 1625950 | J164: ='出金明細【17期】'!M163 -> 5540349 | K164: ='出金明細【17期】'!AD163 -> 770946
B165: 10月合計 | C165: =SUM(D165-H165) -> -8954918 | D165: =SUM(D134:D164) -> 38791296 | H165: =SUM(H134:H164) -> 47746214
B166: 累計 | C166: =SUM(D166-H166) -> -2782644 | D166: =D133+D165 -> 610340000 | H166: =H133+H165 -> 613122644
B167: 44501 | C167: =SUM(C164+D167-H167) -> 11680076 | D167: =E167+F167+G167 -> 0 | E167: ='入金明細【17期】'!D165 -> 0 | F167: ='入金明細【17期】'!M165 -> 0 | G167: ='入金明細【17期】'!T165 -> 0 | H167: =I167+J167+K167 -> 0 | I167: ='出金明細【17期】'!D165 -> 0 | J167: ='出金明細【17期】'!M165 -> 0 | K167: ='出金明細【17期】'!AD165 -> 0
B168: 44502 | C168: =SUM(C167+D168-H168) -> 11680076 | D168: =E168+F168+G168 -> 0 | E168: ='入金明細【17期】'!D166 -> 0 | F168: ='入金明細【17期】'!M166 -> 0 | G168: ='入金明細【17期】'!T166 -> 0 | H168: =I168+J168+K168 -> 0 | I168: ='出金明細【17期】'!D166 -> 0 | J168: ='出金明細【17期】'!M166 -> 0 | K168: ='出金明細【17期】'!AD166 -> 0
B169: 44503 | C169: =SUM(C168+D169-H169) -> 11680076 | D169: =E169+F169+G169 -> 0 | E169: ='入金明細【17期】'!D167 -> 0 | F169: ='入金明細【17期】'!M167 -> 0 | G169: ='入金明細【17期】'!T167 -> 0 | H169: =I169+J169+K169 -> 0 | I169: ='出金明細【17期】'!D167 -> 0 | J169: ='出金明細【17期】'!M167 -> 0 | K169: ='出金明細【17期】'!AD167 -> 0
B170: 44504 | C170: =SUM(C169+D170-H170) -> 11448412 | D170: =E170+F170+G170 -> 0 | E170: ='入金明細【17期】'!D168 -> 0 | F170: ='入金明細【17期】'!M168 -> 0 | G170: ='入金明細【17期】'!T168 -> 0 | H170: =I170+J170+K170 -> 231664 | I170: ='出金明細【17期】'!D168 -> 0 | J170: ='出金明細【17期】'!M168 -> 0 | K170: ='出金明細【17期】'!AD168 -> 231664
B171: 44505 | C171: =SUM(C170+D171-H171) -> 11829012 | D171: =E171+F171+G171 -> 380600 | E171: ='入金明細【17期】'!D169 -> 0 | F171: ='入金明細【17期】'!M169 -> 0 | G171: ='入金明細【17期】'!T169 -> 380600 | H171: =I171+J171+K171 -> 0 | I171: ='出金明細【17期】'!D169 -> 0 | J171: ='出金明細【17期】'!M169 -> 0 | K171: ='出金明細【17期】'!AD169 -> 0
B172: 44506 | C172: =SUM(C171+D172-H172) -> 11813097 | D172: =E172+F172+G172 -> 0 | E172: ='入金明細【17期】'!D170 -> 0 | F172: ='入金明細【17期】'!M170 -> 0 | G172: ='入金明細【17期】'!T170 -> 0 | H172: =I172+J172+K172 -> 15915 | I172: ='出金明細【17期】'!D170 -> 0 | J172: ='出金明細【17期】'!M170 -> 0 | K172: ='出金明細【17期】'!AD170 -> 15915
B173: 44507 | C173: =SUM(C172+D173-H173) -> 11661234 | D173: =E173+F173+G173 -> 0 | E173: ='入金明細【17期】'!D171 -> 0 | F173: ='入金明細【17期】'!M171 -> 0 | G173: ='入金明細【17期】'!T171 -> 0 | H173: =I173+J173+K173 -> 151863 | I173: ='出金明細【17期】'!D171 -> 1210 | J173: ='出金明細【17期】'!M171 -> 0 | K173: ='出金明細【17期】'!AD171 -> 150653
B174: 44508 | C174: =SUM(C173+D174-H174) -> 11661234 | D174: =E174+F174+G174 -> 0 | E174: ='入金明細【17期】'!D172 -> 0 | F174: ='入金明細【17期】'!M172 -> 0 | G174: ='入金明細【17期】'!T172 -> 0 | H174: =I174+J174+K174 -> 0 | I174: ='出金明細【17期】'!D172 -> 0 | J174: ='出金明細【17期】'!M172 -> 0 | K174: ='出金明細【17期】'!AD172 -> 0
B175: 44509 | C175: =SUM(C174+D175-H175) -> 11656724 | D175: =E175+F175+G175 -> 0 | E175: ='入金明細【17期】'!D173 -> 0 | F175: ='入金明細【17期】'!M173 -> 0 | G175: ='入金明細【17期】'!T173 -> 0 | H175: =I175+J175+K175 -> 4510 | I175: ='出金明細【17期】'!D173 -> 4510 | J175: ='出金明細【17期】'!M173 -> 0 | K175: ='出金明細【17期】'!AD173 -> 0
B176: 44510 | C176: =SUM(C175+D176-H176) -> 8214255 | D176: =E176+F176+G176 -> 134447 | E176: ='入金明細【17期】'!D174 -> 0 | F176: ='入金明細【17期】'!M174 -> 0 | G176: ='入金明細【17期】'!T174 -> 134447 | H176: =I176+J176+K176 -> 3576916 | I176: ='出金明細【17期】'!D174 -> 21560 | J176: ='出金明細【17期】'!M174 -> 0 | K176: ='出金明細【17期】'!AD174 -> 3555356
B177: 44511 | C177: =SUM(C176+D177-H177) -> 8214255 | D177: =E177+F177+G177 -> 0 | E177: ='入金明細【17期】'!D175 -> 0 | F177: ='入金明細【17期】'!M175 -> 0 | G177: ='入金明細【17期】'!T175 -> 0 | H177: =I177+J177+K177 -> 0 | I177: ='出金明細【17期】'!D175 -> 0 | J177: ='出金明細【17期】'!M175 -> 0 | K177: ='出金明細【17期】'!AD175 -> 0
B178: 44512 | C178: =SUM(C177+D178-H178) -> 8214255 | D178: =E178+F178+G178 -> 0 | E178: ='入金明細【17期】'!D176 -> 0 | F178: ='入金明細【17期】'!M176 -> 0 | G178: ='入金明細【17期】'!T176 -> 0 | H178: =I178+J178+K178 -> 0 | I178: ='出金明細【17期】'!D176 -> 0 | J178: ='出金明細【17期】'!M176 -> 0 | K178: ='出金明細【17期】'!AD176 -> 0
B179: 44513 | C179: =SUM(C178+D179-H179) -> 8046223 | D179: =E179+F179+G179 -> 50000 | E179: ='入金明細【17期】'!D177 -> 50000 | F179: ='入金明細【17期】'!M177 -> 0 | G179: ='入金明細【17期】'!T177 -> 0 | H179: =I179+J179+K179 -> 218032 | I179: ='出金明細【17期】'!D177 -> 100000 | J179: ='出金明細【17期】'!M177 -> 0 | K179: ='出金明細【17期】'!AD177 -> 118032
... B196: 44530 | C196: =SUM(C195+D196-H196) -> 9463211 | D196: =E196+F196+G196 -> 0 | E196: ='入金明細【17期】'!D194 -> 0 | F196: ='入金明細【17期】'!M194 -> 0 | G196: ='入金明細【17期】'!T194 -> 0 | H196: =I196+J196+K196 -> 954039 | I196: ='出金明細【17期】'!D194 -> 954039 | J196: ='出金明細【17期】'!M194 -> 0 | K196: ='出金明細【17期】'!AD194 -> 0
B197: 1１月合計 | C197: =SUM(D197-H197) -> -2216865 | D197: =SUM(D167:D196) -> 27107980 | H197: =SUM(H167:H196) -> 29324845
B198: 累計 | C198: =SUM(D198-H198) -> -4999509 | D198: =D166+D197 -> 637447980 | H198: =H166+H197 -> 642447489
...

Sheet 入金明細【17期】
C1: ２０２5年６月‐２０２6年５月入金
C2: 入金日次 | D2: 金融小計 | E2: 金融機関関連 | M2: 保険小計 | N2: 保険関連 | T2: お客様小計 | U2: お客様関連
B3: 44348 | C3: =D3+M3+T3 -> 0 | D3: =F3+H3+J3+L3 -> 0 | M3: =O3+Q3+S3 -> 0 | T3: =V3+X3+Z3+AB3+AD3+AF3+AH3+AJ3+AV3+AL3+AN3+AP3+AR3+'入金明細【17期】'!AT3 -> 0
B4: 44349 | C4: =D4+M4+T4 -> 0 | D4: =F4+H4+J4+L4 -> 0 | M4: =O4+Q4+S4 -> 0 | T4: =V4+X4+Z4+AB4+AD4+AF4+AH4+AJ4+AV4+AL4+AN4+AP4+AR4+AT4 -> 0
B5: 45446 | C5: =D5+M5+T5 -> 1930350 | D5: =F5+H5+J5+L5 -> 600000 | E5: 笠信(小口現金分) | F5: 600000 | M5: =O5+Q5+S5 -> 0 | T5: =V5+X5+Z5+AB5+AD5+AF5+AH5+AJ5+AV5+AL5+AN5+AP5+AR5+AT5 -> 1330350 | U5: 映ｸﾗ㈱様ﾐﾓｻﾞ薬局様日産ﾘｰﾌ | V5: 1330350
B6: 44351 | C6: =D6+M6+T6 -> 77000 | D6: =F6+H6+J6+L6 -> 0 | M6: =O6+Q6+S6 -> 0 | T6: =V6+X6+Z6+AB6+AD6+AF6+AH6+AJ6+AV6+AL6+AN6+AP6+AR6+AT6 -> 77000 | U6: あいおいﾆｯｾｲ同和様 | V6: 77000
B7: 44352 | C7: =D7+M7+T7 -> 65780 | D7: =F7+H7+J7+L7 -> 0 | M7: =O7+Q7+S7 -> 0 | T7: =V7+X7+Z7+AB7+AD7+AF7+AH7+AJ7+AV7+AL7+AN7+AP7+AR7+AT7 -> 65780 | U7: おもてちょう不動産㈱様 | V7: 65780
B8: 44353 | C8: =D8+M8+T8 -> 0 | D8: =F8+H8+J8+L8 -> 0 | M8: =O8+Q8+S8 -> 0 | T8: =V8+X8+Z8+AB8+AD8+AF8+AH8+AJ8+AV8+AL8+AN8+AP8+AR8+AT8 -> 0
B9: 44354 | C9: =D9+M9+T9 -> 25000 | D9: =F9+H9+J9+L9 -> 0 | M9: =O9+Q9+S9 -> 0 | T9: =V9+X9+Z9+AB9+AD9+AF9+AH9+AJ9+AV9+AL9+AN9+AP9+AR9+AT9 -> 25000 | U9: 土肥良太郎様 | V9: 25000
B10: 45816 | C10: =D10+M10+T10 -> 0 | D10: =F10+H10+J10+L10 -> 0 | M10: =O10+Q10+S10 -> 0 | T10: =V10+X10+Z10+AB10+AD10+AF10+AH10+AJ10+AV10+AL10+AN10+AP10+AR10+AT10 -> 0
B11: 44356 | C11: =D11+M11+T11 -> 248 | D11: =F11+H11+J11+L11 -> 248 | E11: 調整分 | F11: 248 | M11: =O11+Q11+S11 -> 0 | T11: =V11+X11+Z11+AB11+AD11+AF11+AH11+AJ11+AV11+AL11+AN11+AP11+AR11+AT11 -> 0
B12: 44357 | C12: =D12+M12+T12 -> 0 | D12: =F12+H12+J12+L12 -> 0 | M12: =O12+Q12+S12 -> 0 | T12: =V12+X12+Z12+AB12+AD12+AF12+AH12+AJ12+AV12+AL12+AN12+AP12+AR12+AT12 -> 0
B13: 44358 | C13: =D13+M13+T13 -> 2009574 | D13: =F13+H13+J13+L13 -> 0 | M13: =O13+Q13+S13 -> 0 | T13: =V13+X13+Z13+AB13+AD13+AF13+AH13+AJ13+AV13+AL13+AN13+AP13+AR13+AT13 -> 2009574 | U13: 東京海上日動 | V13: 2009574
B14: 44359 | C14: =D14+M14+T14 -> 0 | D14: =F14+H14+J14+L14 -> 0 | M14: =O14+Q14+S14 -> 0 | T14: =V14+X14+Z14+AB14+AD14+AF14+AH14+AJ14+AV14+AL14+AN14+AP14+AR14+AT14 -> 0
B15: 44360 | C15: =D15+M15+T15 -> 1900000 | D15: =F15+H15+J15+L15 -> 1900000 | E15: 小口現金より広銀本社へ資金移動（幸洋板金入金分） | F15: 1900000 | M15: =O15+Q15+S15 -> 0 | T15: =V15+X15+Z15+AB15+AD15+AF15+AH15+AJ15+AV15+AL15+AN15+AP15+AR15+AT15 -> 0
B16: 44361 | C16: =D16+M16+T16 -> 0 | D16: =F16+H16+J16+L16 -> 0 | M16: =O16+Q16+S16 -> 0 | T16: =V16+X16+Z16+AB16+AD16+AF16+AH16+AJ16+AV16+AL16+AN16+AP16+AR16+AT16 -> 0
B17: 44362 | C17: =D17+M17+T17 -> 0 | D17: =F17+H17+J17+L17 -> 0 | M17: =O17+Q17+S17 -> 0 | T17: =V17+X17+Z17+AB17+AD17+AF17+AH17+AJ17+AV17+AL17+AN17+AP17+AR17+AT17 -> 0
B18: 44363 | C18: =D18+M18+T18 -> 718547 | D18: =F18+H18+J18+L18 -> 0 | M18: =O18+Q18+S18 -> 138826 | N18: 三井住友海上火災保険㈱代理店保険手数料 | O18: 138826 | T18: =V18+X18+Z18+AB18+AD18+AF18+AH18+AJ18+AV18+AL18+AN18+AP18+AR18+AT18 -> 579721 | U18: ｷﾑﾗﾕﾆﾃｨ様 | V18: 42680 | W18: 中銀JCB | X18: 73547 | Y18: 中銀VISA | Z18: 463494
B19: 44364 | C19: =D19+M19+T19 -> 1815128 | D19: =F19+H19+J19+L19 -> 0 | M19: =O19+Q19+S19 -> 31808 | N19: 東京海上日動 代理店保険手数料 | O19: 31808 | T19: =V19+X19+Z19+AB19+AD19+AF19+AH19+AJ19+AV19+AL19+AN19+AP19+AR19+AT19 -> 1783320 | U19: 日新火災海上保険㈱ 安保雅文様 | V19: 1783320
B20: 44365 | C20: =D20+M20+T20 -> 1592 | D20: =F20+H20+J20+L20 -> 1592 | E20: 配当金出資 | F20: 1592 | M20: =O20+Q20+S20 -> 0 | T20: =V20+X20+Z20+AB20+AD20+AF20+AH20+AJ20+AV20+AL20+AN20+AP20+AR20+AT20 -> 0
B21: 44366 | C21: =D21+M21+T21 -> 391080 | D21: =F21+H21+J21+L21 -> 0 | M21: =O21+Q21+S21 -> 0 | T21: =V21+X21+Z21+AB21+AD21+AF21+AH21+AJ21+AV21+AL21+AN21+AP21+AR21+AT21 -> 391080 | U21: 損保ｼﾞｬﾊﾟﾝ | V21: 300000 | W21: 三栄石油㈱ | X21: 91080
B22: 44367 | C22: =D22+M22+T22 -> 0 | D22: =F22+H22+J22+L22 -> 0 | M22: =O22+Q22+S22 -> 0 | T22: =V22+X22+Z22+AB22+AD22+AF22+AH22+AJ22+AV22+AL22+AN22+AP22+AR22+AT22 -> 0
B23: 44368 | C23: =D23+M23+T23 -> 0 | D23: =F23+H23+J23+L23 -> 0 | M23: =O23+Q23+S23 -> 0 | T23: =V23+X23+Z23+AB23+AD23+AF23+AH23+AJ23+AV23+AL23+AN23+AP23+AR23+AT23 -> 0
B24: 44369 | C24: =D24+M24+T24 -> 0 | D24: =F24+H24+J24+L24 -> 0 | M24: =O24+Q24+S24 -> 0 | T24: =V24+X24+Z24+AB24+AD24+AF24+AH24+AJ24+AV24+AL24+AN24+AP24+AR24+AT24 -> 0
B25: 44370 | C25: =D25+M25+T25 -> 204775 | D25: =F25+H25+J25+L25 -> 4775 | E25: 笠信出資配当 | F25: 4775 | M25: =O25+Q25+S25 -> 0 | T25: =V25+X25+Z25+AB25+AD25+AF25+AH25+AJ25+AV25+AL25+AN25+AP25+AR25+AT25 -> 200000 | U25: 藤田勲様 | V25: 200000
B26: 44371 | C26: =D26+M26+T26 -> 3761192 | D26: =F26+H26+J26+L26 -> 0 | M26: =O26+Q26+S26 -> 0 | T26: =V26+X26+Z26+AB26+AD26+AF26+AH26+AJ26+AV26+AL26+AN26+AP26+AR26+AT26 -> 3761192 | U26: 映ｸﾗ㈱様 ﾄﾖﾀ ﾗｲｽﾞ | V26: 1808790 | W26: ㈲ｱﾄﾘｴﾋﾟｭｱ様 | X26: 220000 | Y26: 福山ｽﾎﾟｰﾂ雇用ｻﾎﾟｰﾄｾﾝﾀｰ様 | Z26: 1732402
B27: 44372 | C27: =D27+M27+T27 -> 301970 | D27: =F27+H27+J27+L27 -> 0 | M27: =O27+Q27+S27 -> 0 | T27: =V27+X27+Z27+AB27+AD27+AF27+AH27+AJ27+AV27+AL27+AN27+AP27+AR27+AT27 -> 301970 | U27: 美建工業㈱ | V27: 301970
B28: 44373 | C28: =D28+M28+T28 -> 0 | D28: =F28+H28+J28+L28 -> 0 | M28: =O28+Q28+S28 -> 0 | T28: =V28+X28+Z28+AB28+AD28+AF28+AH28+AJ28+AV28+AL28+AN28+AP28+AR28+AT28 -> 0
B29: 44374 | C29: =D29+M29+T29 -> 9484229 | D29: =F29+H29+J29+L29 -> 0 | M29: =O29+Q29+S29 -> 0 | T29: =V29+X29+Z29+AB29+AD29+AF29+AH29+AJ29+AV29+AL29+AN29+AP29+AR29+AT29 -> 9484229 | U29: ㈱ﾛﾍﾟﾗｲｵ（車両代） | V29: 270809 | W29: ㈱ｽﾋﾟﾝｸﾞﾙｶﾝﾊﾟﾆｰ様 | X29: 9189220 | Y29: ㈱今川建築設計 | Z29: 24200
B30: 44375 | C30: =D30+M30+T30 -> 0 | D30: =F30+H30+J30+L30 -> 0 | M30: =O30+Q30+S30 -> 0 | T30: =V30+X30+Z30+AB30+AD30+AF30+AH30+AJ30+AV30+AL30+AN30+AP30+AR30+AT30 -> 0
B31: 44376 | C31: =D31+M31+T31 -> 0 | D31: =F31+H31+J31+L31 -> 0 | M31: =O31+Q31+S31 -> 0 | T31: =V31+X31+Z31+AB31+AD31+AF31+AH31+AJ31+AV31+AL31+AN31+AP31+AR31+AT31 -> 0
B32: 44377 | C32: =D32+M32+T32 -> 16042404 | D32: =F32+H32+J32+L32 -> 0 | M32: =O32+Q32+S32 -> 0 | T32: =V32+X32+Z32+AB32+AD32+AF32+AH32+AJ32+AV32+AL32+AN32+AP32+AR32+AT32 -> 16042404 | U32: 山道千絵様下取り車自動車税一か月分 | V32: 3000 | W32: ｺﾝｸｴｽﾄ様J&LR営業部門 | X32: 1936707 | Y32: ｺﾝｸｴｽﾄ様J&LR整備 | Z32: 313716 | AA32: ｺﾝｸｴｽﾄ様J&LR営業部門 ﾐﾓｻﾞ薬局様 | AB32: 921030 | AC32: ｺﾝｸｴｽﾄ様ﾗﾝﾄﾞﾛｰﾊﾞｰ小林様分 | AD32: 4557210 | AE32: ｺﾝｸｴｽﾄ様ｼﾞｬｶﾞｰXE林様分 | AF32: 4103046 | AG32: ｺﾝｸｴｽﾄ様紹介料 | AH32: 488164 | AI32: ｺﾝｸｴｽﾄ様経費 | AJ32: 2876175 | AK32: 中銀JCB | AL32: 74292 | AM32: 中銀VISA | AN32: 524526 | AO32: ㈱ｾﾞﾈｺｽ | AP32: 1100 | AQ32: 福山ｽﾎﾟｰﾂ雇用ｻﾎﾟｰﾄｾﾝﾀｰ様 | AR32: 93438 | AS32: あいおいﾆｯｾｲ同和様 | AT32: 150000
B33: ６月合計 | C33: =D33+M33+T33 -> 38728869 | D33: =SUM(D2:D32) -> 2506615 | M33: =SUM(M2:M32) -> 170634 | T33: =SUM(T3:T32) -> 36051620
B34: 未確定 | C34: =D34+M34+T34 -> 0 | T34: =V34+X34+Z34+AB34+AD34+AF34+AH34+AJ34+AV34 -> 0
B35: 44378 | C35: =D35+M35+T35 -> 0 | D35: =F35+H35+J35+L35 -> 0 | M35: =O35+Q35+S35 -> 0 | T35: =V35+X35+Z35+AB35+AD35+AF35+AH35+AJ35+AV35+AL35+AN35+AP35+AR35+AT35 -> 0
B36: 45109 | C36: =D36+M36+T36 -> 430000 | D36: =F36+H36+J36+L36 -> 0 | M36: =O36+Q36+S36 -> 0 | T36: =V36+X36+Z36+AB36+AD36+AF36+AH36+AJ36+AV36+AL36+AN36+AP36+AR36+AT36 -> 430000 | U36: 小畠興産㈱ | V36: 430000
B37: 45110 | C37: =D37+M37+T37 -> 29712480 | D37: =F37+H37+J37+L37 -> 12470891 | E37: 笠信手形貸付金 | F37: 12470891 | M37: =O37+Q37+S37 -> 0 | T37: =V37+X37+Z37+AB37+AD37+AF37+AH37+AJ37+AV37+AL37+AN37+AP37+AR37+AT37 -> 17241589 | U37: 損保ｼﾞｬﾊﾟﾝ | V37: 3656050 | W37: ｽﾄﾛﾝｸﾞﾏｳﾝﾃﾝ様 | X37: 13560539 | Y37: 土肥良太郎様 | Z37: 25000
B38: 45111 | C38: =D38+M38+T38 -> 0 | D38: =F38+H38+J38+L38 -> 0 | M38: =O38+Q38+S38 -> 0 | T38: =V38+X38+Z38+AB38+AD38+AF38+AH38+AJ38+AV38+AL38+AN38+AP38+AR38+AT38 -> 0
B39: 45112 | C39: =D39+M39+T39 -> 0 | D39: =F39+H39+J39+L39 -> 0 | M39: =O39+Q39+S39 -> 0 | T39: =V39+X39+Z39+AB39+AD39+AF39+AH39+AJ39+AV39+AL39+AN39+AP39+AR39+AT39 -> 0
B40: 45113 | C40: =D40+M40+T40 -> 0 | D40: =F40+H40+J40+L40 -> 0 | M40: =O40+Q40+S40 -> 0 | T40: =V40+X40+Z40+AB40+AD40+AF40+AH40+AJ40+AV40+AL40+AN40+AP40+AR40+AT40 -> 0
B41: 45114 | C41: =D41+M41+T41 -> 0 | D41: =F41+H41+J41+L41 -> 0 | M41: =O41+Q41+S41 -> 0 | T41: =V41+X41+Z41+AB41+AD41+AF41+AH41+AJ41+AV41+AL41+AN41+AP41+AR41+AT41 -> 0
B42: 45115 | C42: =D42+M42+T42 -> 354024 | D42: =F42+H42+J42+L42 -> 0 | M42: =O42+Q42+S42 -> 0 | T42: =V42+X42+Z42+AB42+AD42+AF42+AH42+AJ42+AV42+AL42+AN42+AP42+AR42+AT42 -> 354024 | U42: 皿谷ﾓｰﾀｰｽ(小切手） | V42: 354024
B43: 45116 | C43: =D43+M43+T43 -> 0 | D43: =F43+H43+J43+L43 -> 0 | M43: =O43+Q43+S43 -> 0 | T43: =V43+X43+Z43+AB43+AD43+AF43+AH43+AJ43+AV43+AL43+AN43+AP43+AR43+AT43 -> 0
B44: 45117 | C44: =D44+M44+T44 -> 0 | D44: =F44+H44+J44+L44 -> 0 | M44: =O44+Q44+S44 -> 0 | T44: =V44+X44+Z44+AB44+AD44+AF44+AH44+AJ44+AV44+AL44+AN44+AP44+AR44+AT44 -> 0
B45: 45118 | C45: =D45+M45+T45 -> 6855439 | D45: =F45+H45+J45+L45 -> 0 | M45: =O45+Q45+S45 -> 0 | T45: =V45+X45+Z45+AB45+AD45+AF45+AH45+AJ45+AV45+AL45+AN45+AP45+AR45+AT45 -> 6855439 | U45: ｵﾘｺ泉様 | V45: 6855439
B46: 45119 | C46: =D46+M46+T46 -> 0 | D46: =F46+H46+J46+L46 -> 0 | M46: =O46+Q46+S46 -> 0 | T46: =V46+X46+Z46+AB46+AD46+AF46+AH46+AJ46+AV46+AL46+AN46+AP46+AR46+AT46 -> 0
B47: 45120 | C47: =D47+M47+T47 -> 0 | D47: =F47+H47+J47+L47 -> 0 | M47: =O47+Q47+S47 -> 0 | T47: =V47+X47+Z47+AB47+AD47+AF47+AH47+AJ47+AV47+AL47+AN47+AP47+AR47+AT47 -> 0
B48: 45121 | C48: =D48+M48+T48 -> 3762150 | D48: =F48+H48+J48+L48 -> 0 | M48: =O48+Q48+S48 -> 0 | T48: =V48+X48+Z48+AB48+AD48+AF48+AH48+AJ48+AV48+AL48+AN48+AP48+AR48+AT48 -> 3762150 | U48: ｺﾝｸｴｽﾄ様 | V48: 3662150 | W48: 安心生命保険 | X48: 100000
B49: 45122 | C49: =D49+M49+T49 -> 321783 | D49: =F49+H49+J49+L49 -> 0 | M49: =O49+Q49+S49 -> 233540 | N49: 東京海上日動 代理店手数料 | O49: 18593 | P49: 三井住友海上火災保険㈱ | Q49: 214947 | T49: =V49+X49+Z49+AB49+AD49+AF49+AH49+AJ49+AV49+AL49+AN49+AP49+AR49+AT49 -> 88243 | U49: ｷﾑﾗﾕﾆﾃｨ様 | V49: 17220 | W49: 中銀ｶｰﾄﾞVISA | X49: 71023
B50: 45123 | C50: =D50+M50+T50 -> 0 | D50: =F50+H50+J50+L50 -> 0 | M50: =O50+Q50+S50 -> 0 | T50: =V50+X50+Z50+AB50+AD50+AF50+AH50+AJ50+AV50+AL50+AN50+AP50+AR50+AT50 -> 0
B51: 45124 | C51: =D51+M51+T51 -> 390000 | D51: =F51+H51+J51+L51 -> 0 | M51: =O51+Q51+S51 -> 0 | T51: =V51+X51+Z51+AB51+AD51+AF51+AH51+AJ51+AV51+AL51+AN51+AP51+AR51+AT51 -> 390000 | U51: 三井住友海上火災保険㈱ｴﾙｸﾞﾚｺ様 | V51: 390000
B52: 45125 | C52: =D52+M52+T52 -> 885734 | D52: =F52+H52+J52+L52 -> 0 | M52: =O52+Q52+S52 -> 0 | T52: =V52+X52+Z52+AB52+AD52+AF52+AH52+AJ52+AV52+AL52+AN52+AP52+AR52+AT52 -> 885734 | U52: 福山ｽﾎﾟｰﾂ雇用ｻﾎﾟｰﾄｾﾝﾀｰ様 | V52: 885734
B53: 45126 | C53: =D53+M53+T53 -> 0 | D53: =F53+H53+J53+L53 -> 0 | M53: =O53+Q53+S53 -> 0 | T53: =V53+X53+Z53+AB53+AD53+AF53+AH53+AJ53+AV53+AL53+AN53+AP53+AR53+AT53 -> 0
B54: 45127 | C54: =D54+M54+T54 -> 0 | D54: =F54+H54+J54+L54 -> 0 | M54: =O54+Q54+S54 -> 0 | T54: =V54+X54+Z54+AB54+AD54+AF54+AH54+AJ54+AV54+AL54+AN54+AP54+AR54+AT54 -> 0
B55: 45128 | C55: =D55+M55+T55 -> 0 | D55: =F55+H55+J55+L55 -> 0 | M55: =O55+Q55+S55 -> 0 | T55: =V55+X55+Z55+AB55+AD55+AF55+AH55+AJ55+AV55+AL55+AN55+AP55+AR55+AT55 -> 0
B56: 45129 | C56: =D56+M56+T56 -> 41203 | D56: =F56+H56+J56+L56 -> 0 | M56: =O56+Q56+S56 -> 0 | T56: =V56+X56+Z56+AB56+AD56+AF56+AH56+AJ56+AV56+AL56+AN56+AP56+AR56+AT56 -> 41203 | U56: ｵﾘｺ 泉様ｷｯｸﾊﾞｯｸ | V56: 41203
B57: 45130 | C57: =D57+M57+T57 -> 597696 | D57: =F57+H57+J57+L57 -> 0 | M57: =O57+Q57+S57 -> 0 | T57: =V57+X57+Z57+AB57+AD57+AF57+AH57+AJ57+AV57+AL57+AN57+AP57+AR57+AT57 -> 597696 | U57: 三井住友海上 | V57: 597696
B58: 45131 | C58: =D58+M58+T58 -> 6129450 | D58: =F58+H58+J58+L58 -> 0 | M58: =O58+Q58+S58 -> 0 | T58: =V58+X58+Z58+AB58+AD58+AF58+AH58+AJ58+AV58+AL58+AN58+AP58+AR58+AT58 -> 6129450 | U58: ㈱USS大阪 | V58: 6076650 | W58: 福山ｽﾎﾟｰﾂ雇用ｻﾎﾟｰﾄｾﾝﾀｰ様 | X58: 52800
B59: 45132 | C59: =D59+M59+T59 -> 454170 | D59: =F59+H59+J59+L59 -> 0 | M59: =O59+Q59+S59 -> 0 | T59: =V59+X59+Z59+AB59+AD59+AF59+AH59+AJ59+AV59+AL59+AN59+AP59+AR59+AT59 -> 454170 | U59: ㈱ｻﾝｴｽ | V59: 294170 | W59: 藤田勲様 | X59: 50000 | Y59: ｱﾄﾘｴﾋﾟｭｱ様 | Z59: 110000
B60: 45133 | C60: =D60+M60+T60 -> 0 | D60: =F60+H60+J60+L60 -> 0 | M60: =O60+Q60+S60 -> 0 | T60: =V60+X60+Z60+AB60+AD60+AF60+AH60+AJ60+AV60+AL60+AN60+AP60+AR60+AT60 -> 0
B61: 45134 | C61: =D61+M61+T61 -> 0 | D61: =F61+H61+J61+L61 -> 0 | M61: =O61+Q61+S61 -> 0 | T61: =V61+X61+Z61+AB61+AD61+AF61+AH61+AJ61+AV61+AL61+AN61+AP61+AR61+AT61 -> 0
B62: 45135 | C62: =D62+M62+T62 -> 108240 | D62: =F62+H62+J62+L62 -> 0 | M62: =O62+Q62+S62 -> 0 | T62: =V62+X62+Z62+AB62+AD62+AF62+AH62+AJ62+AV62+AL62+AN62+AP62+AR62+AT62 -> 108240 | U62: 畠山徹也様 | V62: 108240
B63: 45136 | C63: =D63+M63+T63 -> 0 | D63: =F63+H63+J63+L63 -> 0 | M63: =O63+Q63+S63 -> 0 | T63: =V63+X63+Z63+AB63+AD63+AF63+AH63+AJ63+AV63+AL63+AN63+AP63+AR63+AT63 -> 0
B64: 45137 | C64: =D64+M64+T64 -> 1100 | D64: =F64+H64+J64+L64 -> 0 | M64: =O64+Q64+S64 -> 0 | T64: =V64+X64+Z64+AB64+AD64+AF64+AH64+AJ64+AV64+AL64+AN64+AP64+AR64+AT64 -> 1100 | U64: ｸﾚｽﾄ不動産㈱様 誤入金 | V64: 1100
B65: 45138 | C65: =D65+M65+T65 -> 23047517 | D65: =F65+H65+J65+L65 -> 0 | M65: =O65+Q65+S65 -> 0 | T65: =V65+X65+Z65+AB65+AD65+AF65+AH65+AJ65+AV65+AL65+AN65+AP65+AR65+AT65 -> 23047517 | U65: ｵﾘｺｵｰﾄﾘｰｽ様 | V65: 7130421 | W65: ｺﾝｸｴｽﾄ様J&LR営業部門 | X65: -80025 | Y65: ｺﾝｸｴｽﾄ様J&LR整備 | Z65: 482243 | AA65: ｺﾝｸｴｽﾄ様ｸﾞﾚｶｰﾚ | AB65: 12000000 | AC65: ｺﾝｸｴｽﾄ様dyﾏｰｹﾃｨﾝｸﾞ様 Q2 | AD65: 282228 | AE65: ｺﾝｸｴｽﾄ様紹介料 | AF65: 590225 | AG65: ｺﾝｸｴｽﾄ様経費 | AH65: 1032005 | AI65: 吉元建設㈱様 | AJ65: 266420 | AK65: 中銀ｶｰﾄﾞVISA | AL65: 250224 | AM65: 中銀ｶｰﾄﾞJCB | AN65: 589059 | AO65: 宇田製菓㈱様 | AP65: 239170 | AQ65: 三愛運輸㈱様 | AR65: 265547
B66: ７月合計 | C66: =D66+M66+T66 -> 73090986 | D66: =SUM(D35:D65) -> 12470891 | M66: =SUM(M35:M65) -> 233540 | T66: =SUM(T35:T65) -> 60386555
B67: 未確定 | C67: =D67+M67+T67 -> 0 | T67: =V67+X67+Z67+AB67+AD67+AF67+AH67+AJ67+AV67 -> 0
B68: 45139 | C68: =D68+M68+T68 -> 0 | D68: =F68+H68+J68+L68 -> 0 | M68: =O68 | T68: =V68+X68+Z68+AB68+AD68+AF68+AH68+AJ68+AV68 -> 0
B69: 45140 | C69: =D69+M69+T69 -> 0 | D69: =F69+H69+J69+L69 -> 0 | M69: =O69 | T69: =V69+X69+Z69+AB69+AD69+AF69+AH69+AJ69+AV69 -> 0
B70: 45141 | C70: =D70+M70+T70 -> 0 | D70: =F70+H70+J70+L70 -> 0 | M70: =O70 | T70: =V70+X70+Z70+AB70+AD70+AF70+AH70+AJ70+AV70 -> 0
B71: 45142 | C71: =D71+M71+T71 -> 0 | D71: =F71+H71+J71+L71 -> 0 | M71: =O71 | T71: =V71+X71+Z71+AB71+AD71+AF71+AH71+AJ71+AV71 -> 0
B72: 45143 | C72: =D72+M72+T72 -> 0 | D72: =F72+H72+J72+L72 -> 0 | M72: =O72+Q72 -> 0 | T72: =V72+X72+Z72+AB72+AD72+AF72+AH72+AJ72+AV72 -> 0
B73: 45144 | C73: =D73+M73+T73 -> 2061290 | D73: =F73+H73+J73+L73 -> 0 | M73: =O73+Q73 -> 0 | T73: =V73+X73+Z73+AB73+AD73+AF73+AH73+AJ73+AV73 -> 2061290 | U73: あいおいﾆｯｾｲ同和様 | V73: 2061290
B74: 45145 | C74: =D74+M74+T74 -> 303930 | D74: =F74+H74+J74+L74 -> 0 | M74: =O74+Q74 -> 0 | T74: =V74+X74+Z74+AB74+AD74+AF74+AH74+AJ74+AV74 -> 303930 | U74: 三栄石油㈱様 | V74: 270160 | W74: ｶｰｻｰﾋﾞｽﾐｿﾞｳｴ様 | X74: 33770
B75: 45146 | C75: =D75+M75+T75 -> 17650 | D75: =F75+H75+J75+L75 -> 0 | M75: =O75+Q75 -> 0 | T75: =V75+X75+Z75+AB75+AD75+AF75+AH75+AJ75+AV75 -> 17650 | U75: 日本ｶｰｿﾘｭｰｼｮﾝｽﾞ | V75: 17650
B76: 45147 | C76: =D76+M76+T76 -> 0 | D76: =F76+H76+J76+L76 -> 0 | M76: =O76+Q76 -> 0 | T76: =V76+X76+Z76+AB76+AD76+AF76+AH76+AJ76+AV76 -> 0
B77: 45148 | C77: =D77+M77+T77 -> 0 | D77: =F77+H77+J77+L77 -> 0 | M77: =O77+Q77 -> 0 | T77: =V77+X77+Z77+AB77+AD77+AF77+AH77+AJ77+AV77 -> 0
B78: 45149 | C78: =D78+M78+T78 -> 25000 | D78: =F78+H78+J78+L78 -> 0 | M78: =O78+Q78 -> 0 | T78: =V78+X78+Z78+AB78+AD78+AF78+AH78+AJ78+AV78 -> 25000 | U78: 土肥良太郎様 | V78: 25000
B79: 45150 | C79: =D79+M79+T79 -> 77831 | D79: =F79+H79+J79+L79 -> 0 | M79: =O79+Q79 -> 0 | T79: =V79+X79+Z79+AB79+AD79+AF79+AH79+AJ79+AV79 -> 77831 | U79: ㈲ｴﾙｸﾞﾚｺ様 | V79: 77831
B80: 45151 | C80: =D80+M80+T80 -> 0 | D80: =F80+H80+J80+L80 -> 0 | M80: =O80+Q80 -> 0 | T80: =V80+X80+Z80+AB80+AD80+AF80+AH80+AJ80+AV80 -> 0
B81: 45152 | C81: =D81+M81+T81 -> 461500 | D81: =F81+H81+J81+L81 -> 0 | M81: =O81+Q81 -> 0 | T81: =V81+X81+Z81+AB81+AD81+AF81+AH81+AJ81+AV81 -> 461500 | U81: 三井住友海上 | V81: 461500
B82: 45153 | C82: =D82+M82+T82 -> 1341861 | D82: =F82+H82+J82+L82 -> 3722 | E82: 広信国税還付金 | F82: 3722 | M82: =O82+Q82 -> 0 | T82: =V82+X82+Z82+AB82+AD82+AF82+AH82+AJ82+AV82 -> 1338139 | U82: 中銀ｶｰﾄﾞVISA | V82: 18102 | W82: 中銀ｶｰﾄﾞJCB | X82: 250295 | Y82: 東京海上日動 | Z82: 880000 | AA82: ｷﾑﾗﾕﾆﾃｨ様 | AB82: 117417 | AC82: 田辺ﾃﾂﾛｳ様 | AD82: 72325
B83: 45154 | C83: =D83+M83+T83 -> 0 | D83: =F83+H83+J83+L83 -> 0 | M83: =O83+Q83 -> 0 | T83: =V83+X83+Z83+AB83+AD83+AF83+AH83+AJ83+AV83 -> 0
B84: 45155 | C84: =D84+M84+T84 -> 61 | D84: =F84+H84+J84+L84 -> 61 | E84: 広信決算利息 | F84: 61 | M84: =O84+Q84 -> 0 | T84: =V84+X84+Z84+AB84+AD84+AF84+AH84+AJ84+AV84 -> 0
B85: 45156 | C85: =D85+M85+T85 -> 226519 | D85: =F85+H85+J85+L85 -> 4509 | E85: 中銀利息 | F85: 2074 | G85: もみじ利息 | H85: 2435 | M85: =O85+Q85 -> 222010 | N85: 三井住友海上 代理店手数料 | O85: 148560 | P85: 橋本祥子取締役治療費笠信へ返金 | Q85: 73450 | T85: =V85+X85+Z85+AB85+AD85+AF85+AH85+AJ85+AV85 -> 0
B86: 45157 | C86: =D86+M86+T86 -> 21381 | D86: =F86+H86+J86+L86 -> 0 | M86: =O86+Q86 -> 21381 | N86: 東京海上日動代理店手数料 | O86: 21381 | T86: =V86+X86+Z86+AB86+AD86+AF86+AH86+AJ86+AV86 -> 0
B87: 45158 | C87: =D87+M87+T87 -> 1000000 | D87: =F87+H87+J87+L87 -> 0 | M87: =O87+Q87 -> 0 | T87: =V87+X87+Z87+AB87+AD87+AF87+AH87+AJ87+AV87 -> 1000000 | U87: 山本彩加様 | V87: 1000000
B88: 45159 | C88: =D88+M88+T88 -> 0 | D88: =F88+H88+J88+L88 -> 0 | M88: =O88+Q88 -> 0 | T88: =V88+X88+Z88+AB88+AD88+AF88+AH88+AJ88+AV88 -> 0
B89: 45160 | C89: =D89+M89+T89 -> 270160 | D89: =F89+H89+J89+L89 -> 0 | M89: =O89+Q89 -> 0 | T89: =V89+X89+Z89+AB89+AD89+AF89+AH89+AJ89+AV89 -> 270160 | U89: 髙山産業㈱ | V89: 270160
B90: 45161 | C90: =D90+M90+T90 -> 0 | D90: =F90+H90+J90+L90 -> 0 | M90: =O90+Q90 -> 0 | T90: =V90+X90+Z90+AB90+AD90+AF90+AH90+AJ90+AV90 -> 0
B91: 45162 | C91: =D91+M91+T91 -> 0 | D91: =F91+H91+J91+L91 -> 0 | M91: =O91+Q91 -> 0 | T91: =V91+X91+Z91+AB91+AD91+AF91+AH91+AJ91+AV91 -> 0
B92: 45163 | C92: =D92+M92+T92 -> 478561 | D92: =F92+H92+J92+L92 -> 0 | M92: =O92+Q92 -> 0 | T92: =V92+X92+Z92+AB92+AD92+AF92+AH92+AJ92+AV92 -> 478561 | U92: ㈱一条工務店広島 | V92: 93896 | W92: 村上ﾕｳｼﾞ様村上脳神経外科内科 | X92: 274665 | Y92: ｱﾄﾘｴﾋﾟｭｱ様 | Z92: 110000
B93: 45164 | C93: =D93+M93+T93 -> 3765900 | D93: =F93+H93+J93+L93 -> 0 | M93: =O93+Q93 -> 0 | T93: =V93+X93+Z93+AB93+AD93+AF93+AH93+AJ93+AV93 -> 3765900 | U93: 映ｸﾗ㈱ | V93: 1300000 | W93: 藤田勲様 | X93: 50000 | Y93: 損保ｼﾞｬﾊﾟﾝ 株式会社CalmeTrading | Z93: 2415900
B94: 45165 | C94: =D94+M94+T94 -> 0 | D94: =F94+H94+J94+L94 -> 0 | M94: =O94+Q94 -> 0 | T94: =V94+X94+Z94+AB94+AD94+AF94+AH94+AJ94+AV94 -> 0
B95: 45166 | C95: =D95+M95+T95 -> 788639 | D95: =F95+H95+J95+L95 -> 788639 | E95: 8/29もみじ利息 | F95: 71013 | G95: 8/29もみじ利息 | H95: 12962 | I95: 8/29もみじ利息 | J95: 4664 | K95: 8/29現金より広銀へ資金移動 | L95: 700000 | M95: =O95+Q95 -> 0 | T95: =V95+X95+Z95+AB95+AD95+AF95+AH95+AJ95+AV95 -> 0
B96: 45167 | C96: =D96+M96+T96 -> 438616942 | D96: =F96+H96+J96+L96 -> 436365644 | E96: 笠信短期借入 | F96: 7545864 | G96: 日本政策金融金庫 | H96: 59999780 | I96: 笠信 | J96: 260000000 | K96: 8/29もみじ（笠信より | L96: 108820000 | M96: =O96+Q96 -> 0 | T96: =V96+X96+Z96+AB96+AD96+AF96+AH96+AJ96+AV96 -> 2251298 | U96: ｺﾝｸｴｽﾄ様J&LR整備 | V96: 251357 | W96: ｺﾝｸｴｽﾄ様J&LR営業部門 | X96: 688600 | Y96: ｺﾝｸｴｽﾄ様㈱大成様車庫証明 | Z96: 2300 | AA96: ｺﾝｸｴｽﾄ様経費 | AB96: 900825 | AC96: 中銀ｶｰﾄﾞVISA | AD96: 161158 | AE96: 中銀ｶｰﾄﾞJCB | AF96: 210318 | AG96: ㈲ｻﾝｴｽﾋﾞｼﾞﾈｽｿﾘｭｰｼｮﾝ | AH96: 36740
B97: 45168 | C97: =D97+M97+T97 -> 0 | D97: =F97+H97+J97+L97 -> 0 | M97: =O97+Q97 -> 0 | T97: =V97+X97+Z97+AB97+AD97+AF97+AH97+AJ97+AV97 -> 0
B98: 45169 | C98: =D98+M98+T98 -> 0 | D98: =F98+H98+J98+L98 -> 0 | M98: =O98+Q98 -> 0 | T98: =V98+X98+Z98+AB98+AD98+AF98+AH98+AJ98+AV98 -> 0
B99: ８月合計 | C99: =D99+M99+T99 -> 449457225 | D99: =SUM(D68:D98) -> 437162575 | M99: =SUM(M68:M98) -> 243391 | T99: =SUM(T68:T98) -> 12051259
B100: 未確定
...

Sheet 出金明細【17期】
C1: ２０２5年６月‐２０２6年５月出金
C2: 出金日次 | D2: 金融小計 | M2: 買掛小計 | AD2: 経費小計
B3: 44348 | C3: =D3+M3+AD3 -> 1732564 | D3: =F3+H3+J3+L3 -> 1732564 | E3: 6/2広銀ｼｮｳｶﾞｼ | F3: 240940 | G3: 6/2もみじ融資利息 | H3: 197624 | I3: 6/2もみじ長期借入返済 | J3: 404000 | K3: 6/2もみじ長期借入返済 | L3: 890000 | M3: =O3+Q3+S3+U3+W3+Y3+AA3+AC3 -> 0 | AD3: =AF3+AH3+AJ3+AL3+AN3+AP3+AR3+AT3+AV3+AX3+AZ3+BB3+BD3+BF3+BH3+BJ3+BL3+BN3+BP3+BR3+BT3+BV3+BX3+BZ3+CB3+CD3 -> 0
B4: 44349 | C4: =D4+M4+AD4 -> 6226157 | D4: =F4+H4+J4+L4 -> 3224600 | E4: 笠信ｼｮｳｶﾞｼ | F4: 522575 | G4: 笠岡貸付利息 | H4: 104041 | I4: 笠信ｼｮｳｶﾞｼ | J4: 2200600 | K4: 笠信ｼｮｳｶﾞｼ397384 | L4: 397384 | M4: =O4+Q4+S4+U4+W4+Y4+AA4+AC4 -> 1043380 | N4: ﾄﾖﾀﾌｧｲﾅﾝｽ残債 ｺﾝｸｴｽﾄ様ｲｳﾞｫｰｸﾞ110362小川様下取り分（映ｸﾗ様より200万円まだ？前田先生提案中 | O4: 1043380 | AD4: =AF4+AH4+AJ4+AL4+AN4+AP4+AR4+AT4+AV4+AX4+AZ4+BB4+BD4+BF4+BH4+BJ4+BL4+BN4+BP4+BR4+BT4+BV4+BX4+BZ4+CB4+CD4 -> 1958177 | AE4: も）ﾄﾖﾀﾌｧｲﾅﾝｽ | AF4: 44411 | AG4: 自動車税 | AH4: 659200 | AI4: 住民税、所得税支払い | AJ4: 78700 | AK4: 笠信）年金事務所 | AL4: 659440 | AM4: ﾋﾞｰﾌｨｰﾙﾄﾞ | AN4: 2200 | AO4: 日本政策公庫 | AP4: 514226
B5: 45446 | C5: =D5+M5+AD5 -> 195360 | D5: =F5+H5+J5+L5 -> 0 | M5: =O5+Q5+S5+U5+W5+Y5+AA5+AC5 -> 0 | AD5: =AF5+AH5+AJ5+AL5+AN5+AP5+AR5+AT5+AV5+AX5+AZ5+BB5+BD5+BF5+BH5+BJ5+BL5+BN5+BP5+BR5+BT5+BV5+BX5+BZ5+CB5+CD5 -> 195360 | AE5: 三井住友FL（SM） | AF5: 195360
B6: 44351 | C6: =D6+M6+AD6 -> 141790 | D6: =F6+H6+J6+L6 -> 550 | E6: 笠信支払手数料 | F6: 550 | M6: =O6+Q6+S6+U6+W6+Y6+AA6+AC6 -> 0 | AD6: =AF6+AH6+AJ6+AL6+AN6+AP6+AR6+AT6+AV6+AX6+AZ6+BB6+BD6+BF6+BH6+BJ6+BL6+BN6+BP6+BR6+BT6+BV6+BX6+BZ6+CB6+CD6 -> 141240 | AE6: 未来経営 | AF6: 88000 | AG6: ﾘｺｰPCﾘｰｽ | AH6: 53240
B7: 44352 | C7: =D7+M7+AD7 -> 0 | D7: =F7+H7+J7+L7 -> 0 | M7: =O7+Q7+S7+U7+W7+Y7+AA7+AC7 -> 0 | AD7: =AF7+AH7+AJ7+AL7+AN7+AP7+AR7+AT7+AV7+AX7+AZ7+BB7+BD7+BF7+BH7+BJ7+BL7+BN7+BP7+BR7+BT7+BV7+BX7+BZ7+CB7+CD7 -> 0 | AE7: 自賠責 | AF7: 0
B8: 44353 | C8: =D8+M8+AD8 -> 0 | D8: =F8+H8+J8+L8 -> 0 | M8: =O8+Q8+S8+U8+W8+Y8+AA8+AC8 -> 0 | AD8: =AF8+AH8+AJ8+AL8+AN8+AP8+AR8+AT8+AV8+AX8+AZ8+BB8+BD8+BF8+BH8+BJ8+BL8+BN8+BP8+BR8+BT8+BV8+BX8+BZ8+CB8+CD8 -> 0
B9: 44354 | C9: =D9+M9+AD9 -> 0 | D9: =F9+H9+J9+L9 -> 0 | M9: =O9+Q9+S9+U9+W9+Y9+AA9+AC9 -> 0 | AD9: =AF9+AH9+AJ9+AL9+AN9+AP9+AR9+AT9+AV9+AX9+AZ9+BB9+BD9+BF9+BH9+BJ9+BL9+BN9+BP9+BR9+BT9+BV9+BX9+BZ9+CB9+CD9 -> 0
B10: 45816 | C10: =D10+M10+AD10 -> 3630 | D10: =F10+H10+J10+L10 -> 3630 | E10: 6/10もみじIB手数料 | F10: 3630 | M10: =O10+Q10+S10+U10+W10+Y10+AA10+AC10 -> 0 | AD10: =AF10+AH10+AJ10+AL10+AN10+AP10+AR10+AT10+AV10+AX10+AZ10+BB10+BD10+BF10+BH10+BJ10+BL10+BN10+BP10+BR10+BT10+BV10+BX10+BZ10+CB10+CD10 -> 0
B11: 44356 | C11: =D11+M11+AD11 -> 14960 | D11: =F11+H11+J11+L11 -> 14960 | E11: 広信支払手数料 | F11: 1210 | G11: 6/10広銀B-WEB基本手数料 | H11: 1650 | I11: 6/10広銀B-WEB伝送基本手数料 | J11: 2530 | K11: 6/10広銀B-WEB振込手数料 | L11: 9570 | M11: =O11+Q11+S11+U11+W11+Y11+AA11+AC11 -> 0 | AD11: =AF11+AH11+AJ11+AL11+AN11+AP11+AR11+AT11+AV11+AX11+AZ11+BB11+BD11+BF11+BH11+BJ11+BL11+BN11+BP11+BR11+BT11+BV11+BX11+BZ11+CB11+CD11 -> 0
B12: 44357 | C12: =D12+M12+AD12 -> 4040944 | D12: =F12+H12+J12+L12 -> 5170 | E12: もみじ残高証明 | F12: 330 | G12: 中銀残高証明 | H12: 330 | I12: 中銀FBｻｰﾋﾞｽ | J12: 3850 | K12: もみじ振込手数料 | L12: 660 | M12: =O12+Q12+S12+U12+W12+Y12+AA12+AC12 -> 0 | AD12: =AF12+AH12+AJ12+AL12+AN12+AP12+AR12+AT12+AV12+AX12+AZ12+BB12+BD12+BF12+BH12+BJ12+BL12+BN12+BP12+BR12+BT12+BV12+BX12+BZ12+CB12+CD12 -> 4035774 | AE12: 田中賢治様 | AF12: 14600 | AG12: 笠信）ｶｰﾄﾞ引落 ﾀﾞｲﾅｰｽﾞ | AH12: 1109555 | AI12: 給与 | AJ12: 1197136 | AK12: 橋本祥子様 | AL12: 700000 | AM12: 高田自動車 | AN12: 259210 | AO12: 銚子さん | AP12: 170000 | AQ12: もみじ引落ｶﾀﾞｲﾅｰｽｶｰﾄﾞ・ﾄﾗｽﾄｸﾗﾌﾞ整備 | AR12: 209532 | AS12: もみじ引落ｶﾀﾞｲﾅｰｽｶｰﾄﾞ・ﾄﾗｽﾄｸﾗﾌﾞ整備 | AT12: 375741
B13: 44358 | C13: =D13+M13+AD13 -> 0 | D13: =F13+H13+J13+L13 -> 0 | M13: =O13+Q13+S13+U13+W13+Y13+AA13+AC13 -> 0 | AD13: =AF13+AH13+AJ13+AL13+AN13+AP13+AR13+AT13+AV13+AX13+AZ13+BB13+BD13+BF13+BH13+BJ13+BL13+BN13+BP13+BR13+BT13+BV13+BX13+BZ13+CB13+CD13 -> 0
B14: 44359 | C14: =D14+M14+AD14 -> 25433 | D14: =F14+H14+J14+L14 -> 0 | M14: =O14+Q14+S14+U14+W14+Y14+AA14+AC14 -> 0 | AD14: =AF14+AH14+AJ14+AL14+AN14+AP14+AR14+AT14+AV14+AX14+AZ14+BB14+BD14+BF14+BH14+BJ14+BL14+BN14+BP14+BR14+BT14+BV14+BX14+BZ14+CB14+CD14 -> 25433 | AE14: ｱｽｸﾙ | AF14: 9628 | AG14: 自賠責 | AH14: 15805
B15: 44360 | C15: =D15+M15+AD15 -> 5000 | D15: =F15+H15+J15+L15 -> 0 | M15: =O15+Q15+S15+U15+W15+Y15+AA15+AC15 -> 0 | AD15: =AF15+AH15+AJ15+AL15+AN15+AP15+AR15+AT15+AV15+AX15+AZ15+BB15+BD15+BF15+BH15+BJ15+BL15+BN15+BP15+BR15+BT15+BV15+BX15+BZ15+CB15+CD15 -> 5000 | AE15: 福山遠鐘ｸﾗﾌﾞ | AF15: 5000
B16: 44361 | C16: =D16+M16+AD16 -> 0 | D16: =F16+H16+J16+L16 -> 0 | M16: =O16+Q16+S16+U16+W16+Y16+AA16+AC16 -> 0 | AD16: =AF16+AH16+AJ16+AL16+AN16+AP16+AR16+AT16+AV16+AX16+AZ16+BB16+BD16+BF16+BH16+BJ16+BL16+BN16+BP16+BR16+BT16+BV16+BX16+BZ16+CB16+CD16 -> 0
B17: 44362 | C17: =D17+M17+AD17 -> 0 | D17: =F17+H17+J17+L17 -> 0 | M17: =O17+Q17+S17+U17+W17+Y17+AA17+AC17 -> 0 | AD17: =AF17+AH17+AJ17+AL17+AN17+AP17+AR17+AT17+AV17+AX17+AZ17+BB17+BD17+BF17+BH17+BJ17+BL17+BN17+BP17+BR17+BT17+BV17+BX17+BZ17+CB17+CD17 -> 0
B18: 44363 | C18: =D18+M18+AD18 -> 0 | D18: =F18+H18+J18+L18 -> 0 | M18: =O18+Q18+S18+U18+W18+Y18+AA18+AC18 -> 0 | AD18: =AF18+AH18+AJ18+AL18+AN18+AP18+AR18+AT18+AV18+AX18+AZ18+BB18+BD18+BF18+BH18+BJ18+BL18+BN18+BP18+BR18+BT18+BV18+BX18+BZ18+CB18+CD18 -> 0
B19: 44364 | C19: =D19+M19+AD19 -> 0 | D19: =F19+H19+J19+L19 -> 0 | M19: =O19+Q19+S19+U19+W19+Y19+AA19+AC19 -> 0 | AD19: =AF19+AH19+AJ19+AL19+AN19+AP19+AR19+AT19+AV19+AX19+AZ19+BB19+BD19+BF19+BH19+BJ19+BL19+BN19+BP19+BR19+BT19+BV19+BX19+BZ19+CB19+CD19 -> 0
B20: 44365 | C20: =D20+M20+AD20 -> 1100 | D20: =F20+H20+J20+L20 -> 1100 | E20: 笠信支払手数料 | F20: 1100 | M20: =O20+Q20+S20+U20+W20+Y20+AA20+AC20 -> 0 | AD20: =AF20+AH20+AJ20+AL20+AN20+AP20+AR20+AT20+AV20+AX20+AZ20+BB20+BD20+BF20+BH20+BJ20+BL20+BN20+BP20+BR20+BT20+BV20+BX20+BZ20+CB20+CD20 -> 0
B21: 44366 | C21: =D21+M21+AD21 -> 1331830 | D21: =F21+H21+J21+L21 -> 0 | M21: =O21+Q21+S21+U21+W21+Y21+AA21+AC21 -> 1300000 | N21: ㈱ｱﾄﾞｸﾞﾗﾌｨｰ様 1,300,000円 | O21: 1300000 | AD21: =AF21+AH21+AJ21+AL21+AN21+AP21+AR21+AT21+AV21+AX21+AZ21+BB21+BD21+BF21+BH21+BJ21+BL21+BN21+BP21+BR21+BT21+BV21+BX21+BZ21+CB21+CD21 -> 31830 | AE21: 自賠責 | AF21: 31830
B22: 44367 | C22: =D22+M22+AD22 -> 56146 | D22: =F22+H22+J22+L22 -> 0 | M22: =O22+Q22+S22+U22+W22+Y22+AA22+AC22 -> 0 | AD22: =AF22+AH22+AJ22+AL22+AN22+AP22+AR22+AT22+AV22+AX22+AZ22+BB22+BD22+BF22+BH22+BJ22+BL22+BN22+BP22+BR22+BT22+BV22+BX22+BZ22+CB22+CD22 -> 56146 | AE22: 三井住友車両保険対人対物17.520円＋販売車車両保険8.894円 | AF22: 25759 | AG22: 本社水道代引落 | AH22: 17247 | AI22: 水道料J&LR | AJ22: 4202 | AK22: 本社水道代引落 | AL22: 3938 | AM22: 希望ﾝﾝﾊﾞｰdyﾏｰｹﾃｨﾝｸﾞ様 | AN22: 5000
B23: 44368 | C23: =D23+M23+AD23 -> 0 | D23: =F23+H23+J23+L23 -> 0 | M23: =O23+Q23+S23+U23+W23+Y23+AA23+AC23 -> 0 | AD23: =AF23+AH23+AJ23+AL23+AN23+AP23+AR23+AT23+AV23+AX23+AZ23+BB23+BD23+BF23+BH23+BJ23+BL23+BN23+BP23+BR23+BT23+BV23+BX23+BZ23+CB23+CD23 -> 0
B24: 44369 | C24: =D24+M24+AD24 -> 0 | D24: =F24+H24+J24+L24 -> 0 | M24: =O24+Q24+S24+U24+W24+Y24+AA24+AC24 -> 0 | AD24: =AF24+AH24+AJ24+AL24+AN24+AP24+AR24+AT24+AV24+AX24+AZ24+BB24+BD24+BF24+BH24+BJ24+BL24+BN24+BP24+BR24+BT24+BV24+BX24+BZ24+CB24+CD24 -> 0
B25: 44370 | C25: =D25+M25+AD25 -> 50918 | D25: =F25+H25+J25+L25 -> 0 | M25: =O25+Q25+S25+U25+W25+Y25+AA25+AC25 -> 0 | AD25: =AF25+AH25+AJ25+AL25+AN25+AP25+AR25+AT25+AV25+AX25+AZ25+BB25+BD25+BF25+BH25+BJ25+BL25+BN25+BP25+BR25+BT25+BV25+BX25+BZ25+CB25+CD25 -> 50918 | AE25: も引落）ｷｬﾉﾝ | AF25: 7918 | AG25: 笠引落）㈱ﾌﾟﾛﾄｺｰﾎﾟﾚｰｼｮﾝ | AH25: 33000 | AI25: 笠信 収入印紙 | AJ25: 10000
B26: 44371 | C26: =D26+M26+AD26 -> 0 | D26: =F26+H26+J26+L26 -> 0 | M26: =O26+Q26+S26+U26+W26+Y26+AA26+AC26 -> 0 | AD26: =AF26+AH26+AJ26+AL26+AN26+AP26+AR26+AT26+AV26+AX26+AZ26+BB26+BD26+BF26+BH26+BJ26+BL26+BN26+BP26+BR26+BT26+BV26+BX26+BZ26+CB26+CD26 -> 0
B27: 44372 | C27: =D27+M27+AD27 -> 220000 | D27: =F27+H27+J27+L27 -> 0 | M27: =O27+Q27+S27+U27+W27+Y27+AA27+AC27 -> 0 | AD27: =AF27+AH27+AJ27+AL27+AN27+AP27+AR27+AT27+AV27+AX27+AZ27+BB27+BD27+BF27+BH27+BJ27+BL27+BN27+BP27+BR27+BT27+BV27+BX27+BZ27+CB27+CD27 -> 220000 | AE27: SoleilﾏｾﾗﾃｨMC20賃貸借2024.9.1～2026.8.31 | AF27: 220000
B28: 44373 | C28: =D28+M28+AD28 -> 542271 | D28: =F28+H28+J28+L28 -> 0 | M28: =O28+Q28+S28+U28+W28+Y28+AA28+AC28 -> 0 | AD28: =AF28+AH28+AJ28+AL28+AN28+AP28+AR28+AT28+AV28+AX28+AZ28+BB28+BD28+BF28+BH28+BJ28+BL28+BN28+BP28+BR28+BT28+BV28+BX28+BZ28+CB28+CD28 -> 542271 | AE28: ｿﾌﾄﾊﾞﾝｸ | AF28: 46680 | AG28: 笠）三井損害保険 | AH28: 172790 | AI28: 自賠責 | AJ28: 31720 | AK28: も）まるとく本社ｺﾋﾟｰ機 | AL28: 2833 | AM28: も）ﾞ引落中国新聞 | AN28: 3900 | AO28: も）ﾕﾆﾏｯﾄ | AP28: 4400 | AQ28: 広島労働局 | AR28: 279948
B29: 44374 | C29: =D29+M29+AD29 -> 11855932 | D29: =F29+H29+J29+L29 -> 204585 | E29: 笠信貸金庫料 | F29: 13200 | G29: 6/30もみじ印紙代 | H29: 6200 | I29: 6/30もみじ融資利息 | J29: 49270 | K29: 6/30もみじ融資利息 | L29: 135915 | M29: =O29+Q29+S29+U29+W29+Y29+AA29+AC29 -> 11286120 | N29: ㈱ｱﾄﾞｸﾞﾗﾌｨｰ様 1,300,000円残り ｽﾋﾟﾝｸﾞﾙｶﾝﾊﾟﾆｰ ﾎﾟﾙｼｪﾏｶﾝ | O29: 11286120 | AD29: =AF29+AH29+AJ29+AL29+AN29+AP29+AR29+AT29+AV29+AX29+AZ29+BB29+BD29+BF29+BH29+BJ29+BL29+BN29+BP29+BR29+BT29+BV29+BX29+BZ29+CB29+CD29 -> 365227 | AE29: 笠信）富士生命 | AF29: 84678 | AG29: も）ﾁｭｰﾘｯﾋ生命 | AH29: 6015 | AI29: も）ｵﾘｺｶｰｻｺﾋﾟｰ機 | AJ29: 27293 | AK29: も）あんしん生命 | AL29: 58201 | AM29: も）三和地所 | AN29: 67440 | AO29: も)ｵﾘｺJCM | AP29: 99000 | AQ29: も）福山法人会 | AR29: 5000 | AS29: 中銀引落)USS月会費 | AT29: 12980 | AU29: も）ｶｰｾﾌﾞﾝﾃﾞｼﾞﾌｨｰﾙﾄﾞｲﾝｽﾏｰﾄｼｽﾃﾑ | AV29: 4620
B30: 44375 | C30: =D30+M30+AD30 -> 1848874 | D30: =F30+H30+J30+L30 -> 1848874 | E30: 6/30笠信現金 | F30: 320135 | G30: 6/30もみじ融資利息 | H30: 234739 | I30: 6/30もみじ長期借入返済 | J30: 404000 | K30: 6/30もみじ長期借入返済 | L30: 890000 | M30: =O30+Q30+S30+U30+W30+Y30+AA30+AC30 -> 0 | AD30: =AF30+AH30+AJ30+AL30+AN30+AP30+AR30+AT30+AV30+AX30+AZ30+BB30+BD30+BF30+BH30+BJ30+BL30+BN30+BP30+BR30+BT30+BV30+BX30+BZ30+CB30+CD30 -> 0
B31: 44376 | C31: =D31+M31+AD31 -> 3195615 | D31: =F31+H31+J31+L31 -> 3195615 | E31: 6/30笠信ｼｮｳｶﾞｼ | F31: 521103 | G31: 6/30笠岡貸付利息 | H31: 100684 | I31: 6/30笠信ｼｮｳｶﾞｼ | J31: 2179160 | K31: 6/30笠信ｼｮｳｶﾞｼ397384 | L31: 394668 | M31: =O31+Q31+S31+U31+W31+Y31+AA31+AC31 -> 0 | AD31: =AF31+AH31+AJ31+AL31+AN31+AP31+AR31+AT31+AV31+AX31+AZ31+BB31+BD31+BF31+BH31+BJ31+BL31+BN31+BP31+BR31+BT31+BV31+BX31+BZ31+CB31+CD31 -> 0
B32: 44377 | C32: =D32+M32+AD32 -> 14510347 | D32: =F32+H32+J32+L32 -> 573237 | E32: ｺﾝｸｴｽﾄ様劣後利息 | F32: 26666 | G32: ｺﾝｸｴｽﾄ様ｸﾞﾚｶｰﾚﾃﾞﾓｶｰ分割 | H32: 305302 | I32: 6/30広銀ｼｮｳｶﾞｼ | J32: 240609 | K32: 中銀振込手数料 | L32: 660 | M32: =O32+Q32+S32+U32+W32+Y32+AA32+AC32 -> 11891372 | N32: ｺﾝｸｴｽﾄJ&LR4月分請求書 | O32: 731588 | P32: ｵﾘｺ地蔵院様ｷﾞﾌﾞﾘ買取 | Q32: 4539820 | R32: ｺﾝｸｴｽﾄ様小川洵様下取り分ﾄﾖﾀﾗｲｽﾞ | S32: 406620 | T32: ﾏｾﾗﾃｨ5月分ｺﾝｸｴｽﾄ様M整備 | U32: 7458 | V32: 月末支払い整備 | W32: 2783176 | X32: ｺﾝｸｴｽﾄ様ｲｳﾞｫｰｸﾞ | Y32: 3422710 | AD32: =AF32+AH32+AJ32+AL32+AN32+AP32+AR32+AT32+AV32+AX32+AZ32+BB32+BD32+BF32+BH32+BJ32+BL32+BN32+BP32+BR32+BT32+BV32+BX32+BZ32+CB32+CD32 -> 2045738 | AE32: 笠）年金事務所 | AF32: 716858 | AG32: ﾋﾞｰﾌｨｰﾙﾄﾞ | AH32: 2200 | AI32: 月末支払 | AJ32: 234044 | AK32: も)日本政策公庫 | AL32: 497636 | AM32: 大和ﾘﾋﾞﾝｸﾞ（但井） | AN32: 65000 | AO32: 吉野ｶﾞﾚｰｼﾞ | AP32: 165000 | AQ32: ウツミ屋証券 | AR32: 160000 | AS32: NPO | AT32: 205000
B33: ６月合計 | C33: =D33+M33+AD33 -> 45998871 | D33: =SUM(D3:D32) -> 10804885 | M33: =SUM(M3:M32) -> 25520872 | AD33: =SUM(AD3:AD32) -> 9673114
B34: 未確定
B35: 44378 | C35: =D35+M35+AD35 -> 50611 | D35: =F35+H35+J35+L35 -> 0 | M35: =O35+Q35+S35+U35+W35+Y35+AA35+AC35 -> 0 | AD35: =AF35+AH35+AJ35+AL35+AN35+AP35+AR35+AT35+AV35+AX35+AZ35+BB35+BD35+BF35+BH35+BJ35+BL35+BN35+BP35+BR35+BT35+BV35+BX35+BZ35+CB35+CD35 -> 50611 | AE35: もみじ）ﾄﾖﾀﾌｧｲﾅﾝｽ | AF35: 50611
B36: 45109 | C36: =D36+M36+AD36 -> 8000 | D36: =F36+H36+J36+L36 -> 8000 | E36: 笠信印紙代現金 | F36: 8000 | M36: =O36+Q36+S36+U36+W36+Y36+AA36+AC36 -> 0 | AD36: =AF36+AH36+AJ36+AL36+AN36+AP36+AR36+AT36+AV36+AX36+AZ36+BB36+BD36+BF36+BH36+BJ36+BL36+BN36+BP36+BR36+BT36+BV36+BX36+BZ36+CB36+CD36 -> 0
B37: 45110 | C37: =D37+M37+AD37 -> 0 | D37: =F37+H37+J37+L37 -> 0 | M37: =O37+Q37+S37+U37+W37+Y37+AA37+AC37 -> 0 | AD37: =AF37+AH37+AJ37+AL37+AN37+AP37+AR37+AT37+AV37+AX37+AZ37+BB37+BD37+BF37+BH37+BJ37+BL37+BN37+BP37+BR37+BT37+BV37+BX37+BZ37+CB37+CD37 -> 0 | AE37: 自賠責 | AF37: 0
B38: 45111 | C38: =D38+M38+AD38 -> 5872830 | D38: =F38+H38+J38+L38 -> 0 | M38: =O38+Q38+S38+U38+W38+Y38+AA38+AC38 -> 5731590 | N38: ｺﾝｸｴｽﾄ様追加BMWﾐﾆ ｼﾞｬｶﾞｰF | O38: 5731590 | AD38: =AF38+AH38+AJ38+AL38+AN38+AP38+AR38+AT38+AV38+AX38+AZ38+BB38+BD38+BF38+BH38+BJ38+BL38+BN38+BP38+BR38+BT38+BV38+BX38+BZ38+CB38+CD38 -> 141240 | AE38: 未来経営 | AF38: 88000 | AG38: ﾘｺｰPCﾘｰｽ | AH38: 53240
B39: 45112 | C39: =D39+M39+AD39 -> 0 | D39: =F39+H39+J39+L39 -> 0 | M39: =O39+Q39+S39+U39+W39+Y39+AA39+AC39 -> 0 | AD39: =AF39+AH39+AJ39+AL39+AN39+AP39+AR39+AT39+AV39+AX39+AZ39+BB39+BD39+BF39+BH39+BJ39+BL39+BN39+BP39+BR39+BT39+BV39+BX39+BZ39+CB39+CD39 -> 0
B40: 45113 | C40: =D40+M40+AD40 -> 0 | D40: =F40+H40+J40+L40 -> 0 | M40: =O40+Q40+S40+U40+W40+Y40+AA40+AC40 -> 0 | AD40: =AF40+AH40+AJ40+AL40+AN40+AP40+AR40+AT40+AV40+AX40+AZ40+BB40+BD40+BF40+BH40+BJ40+BL40+BN40+BP40+BR40+BT40+BV40+BX40+BZ40+CB40+CD40 -> 0
B41: 45114 | C41: =D41+M41+AD41 -> 1210 | D41: =F41+H41+J41+L41 -> 1210 | E41: 広信用支払手数料 | F41: 1210 | M41: =O41+Q41+S41+U41+W41+Y41+AA41+AC41 -> 0 | AD41: =AF41+AH41+AJ41+AL41+AN41+AP41+AR41+AT41+AV41+AX41+AZ41+BB41+BD41+BF41+BH41+BJ41+BL41+BN41+BP41+BR41+BT41+BV41+BX41+BZ41+CB41+CD41 -> 0
B42: 45115 | C42: =D42+M42+AD42 -> 107800 | D42: =F42+H42+J42+L42 -> 0 | M42: =O42+Q42+S42+U42+W42+Y42+AA42+AC42 -> 0 | AD42: =AF42+AH42+AJ42+AL42+AN42+AP42+AR42+AT42+AV42+AX42+AZ42+BB42+BD42+BF42+BH42+BJ42+BL42+BN42+BP42+BR42+BT42+BV42+BX42+BZ42+CB42+CD42 -> 107800 | AE42: 住民税 | AF42: 107800
B43: 45116 | C43: =D43+M43+AD43 -> 7810 | D43: =F43+H43+J43+L43 -> 7810 | E43: 7/10中銀FBｻｰﾋﾞｽ | F43: 3850 | G43: 7/10もみじ振込手数料 | H43: 330 | I43: 7/10もみじIB手数料 | J43: 3630 | M43: =O43+Q43+S43+U43+W43+Y43+AA43+AC43 -> 0 | AD43: =AF43+AH43+AJ43+AL43+AN43+AP43+AR43+AT43+AV43+AX43+AZ43+BB43+BD43+BF43+BH43+BJ43+BL43+BN43+BP43+BR43+BT43+BV43+BX43+BZ43+CB43+CD43 -> 0
B44: 45117 | C44: =D44+M44+AD44 -> 16084844 | D44: =F44+H44+J44+L44 -> 132155 | E44: 笠信 利息（現金） | F44: 116095 | G44: 広銀B-WEB基本料金 | H44: 1650 | I44: 広銀B-WEB伝送基本料金 | J44: 2530 | K44: 広銀振込手数料 | L44: 11880 | M44: =O44+Q44+S44+U44+W44+Y44+AA44+AC44 -> 0 | AD44: =AF44+AH44+AJ44+AL44+AN44+AP44+AR44+AT44+AV44+AX44+AZ44+BB44+BD44+BF44+BH44+BJ44+BL44+BN44+BP44+BR44+BT44+BV44+BX44+BZ44+CB44+CD44 -> 15952689 | AE44: 笠信）ｶｰﾄﾞ引落 ﾀﾞｲﾅｰｽﾞ(橋本社長) | AF44: 662909 | AG44: も)ﾀﾞｲﾅｰｽｶｰﾄﾞ・ﾄﾗｽﾄｸﾗﾌﾞ整備 | AH44: 192090 | AI44: も)ﾀﾞｲﾅｰｽｶｰﾄﾞ・ﾄﾗｽﾄｸﾗﾌﾞ | AJ44: 174969 | AK44: ｼﾞｬｯｸｽ | AL44: 11346592 | AM44: ｵｺｴ瑠偉様 | AN44: 953408 | AO44: 銚子様 | AP44: 170000 | AQ44: 給与 | AR44: 1766231 | AS44: 高田自動車 | AT44: 671890 | AU44: 自賠責 | AV44: 0 | AW44: 田中賢治様 | AX44: 14600
B45: 45118 | C45: =D45+M45+AD45 -> 130000 | D45: =F45+H45+J45+L45 -> 0 | M45: =O45+Q45+S45+U45+W45+Y45+AA45+AC45 -> 0 | AD45: =AF45+AH45+AJ45+AL45+AN45+AP45+AR45+AT45+AV45+AX45+AZ45+BB45+BD45+BF45+BH45+BJ45+BL45+BN45+BP45+BR45+BT45+BV45+BX45+BZ45+CB45+CD45 -> 130000 | AE45: 福山赤坂ﾛｰﾀﾘｰｸﾗﾌﾞ | AF45: 130000
B46: 45119 | C46: =D46+M46+AD46 -> 0 | D46: =F46+H46+J46+L46 -> 0 | M46: =O46+Q46+S46+U46+W46+Y46+AA46+AC46 -> 0 | AD46: =AF46+AH46+AJ46+AL46+AN46+AP46+AR46+AT46+AV46+AX46+AZ46+BB46+BD46+BF46+BH46+BJ46+BL46+BN46+BP46+BR46+BT46+BV46+BX46+BZ46+CB46+CD46 -> 0
B47: 45120 | C47: =D47+M47+AD47 -> 0 | D47: =F47+H47+J47+L47 -> 0 | M47: =O47+Q47+S47+U47+W47+Y47+AA47+AC47 -> 0 | AD47: =AF47+AH47+AJ47+AL47+AN47+AP47+AR47+AT47+AV47+AX47+AZ47+BB47+BD47+BF47+BH47+BJ47+BL47+BN47+BP47+BR47+BT47+BV47+BX47+BZ47+CB47+CD47 -> 0
B48: 45121 | C48: =D48+M48+AD48 -> 15493 | D48: =F48+H48+J48+L48 -> 0 | M48: =O48+Q48+S48+U48+W48+Y48+AA48+AC48 -> 0 | AD48: =AF48+AH48+AJ48+AL48+AN48+AP48+AR48+AT48+AV48+AX48+AZ48+BB48+BD48+BF48+BH48+BJ48+BL48+BN48+BP48+BR48+BT48+BV48+BX48+BZ48+CB48+CD48 -> 15493 | AE48: ｱｽｸﾙ | AF48: 15493
B49: 45122 | C49: =D49+M49+AD49 -> 0 | D49: =F49+H49+J49+L49 -> 0 | M49: =O49+Q49+S49+U49+W49+Y49+AA49+AC49 -> 0 | AD49: =AF49+AH49+AJ49+AL49+AN49+AP49+AR49+AT49+AV49+AX49+AZ49+BB49+BD49+BF49+BH49+BJ49+BL49+BN49+BP49+BR49+BT49+BV49+BX49+BZ49+CB49+CD49 -> 0
B50: 45123 | C50: =D50+M50+AD50 -> 0 | D50: =F50+H50+J50+L50 -> 0 | M50: =O50+Q50+S50+U50+W50+Y50+AA50+AC50 -> 0 | AD50: =AF50+AH50+AJ50+AL50+AN50+AP50+AR50+AT50+AV50+AX50+AZ50+BB50+BD50+BF50+BH50+BJ50+BL50+BN50+BP50+BR50+BT50+BV50+BX50+BZ50+CB50+CD50 -> 0
B51: 45124 | C51: =D51+M51+AD51 -> 700000 | D51: =F51+H51+J51+L51 -> 0 | M51: =O51+Q51+S51+U51+W51+Y51+AA51+AC51 -> 0 | AD51: =AF51+AH51+AJ51+AL51+AN51+AP51+AR51+AT51+AV51+AX51+AZ51+BB51+BD51+BF51+BH51+BJ51+BL51+BN51+BP51+BR51+BT51+BV51+BX51+BZ51+CB51+CD51 -> 700000 | AE51: 橋本祥子取締役 | AF51: 700000 | AG51: 自賠責 | AH51: 0
B52: 45125 | C52: =D52+M52+AD52 -> 557100 | D52: =F52+H52+J52+L52 -> 1100 | E52: 笠信支払手数料 | F52: 1100 | M52: =O52+Q52+S52+U52+W52+Y52+AA52+AC52 -> 0 | AD52: =AF52+AH52+AJ52+AL52+AN52+AP52+AR52+AT52+AV52+AX52+AZ52+BB52+BD52+BF52+BH52+BJ52+BL52+BN52+BP52+BR52+BT52+BV52+BX52+BZ52+CB52+CD52 -> 556000 | AE52: 固定資産税第二期 福山 | AF52: 556000
B53: 45126 | C53: =D53+M53+AD53 -> 0 | D53: =F53+H53+J53+L53 -> 0 | M53: =O53+Q53+S53+U53+W53+Y53+AA53+AC53 -> 0 | AD53: =AF53+AH53+AJ53+AL53+AN53+AP53+AR53+AT53+AV53+AX53+AZ53+BB53+BD53+BF53+BH53+BJ53+BL53+BN53+BP53+BR53+BT53+BV53+BX53+BZ53+CB53+CD53 -> 0
B54: 45127 | C54: =D54+M54+AD54 -> 0 | D54: =F54+H54+J54+L54 -> 0 | M54: =O54+Q54+S54+U54+W54+Y54+AA54+AC54 -> 0 | AD54: =AF54+AH54+AJ54+AL54+AN54+AP54+AR54+AT54+AV54+AX54+AZ54+BB54+BD54+BF54+BH54+BJ54+BL54+BN54+BP54+BR54+BT54+BV54+BX54+BZ54+CB54+CD54 -> 0
B55: 45128 | C55: =D55+M55+AD55 -> 0 | D55: =F55+H55+J55+L55 -> 0 | M55: =O55+Q55+S55+U55+W55+Y55+AA55+AC55 -> 0 | AD55: =AF55+AH55+AJ55+AL55+AN55+AP55+AR55+AT55+AV55+AX55+AZ55+BB55+BD55+BF55+BH55+BJ55+BL55+BN55+BP55+BR55+BT55+BV55+BX55+BZ55+CB55+CD55 -> 0
B56: 45129 | C56: =D56+M56+AD56 -> 0 | D56: =F56+H56+J56+L56 -> 0 | M56: =O56+Q56+S56+U56+W56+Y56+AA56+AC56 -> 0 | AD56: =AF56+AH56+AJ56+AL56+AN56+AP56+AR56+AT56+AV56+AX56+AZ56+BB56+BD56+BF56+BH56+BJ56+BL56+BN56+BP56+BR56+BT56+BV56+BX56+BZ56+CB56+CD56 -> 0
B57: 45130 | C57: =D57+M57+AD57 -> 48072 | D57: =F57+H57+J57+L57 -> 0 | M57: =O57+Q57+S57+U57+W57+Y57+AA57+AC57 -> 0 | AD57: =AF57+AH57+AJ57+AL57+AN57+AP57+AR57+AT57+AV57+AX57+AZ57+BB57+BD57+BF57+BH57+BJ57+BL57+BN57+BP57+BR57+BT57+BV57+BX57+BZ57+CB57+CD57 -> 48072 | AE57: も）ｷｬﾉﾝ | AF57: 15072 | AG57: 笠）㈱ﾌﾟﾛﾄｺｰﾎﾟﾚｰｼｮﾝ | AH57: 33000
B58: 45131 | C58: =D58+M58+AD58 -> 218366 | D58: =F58+H58+J58+L58 -> 0 | M58: =O58+Q58+S58+U58+W58+Y58+AA58+AC58 -> 150700 | N58: ﾌﾟﾚﾐｱﾜﾗﾝﾃｨｻｰﾋﾞｽ㈱ | O58: 150700 | AD58: =AF58+AH58+AJ58+AL58+AN58+AP58+AR58+AT58+AV58+AX58+AZ58+BB58+BD58+BF58+BH58+BJ58+BL58+BN58+BP58+BR58+BT58+BV58+BX58+BZ58+CB58+CD58 -> 67666 | AE58: 三井住友海上火災保険㈱ | AF58: 67666 | AG58: 自賠責 | AH58: 0
B59: 45132 | C59: =D59+M59+AD59 -> 280613 | D59: =F59+H59+J59+L59 -> 0 | M59: =O59+Q59+S59+U59+W59+Y59+AA59+AC59 -> 0 | AD59: =AF59+AH59+AJ59+AL59+AN59+AP59+AR59+AT59+AV59+AX59+AZ59+BB59+BD59+BF59+BH59+BJ59+BL59+BN59+BP59+BR59+BT59+BV59+BX59+BZ59+CB59+CD59 -> 280613 | AE59: SoleilﾏｾﾗﾃｨMC20賃貸借2024.9.1～2026.8.31 | AF59: 220000 | AG59: 鳥越翔太さん | AH59: 60613
B60: 45133 | C60: =D60+M60+AD60 -> 0 | D60: =F60+H60+J60+L60 -> 0 | M60: =O60+Q60+S60+U60+W60+Y60+AA60+AC60 -> 0 | AD60: =AF60+AH60+AJ60+AL60+AN60+AP60+AR60+AT60+AV60+AX60+AZ60+BB60+BD60+BF60+BH60+BJ60+BL60+BN60+BP60+BR60+BT60+BV60+BX60+BZ60+CB60+CD60 -> 0
B61: 45134 | C61: =D61+M61+AD61 -> 200220 | D61: =F61+H61+J61+L61 -> 220 | E61: もみじ支払手数料 | F61: 220 | M61: =O61+Q61+S61+U61+W61+Y61+AA61+AC61 -> 0 | AD61: =AF61+AH61+AJ61+AL61+AN61+AP61+AR61+AT61+AV61+AX61+AZ61+BB61+BD61+BF61+BH61+BJ61+BL61+BN61+BP61+BR61+BT61+BV61+BX61+BZ61+CB61+CD61 -> 200000 | AE61: もみじATMより（資金移動現金へ内120,000） | AF61: 200000
B62: 45135 | C62: =D62+M62+AD62 -> 584822 | D62: =F62+H62+J62+L62 -> 0 | M62: =O62+Q62+S62+U62+W62+Y62+AA62+AC62 -> 0 | AD62: =AF62+AH62+AJ62+AL62+AN62+AP62+AR62+AT62+AV62+AX62+AZ62+BB62+BD62+BF62+BH62+BJ62+BL62+BN62+BP62+BR62+BT62+BV62+BX62+BZ62+CB62+CD62 -> 584822 | AE62: 広）ｿﾌﾄﾊﾞﾝｸ | AF62: 44360 | AG62: も）ｶｰｾﾌﾞﾝﾃﾞｼﾞﾌｨｰﾙﾄﾞｲﾝｽﾏｰﾄｼｽﾃﾑ | AH62: 4620 | AI62: も）引落まるとく本社ｺﾋﾟｰ機 | AJ62: 1829 | AK62: も）ﾁｭｰﾘｯﾋ生命 | AL62: 6015 | AM62: も）ｵﾘｺｶｰｻｺﾋﾟｰ機 | AN62: 27293 | AO62: も）あんしん生命 | AP62: 58201 | AQ62: も）三和地所 | AR62: 67440 | AS62: もみじ)ｵﾘｺJCM | AT62: 99000 | AU62: も）ﾞ引落中国新聞 | AV62: 3900 | AW62: 笠）三井損害保険 | AX62: 172790 | AY62: 広）ﾔﾏﾄ運輸 | AZ62: 1716 | BA62: 中銀引落)USS月会費 | BB62: 12980 | BC62: 笠）富士生命 | BD62: 84678
B63: 45136 | C63: =D63+M63+AD63 -> 2933312 | D63: =F63+H63+J63+L63 -> 1040712 | E63: 7/31もみじ長期借入 | F63: 404000 | G63: 7/31笠信借入金5,000万継続 | H63: 626712 | I63: 7/31笠信5,000万印紙代 | J63: 10000 | M63: =O63+Q63+S63+U63+W63+Y63+AA63+AC63 -> 0 | AD63: =AF63+AH63+AJ63+AL63+AN63+AP63+AR63+AT63+AV63+AX63+AZ63+BB63+BD63+BF63+BH63+BJ63+BL63+BN63+BP63+BR63+BT63+BV63+BX63+BZ63+CB63+CD63 -> 1892600 | AE63: 自動車税 | AF63: 1892600
B64: 45137 | C64: =D64+M64+AD64 -> 4459110 | D64: =F64+H64+J64+L64 -> 4459110 | E64: 7/31笠信ｼｮｳｶﾞｼ | F64: 3109500 | G64: 7/31広銀ｼｮｳｶﾞｼ | H64: 240025 | I64: 7/31もみじ支払利息 | J64: 219585 | K64: 7/31もみじ長期借入 | L64: 890000 | M64: =O64+Q64+S64+U64+W64+Y64+AA64+AC64 -> 0 | AD64: =AF64+AH64+AJ64+AL64+AN64+AP64+AR64+AT64+AV64+AX64+AZ64+BB64+BD64+BF64+BH64+BJ64+BL64+BN64+BP64+BR64+BT64+BV64+BX64+BZ64+CB64+CD64 -> 0
B65: 45138 | C65: =D65+M65+AD65 -> 7015830 | D65: =F65+H65+J65+L65 -> 436295 | E65: 支払手数料 | F65: 770 | G65: 笠信貸付利息 | H65: 104041 | I65: ｺﾝｸｴｽﾄ様劣後利息 | J65: 26666 | K65: ｺﾝｸｴｽﾄ様ｸﾞﾚｶｰﾚﾃﾞﾓｶｰ分割 | L65: 304818 | M65: =O65+Q65+S65+U65+W65+Y65+AA65+AC65 -> 2251085 | N65: ｺﾝｸｴｽﾄJ&LR4月分請求書 | O65: 637549 | P65: 月末支払い整備 | Q65: 1613536 | AD65: =AF65+AH65+AJ65+AL65+AN65+AP65+AR65+AT65+AV65+AX65+AZ65+BB65+BD65+BF65+BH65+BJ65+BL65+BN65+BP65+BR65+BT65+BV65+BX65+BZ65+CB65+CD65 -> 4328450 | AE65: ﾋﾞｰﾌｨｰﾙﾄﾞ | AF65: 2200 | AG65: 大和ﾘﾋﾞﾝｸﾞ（但井） | AH65: 65000 | AI65: 吉野ｶﾞﾚｰｼﾞ | AJ65: 165000 | AK65: ウツミ屋証券 | AL65: 160000 | AM65: 月末支払（経費） | AN65: 332236 | AO65: ｸﾚｽﾄ不動産㈱返金分 | AP65: 1100 | AQ65: 笠）年金事務所 | AR65: 716858 | AS65: 自賠責 | AT65: 31830 | AU65: も）日本政策公庫 | AV65: 2854226
B66: ７月合計 | C66: =SUM(C35:C65) -> 39276043 | D66: =SUM(D35:D65) -> 6086612 | M66: =SUM(M35:M65) -> 8133375 | AD66: =SUM(AD35:AD65) -> 25056056
B67: 未確定
B68: 45139 | C68: =D68+M68+AD68 -> 361845 | D68: =F68+H68+J68+L68 -> 0 | M68: =O68+Q68+S68+U68 -> 288395 | N68: あかつか眼科クリニック様(ﾏｾﾗﾃｨ ｷﾞﾌﾞﾘ） | O68: 288395 | AD68: =AF68+AH68+AJ68+AL68+AN68+AP68+AR68+AT68+AV68+AX68+AZ68+BB68+BD68+BF68+BH68+BJ68+BL68+BN68+BP68+BR68+BT68+BV68+BX68+BZ68+CB68 -> 73450 | AE68: 取締役(堀病院治療費) | AF68: 73450
B69: 45140 | C69: =D69+M69+AD69 -> 0 | D69: =F69+H69+J69+L69 -> 0 | M69: =O69+Q69+S69+U69 -> 0 | AD69: =AF69+AH69+AJ69+AL69+AN69+AP69+AR69+AT69+AV69+AX69+AZ69+BB69+BD69+BF69+BH69+BJ69+BL69+BN69+BP69+BR69+BT69+BV69+BX69+BZ69+CB69 -> 0
B70: 45141 | C70: =D70+M70+AD70 -> 0 | D70: =F70+H70+J70+L70 -> 0 | M70: =O70+Q70+S70+U70 -> 0 | AD70: =AF70+AH70+AJ70+AL70+AN70+AP70+AR70+AT70+AV70+AX70+AZ70+BB70+BD70+BF70+BH70+BJ70+BL70+BN70+BP70+BR70+BT70+BV70+BX70+BZ70+CB70 -> 0
B71: 45142 | C71: =D71+M71+AD71 -> 874069 | D71: =F71+H71+J71+L71 -> 0 | M71: =O71+Q71+S71+U71 -> 0 | AD71: =AF71+AH71+AJ71+AL71+AN71+AP71+AR71+AT71+AV71+AX71+AZ71+BB71+BD71+BF71+BH71+BJ71+BL71+BN71+BP71+BR71+BT71+BV71+BX71+BZ71+CB71 -> 874069 | AE71: 未来経営 | AF71: 418000 | AG71: ﾘｺｰPCﾘｰｽ | AH71: 53240 | AI71: もみじ）ﾄﾖﾀﾌｧｲﾅﾝｽ | AJ71: 50162 | AK71: 橋本社長（立替分） | AL71: 207680 | AM71: 橋本商事（立替分） | AN71: 51887 | AO71: 住民税 | AP71: 93100
B72: 45143 | C72: =D72+M72+AD72 -> 0 | D72: =F72+H72+J72+L72 -> 0 | M72: =O72+Q72+S72+U72 -> 0 | AD72: =AF72+AH72+AJ72+AL72+AN72+AP72+AR72+AT72+AV72+AX72+AZ72+BB72+BD72+BF72+BH72+BJ72+BL72+BN72+BP72+BR72+BT72+BV72+BX72+BZ72+CB72 -> 0
B73: 45144 | C73: =D73+M73+AD73 -> 0 | D73: =F73+H73+J73+L73 -> 0 | M73: =O73+Q73+S73+U73 -> 0 | AD73: =AF73+AH73+AJ73+AL73+AN73+AP73+AR73+AT73+AV73+AX73+AZ73+BB73+BD73+BF73+BH73+BJ73+BL73+BN73+BP73+BR73+BT73+BV73+BX73+BZ73+CB73 -> 0
B74: 45145 | C74: =D74+M74+AD74 -> 1210 | D74: =F74+H74+J74+L74 -> 1210 | E74: 広信支払手数料 | F74: 1210 | M74: =O74+Q74+S74+U74 -> 0 | AD74: =AF74+AH74+AJ74+AL74+AN74+AP74+AR74+AT74+AV74+AX74+AZ74+BB74+BD74+BF74+BH74+BJ74+BL74+BN74+BP74+BR74+BT74+BV74+BX74+BZ74+CB74 -> 0 | AE74: 自賠責 | AF74: 0
B75: 45146 | C75: =D75+M75+AD75 -> 3134564 | D75: =F75+H75+J75+L75 -> 0 | M75: =O75+Q75+S75+U75 -> 2745129 | N75: ｵｰﾄｻｰﾊﾞｰ様(竹本様MINI仕入） | O75: 2745129 | AD75: =AF75+AH75+AJ75+AL75+AN75+AP75+AR75+AT75+AV75+AX75+AZ75+BB75+BD75+BF75+BH75+BJ75+BL75+BN75+BP75+BR75+BT75+BV75+BX75+BZ75+CB75 -> 389435 | AE75: 田中賢治様 | AF75: 214600 | AG75: 銚子部長 | AH75: 170000 | AI75: ｱｽｸﾙ | AJ75: 4835
B76: 45147 | C76: =D76+M76+AD76 -> 0 | D76: =F76+H76+J76+L76 -> 0 | M76: =O76+Q76+S76+U76 -> 0 | AD76: =AF76+AH76+AJ76+AL76+AN76+AP76+AR76+AT76+AV76+AX76+AZ76+BB76+BD76+BF76+BH76+BJ76+BL76+BN76+BP76+BR76+BT76+BV76+BX76+BZ76+CB76 -> 0
B77: 45148 | C77: =D77+M77+AD77 -> 0 | D77: =F77+H77+J77+L77 -> 0 | M77: =O77+Q77+S77+U77 -> 0 | AD77: =AF77+AH77+AJ77+AL77+AN77+AP77+AR77+AT77+AV77+AX77+AZ77+BB77+BD77+BF77+BH77+BJ77+BL77+BN77+BP77+BR77+BT77+BV77+BX77+BZ77+CB77 -> 0
B78: 45149 | C78: =D78+M78+AD78 -> 0 | D78: =F78+H78+J78+L78 -> 0 | M78: =O78+Q78+S78+U78 -> 0 | AD78: =AF78+AH78+AJ78+AL78+AN78+AP78+AR78+AT78+AV78+AX78+AZ78+BB78+BD78+BF78+BH78+BJ78+BL78+BN78+BP78+BR78+BT78+BV78+BX78+BZ78+CB78 -> 0
B79: 45150 | C79: =D79+M79+AD79 -> 3438606 | D79: =F79+H79+J79+L79 -> 19085 | E79: 中銀FBｻｰﾋﾞｽ | F79: 3850 | G79: 広銀B-WEB基本料金 | H79: 1650 | I79: 広銀B-WEB伝送基本料金 | J79: 2530 | K79: 広銀B-WEB振込手数料 | L79: 11055 | M79: =O79+Q79+S79+U79 -> 0 | AD79: =AF79+AH79+AJ79+AL79+AN79+AP79+AR79+AT79+AV79+AX79+AZ79+BB79+BD79+BF79+BH79+BJ79+BL79+BN79+BP79+BR79+BT79+BV79+BX79+BZ79+CB79 -> 3419521 | AE79: 笠）ﾀﾞｲﾅｰｽﾞ(橋本社長) | AF79: 687246 | AG79: も）ﾀﾞｲﾅｰｽﾞ | AH79: 211269 | AI79: も）ﾀﾞｲﾅｰｽﾞ(整備） | AJ79: 195758 | AK79: 給与 | AL79: 1176541 | AM79: 高田自動車 | AN79: 448707 | AO79: 橋本祥子様 | AP79: 700000
B80: 45151 | C80: =D80+M80+AD80 -> 3960 | D80: =F80+H80+J80+L80 -> 3960 | E80: 8/12もみじ振込手数料 | F80: 330 | G80: 8/12もみじIB手数料 | H80: 3630 | M80: =O80+Q80+S80+U80 -> 0 | AD80: =AF80+AH80+AJ80+AL80+AN80+AP80+AR80+AT80+AV80+AX80+AZ80+BB80+BD80+BF80+BH80+BJ80+BL80+BN80+BP80+BR80+BT80+BV80+BX80+BZ80+CB80 -> 0
B81: 45152 | C81: =D81+M81+AD81 -> 0 | D81: =F81+H81+J81+L81 -> 0 | M81: =O81+Q81+S81+U81 -> 0 | AD81: =AF81+AH81+AJ81+AL81+AN81+AP81+AR81+AT81+AV81+AX81+AZ81+BB81+BD81+BF81+BH81+BJ81+BL81+BN81+BP81+BR81+BT81+BV81+BX81+BZ81+CB81 -> 0
B82: 45153 | C82: =D82+M82+AD82 -> 0 | D82: =F82+H82+J82+L82 -> 0 | M82: =O82+Q82+S82+U82 -> 0 | AD82: =AF82+AH82+AJ82+AL82+AN82+AP82+AR82+AT82+AV82+AX82+AZ82+BB82+BD82+BF82+BH82+BJ82+BL82+BN82+BP82+BR82+BT82+BV82+BX82+BZ82+CB82 -> 0
B83: 45154 | C83: =D83+M83+AD83 -> 0 | D83: =F83+H83+J83+L83 -> 0 | M83: =O83+Q83+S83+U83 -> 0 | AD83: =AF83+AH83+AJ83+AL83+AN83+AP83+AR83+AT83+AV83+AX83+AZ83+BB83+BD83+BF83+BH83+BJ83+BL83+BN83+BP83+BR83+BT83+BV83+BX83+BZ83+CB83 -> 0
B84: 45155 | C84: =D84+M84+AD84 -> 0 | D84: =F84+H84+J84+L84 -> 0 | M84: =O84+Q84+S84+U84 -> 0 | AD84: =AF84+AH84+AJ84+AL84+AN84+AP84+AR84+AT84+AV84+AX84+AZ84+BB84+BD84+BF84+BH84+BJ84+BL84+BN84+BP84+BR84+BT84+BV84+BX84+BZ84+CB84 -> 0
B85: 45156 | C85: =D85+M85+AD85 -> 15409857 | D85: =F85+H85+J85+L85 -> 880 | E85: 中銀手数料 | F85: 880 | M85: =O85+Q85+S85+U85 -> 15297877 | N85: ｽﾄﾛﾝｸﾞﾏｳﾝﾃﾝ様(ｱﾙﾌｧｰﾄﾞ買取) | O85: 5876650 | P85: ｵﾘｺｺｰﾎﾟﾚｰｼｮﾝ（あかつか眼科クリニック） | Q85: 7341651 | R85: ｵﾘｺｺｰﾎﾟﾚｰｼｮﾝ（dyﾏｰｹﾃｨﾝｸﾞ様） | S85: 2079576 | AD85: =AF85+AH85+AJ85+AL85+AN85+AP85+AR85+AT85+AV85+AX85+AZ85+BB85+BD85+BF85+BH85+BJ85+BL85+BN85+BP85+BR85+BT85+BV85+BX85+BZ85+CB85 -> 111100 | AE85: 笠信支払手数料 | AF85: 1100 | AG85: ㈱ﾊﾞﾃﾞｨｰｽﾞ様 | AH85: 110000
B86: 45157 | C86: =D86+M86+AD86 -> 29052 | D86: =F86+H86+J86+L86 -> 0 | M86: =O86+Q86+S86+U86 -> 0 | AD86: =AF86+AH86+AJ86+AL86+AN86+AP86+AR86+AT86+AV86+AX86+AZ86+BB86+BD86+BF86+BH86+BJ86+BL86+BN86+BP86+BR86+BT86+BV86+BX86+BZ86+CB86 -> 29052 | AG86: 所得税追加分 | AH86: 29052
B87: 45158 | C87: =D87+M87+AD87 -> 22895 | D87: =F87+H87+J87+L87 -> 0 | M87: =O87+Q87+S87+U87 -> 0 | AD87: =AF87+AH87+AJ87+AL87+AN87+AP87+AR87+AT87+AV87+AX87+AZ87+BB87+BD87+BF87+BH87+BJ87+BL87+BN87+BP87+BR87+BT87+BV87+BX87+BZ87+CB87 -> 22895 | AE87: 本社水道代引落 | AF87: 14799 | AG87: 水道料J&LR | AH87: 4026 | AI87: 本社水道代引落 | AJ87: 4070
B88: 45159 | C88: =D88+M88+AD88 -> 432977 | D88: =F88+H88+J88+L88 -> 550 | E88: 手数料 | F88: 550 | M88: =O88+Q88+S88+U88 -> 350309 | N88: ｺﾝｸｴｽﾄ様整備代金廣岡様 | O88: 15600 | P88: ｺﾝｸｴｽﾄ様ｿﾚｲﾕ様車検立替分 | Q88: 334709 | AD88: =AF88+AH88+AJ88+AL88+AN88+AP88+AR88+AT88+AV88+AX88+AZ88+BB88+BD88+BF88+BH88+BJ88+BL88+BN88+BP88+BR88+BT88+BV88+BX88+BZ88+CB88 -> 82118 | AE88: 自賠責 | AF88: 0 | AG88: 三井住友海上火災保険㈱ | AH88: 77118 | AI88: 竹本様MINI希望ﾅﾝﾊﾞｰ | AJ88: 5000
B89: 45160 | C89: =D89+M89+AD89 -> 1886250 | D89: =F89+H89+J89+L89 -> 0 | M89: =O89+Q89+S89+U89 -> 1886250 | N89: ﾜﾀﾔ自動車㈱ | O89: 1886250 | AD89: =AF89+AH89+AJ89+AL89+AN89+AP89+AR89+AT89+AV89+AX89+AZ89+BB89+BD89+BF89+BH89+BJ89+BL89+BN89+BP89+BR89+BT89+BV89+BX89+BZ89+CB89 -> 0
B90: 45161 | C90: =D90+M90+AD90 -> 0 | D90: =F90+H90+J90+L90 -> 0 | M90: =O90+Q90+S90+U90 -> 0 | AD90: =AF90+AH90+AJ90+AL90+AN90+AP90+AR90+AT90+AV90+AX90+AZ90+BB90+BD90+BF90+BH90+BJ90+BL90+BN90+BP90+BR90+BT90+BV90+BX90+BZ90+CB90 -> 0
B91: 45162 | C91: =D91+M91+AD91 -> 0 | D91: =F91+H91+J91+L91 -> 0 | M91: =O91+Q91+S91+U91 -> 0 | AD91: =AF91+AH91+AJ91+AL91+AN91+AP91+AR91+AT91+AV91+AX91+AZ91+BB91+BD91+BF91+BH91+BJ91+BL91+BN91+BP91+BR91+BT91+BV91+BX91+BZ91+CB91 -> 0
B92: 45163 | C92: =D92+M92+AD92 -> 351238 | D92: =F92+H92+J92+L92 -> 0 | M92: =O92+Q92+S92+U92 -> 303594 | N92: ｺﾝｸｴｽﾄ様IMMSｱｶﾃﾞﾐｰ様ﾅｶｶﾞﾜﾕﾐ | O92: 83594 | P92: SoleilﾏｾﾗﾃｨMC20賃貸借2024.9.1～2026.8.31 | Q92: 220000 | AD92: =AF92+AH92+AJ92+AL92+AN92+AP92+AR92+AT92+AV92+AX92+AZ92+BB92+BD92+BF92+BH92+BJ92+BL92+BN92+BP92+BR92+BT92+BV92+BX92+BZ92+CB92 -> 47644 | AE92: も）ｷｬﾉﾝ | AF92: 14644 | AG92: 笠）㈱ﾌﾟﾛﾄｺｰﾎﾟﾚｰｼｮﾝ | AH92: 33000
B93: 45164 | C93: =D93+M93+AD93 -> 333644 | D93: =F93+H93+J93+L93 -> 102200 | E93: 笠信（印紙代） | F93: 102200 | M93: =O93+Q93+S93+U93 -> 0 | AD93: =AF93+AH93+AJ93+AL93+AN93+AP93+AR93+AT93+AV93+AX93+AZ93+BB93+BD93+BF93+BH93+BJ93+BL93+BN93+BP93+BR93+BT93+BV93+BX93+BZ93+CB93 -> 231444 | AE93: も）㈱ﾕﾆﾏｯﾄﾗｲﾌ | AF93: 4400 | AG93: 広）ｿﾌﾄﾊﾞﾝｸ | AH93: 44701 | AI93: 笠）三井損害保険 | AJ93: 172940 | AK93: も)中国新聞 | AL93: 3900 | AM93: も）まるとく本社ｺﾋﾟｰ機 | AN93: 5503
B94: 45165 | C94: =D94+M94+AD94 -> 109504544 | D94: =F94+H94+J94+L94 -> 109144317 | E94: ㈱日本政策金融金庫（8/27付） | F94: 324317 | G94: 8/29もみじ短期借入金返済 | H94: 30000000 | I94: 8/29もみじ返済 | J94: 60660000 | K94: 8/29もみじ返済 | L94: 18160000 | M94: =O94+Q94+S94+U94 -> 0 | AD94: =AF94+AH94+AJ94+AL94+AN94+AP94+AR94+AT94+AV94+AX94+AZ94+BB94+BD94+BF94+BH94+BJ94+BL94+BN94+BP94+BR94+BT94+BV94+BX94+BZ94+CB94 -> 360227 | AE94: 中)USS月会費 | AF94: 12980 | AG94: 笠）富士生命 | AH94: 84678 | AI94: も）ｶｰｾﾌﾞﾝﾃﾞｼﾞﾌｨｰﾙﾄﾞｲﾝｽﾏｰﾄｼｽﾃﾑ | AJ94: 4620 | AK94: も）ﾁｭｰﾘｯﾋ生命 | AL94: 6015 | AM94: も）ｵﾘｺｶｰｻｺﾋﾟｰ機 | AN94: 27293 | AO94: も）あんしん生命 | AP94: 58201 | AQ94: も）三和地所 | AR94: 67440 | AS94: も)ｵﾘｺJCM | AT94: 99000
B95: 45166 | C95: =D95+M95+AD95 -> 3086760 | D95: =F95+H95+J95+L95 -> 3023100 | E95: 広銀蔵王より笠信固定へ資金移動 | F95: 3000000 | G95: 8/29中銀支払手数料 | H95: 770 | I95: 8/29もみじ手数料 | J95: 22000 | K95: 8/29笠信支払手数料 | L95: 330 | M95: =O95+Q95+S95+U95 -> 0 | AD95: =AF95+AH95+AJ95+AL95+AN95+AP95+AR95+AT95+AV95+AX95+AZ95+BB95+BD95+BF95+BH95+BJ95+BL95+BN95+BP95+BR95+BT95+BV95+BX95+BZ95+CB95 -> 63660 | AE95: 自賠責 | AF95: 63660
B96: 45167 | C96: =D96+M96+AD96 -> 321005392 | D96: =F96+H96+J96+L96 -> 315178256 | E96: 笠信 7/3分短期借入金1,250万（内利息20,547円 | F96: 12520547 | G96: 笠信 | H96: 193803829 | I96: 笠信 | J96: 108820880 | K96: 笠信担保手数料 | L96: 33000 | M96: =O96+Q96+S96+U96+W96 -> 5106883 | N96: 月末支払い整備 | O96: 1869285 | P96: ｺﾝｸｴｽﾄJ&LR7月分請求書 | Q96: 2707433 | R96: ｺﾝｸｴｽﾄﾏｾﾗﾃｨCS6810 | S96: 304334 | T96: ｺﾝｸｴｽﾄ利息 | U96: 26666 | V96: ｺﾝｸｴｽﾄﾏｾﾗﾃｨ分 | W96: 199165 | AD96: =AF96+AH96+AJ96+AL96+AN96+AP96+AR96+AT96+AV96+AX96+AZ96+BB96+BD96+BF96+BH96+BJ96+BL96+BN96+BP96+BR96+BT96+BV96+BX96+BZ96+CB96 -> 720253 | AE96: 大和ﾘﾋﾞﾝｸﾞ（但井） | AF96: 65000 | AG96: 吉野ｶﾞﾚｰｼﾞ | AH96: 165000 | AI96: ウツミ屋証券 | AJ96: 160000 | AK96: 月末支払(経費） | AL96: 330253
B97: 45168 | C97: =D97+M97+AD97 -> 0 | D97: =F97+H97+J97+L97 -> 0 | M97: =O97+Q97+S97+U97 -> 0 | AD97: =AF97+AH97+AJ97+AL97+AN97+AP97+AR97+AT97+AV97+AX97+AZ97+BB97+BD97+BF97+BH97+BJ97+BL97+BN97+BP97+BR97+BT97+BV97+BX97+BZ97+CB97 -> 0
B98: 45169 | C98: =D98+M98+AD98 -> 28602 | D98: =F98+H98+J98+L98 -> 28602 | E98: 9/1もみじ融資利息 | F98: 28602 | M98: =O98+Q98+S98+U98 -> 0 | AD98: =AF98+AH98+AJ98+AL98+AN98+AP98+AR98+AT98+AV98+AX98+AZ98+BB98+BD98+BF98+BH98+BJ98+BL98+BN98+BP98+BR98+BT98+BV98+BX98+BZ98+CB98 -> 0
B99: ８月合計 | C99: =SUM(C68:C98) -> 459905465 | D99: =SUM(D68:D98) -> 427502160 | M99: =SUM(M68:M98) -> 25978437 | AD99: =SUM(AD68:AD98) -> 6424868
B100: 未確定
...

Sheet 入出金合計表 【第16期2024年6月～】  
B1: 2024年5月末残 | C1: ='入出金合計表 【第15期2023年6月～】 '!C392 -> 23772071
C2: ２０２4年６月‐２０２5年５月残高
C3: 残高日次 | D3: 入金合計 | E3: 金融機関関連 | F3: 保険関連 | G3: お客様関連 | H3: 出金合計 | I3: 金融機関関連 | J3: 買掛関連 | K3: 経費関連
B4: 44348 | C4: =SUM(C1+D4-H4) -> 23772071 | D4: =E4+F4+G4 -> 0 | E4: ='入金明細 '!D3 -> 0 | F4: ='入金明細 '!M3 | G4: ='入金明細 '!T3 -> 0 | H4: =I4+J4+K4 -> 0 | I4: ='出金明細 '!D3 -> 0 | J4: ='出金明細 '!M3 -> 0 | K4: ='出金明細 '!AD3 -> 0
B5: 44349 | C5: =SUM(C4+D5-H5) -> 23772071 | D5: =E5+F5+G5 -> 0 | E5: ='入金明細 '!D4 -> 0 | F5: ='入金明細 '!M4 | G5: ='入金明細 '!T4 -> 0 | H5: =I5+J5+K5 -> 0 | I5: ='出金明細 '!D4 -> 0 | J5: ='出金明細 '!M4 -> 0 | K5: ='出金明細 '!AD4 -> 0
B6: 45446 | C6: =SUM(C5+D6-H6) -> 23096733 | D6: =E6+F6+G6 -> 258940 | E6: ='入金明細 '!D5 -> 0 | F6: ='入金明細 '!M5 | G6: ='入金明細 '!T5 -> 258940 | H6: =I6+J6+K6 -> 934278 | I6: ='出金明細 '!D5 -> 0 | J6: ='出金明細 '!M5 -> 0 | K6: ='出金明細 '!AD5 -> 934278
B7: 44351 | C7: =SUM(C6+D7-H7) -> 23394341 | D7: =E7+F7+G7 -> 364708 | E7: ='入金明細 '!D6 -> 0 | F7: ='入金明細 '!M6 | G7: ='入金明細 '!T6 -> 364708 | H7: =I7+J7+K7 -> 67100 | I7: ='出金明細 '!D6 -> 0 | J7: ='出金明細 '!M6 -> 0 | K7: ='出金明細 '!AD6 -> 67100
B8: 44352 | C8: =SUM(C7+D8-H8) -> 28629101 | D8: =E8+F8+G8 -> 5234760 | E8: ='入金明細 '!D7 -> 0 | F8: ='入金明細 '!M7 -> 0 | G8: ='入金明細 '!T7 -> 5234760 | H8: =I8+J8+K8 -> 0 | I8: ='出金明細 '!D7 -> 0 | J8: ='出金明細 '!M7 -> 0 | K8: ='出金明細 '!AD7 -> 0
B9: 44353 | C9: =SUM(C8+D9-H9) -> 28618551 | D9: =E9+F9+G9 -> 0 | E9: ='入金明細 '!D8 -> 0 | F9: ='入金明細 '!M8 -> 0 | G9: ='入金明細 '!T8 -> 0 | H9: =I9+J9+K9 -> 10550 | I9: ='出金明細 '!D8 -> 10550 | J9: ='出金明細 '!M8 -> 0 | K9: ='出金明細 '!AD8 -> 0
B10: 44354 | C10: =SUM(C9+D10-H10) -> 37183388 | D10: =E10+F10+G10 -> 43848730 | E10: ='入金明細 '!D9 -> 43463220 | F10: ='入金明細 '!M9 -> 150000 | G10: ='入金明細 '!T9 -> 235510 | H10: =I10+J10+K10 -> 35283893 | I10: ='出金明細 '!D9 -> 5002750 | J10: ='出金明細 '!M9 -> 30085813 | K10: ='出金明細 '!AD9 -> 195330
B11: 44355 | C11: =SUM(C10+D11-H11) -> 37183388 | D11: =E11+F11+G11 -> 0 | E11: ='入金明細 '!D10 -> 0 | F11: ='入金明細 '!M10 -> 0 | G11: ='入金明細 '!T10 -> 0 | H11: =I11+J11+K11 -> 0 | I11: ='出金明細 '!D10 -> 0 | J11: ='出金明細 '!M10 -> 0 | K11: ='出金明細 '!AD10 -> 0
B12: 44356 | C12: =SUM(C11+D12-H12) -> 37183388 | D12: =E12+F12+G12 -> 0 | E12: ='入金明細 '!D11 -> 0 | F12: ='入金明細 '!M11 -> 0 | G12: ='入金明細 '!T11 -> 0 | H12: =I12+J12+K12 -> 0 | I12: ='出金明細 '!D11 -> 0 | J12: ='出金明細 '!M11 -> 0 | K12: ='出金明細 '!AD11 -> 0
B13: 44357 | C13: =SUM(C12+D13-H13) -> 34283042 | D13: =E13+F13+G13 -> 82137 | E13: ='入金明細 '!D12 -> 0 | F13: ='入金明細 '!M12 -> 25000 | G13: ='入金明細 '!T12 -> 57137 | H13: =I13+J13+K13 -> 2982483 | I13: ='出金明細 '!D12 -> 26026 | J13: ='出金明細 '!M12 -> 0 | K13: ='出金明細 '!AD12 -> 2956457
B14: 44358 | C14: =SUM(C13+D14-H14) -> 34628051 | D14: =E14+F14+G14 -> 345009 | E14: ='入金明細 '!D13 -> 0 | F14: ='入金明細 '!M13 -> 0 | G14: ='入金明細 '!T13 -> 345009 | H14: =I14+J14+K14 -> 0 | I14: ='出金明細 '!D13 -> 0 | J14: ='出金明細 '!M13 -> 0 | K14: ='出金明細 '!AD13 -> 0
B15: 44359 | C15: =SUM(C14+D15-H15) -> 21313115 | D15: =E15+F15+G15 -> 0 | E15: ='入金明細 '!D14 -> 0 | F15: ='入金明細 '!M14 -> 0 | G15: ='入金明細 '!T14 -> 0 | H15: =I15+J15+K15 -> 13314936 | I15: ='出金明細 '!D14 -> 0 | J15: ='出金明細 '!M14 -> 13314936 | K15: ='出金明細 '!AD14 -> 0
B16: 44360 | C16: =SUM(C15+D16-H16) -> 21423115 | D16: =E16+F16+G16 -> 110000 | E16: ='入金明細 '!D15 -> 0 | F16: ='入金明細 '!M15 -> 110000 | G16: ='入金明細 '!T15 -> 0 | H16: =I16+J16+K16 -> 0 | I16: ='出金明細 '!D15 -> 0 | J16: ='出金明細 '!M15 -> 0 | K16: ='出金明細 '!AD15 -> 0
... B33: 44377 | C33: =SUM(C32+D33-H33) -> 12863955 | D33: =E33+F33+G33 -> 0 | E33: ='入金明細 '!D32 -> 0 | F33: ='入金明細 '!M32 -> 0 | G33: ='入金明細 '!T32 -> 0 | H33: =I33+J33+K33 -> 0 | I33: ='出金明細 '!D32 -> 0 | J33: ='出金明細 '!M32 -> 0 | K33: ='出金明細 '!AD32 -> 0
B34: 6月合計 | C34: =SUM(D34-H34) -> -10908116 | D34: =E34+F34+G34 -> 118076821 | E34: =SUM(E4:E33) -> 73474038 | F34: =SUM(F4:F33) -> 2809482 | G34: =SUM(G4:G33) -> 41793301 | H34: =SUM(H4:H33) -> 128984937 | I34: =SUM(I4:I33) -> 63276558 | J34: =SUM(J4:J33) -> 57912062 | K34: =SUM(K4:K33) -> 7796317
B35: 累計 | C35: =SUM(D35-H35) -> -10908116 | D35: =E35+F35+G35 -> 118076821 | E35: =E2+E34 -> 73474038 | F35: =F2+F34 -> 2809482 | G35: =G2+G34 -> 41793301 | H35: =H2+H34 -> 128984937 | I35: =I2+I34 -> 63276558 | J35: =J2+J34 -> 57912062 | K35: =K2+K34 -> 7796317
B36: 44378 | C36: =SUM(C33+D36-H36) -> 11144408 | D36: =E36+F36+G36 -> 10787540 | E36: ='入金明細 '!D35 -> 0 | F36: ='入金明細 '!M35 -> 0 | G36: ='入金明細 '!T35 -> 10787540 | H36: =I36+J36+K36 -> 12507087 | I36: ='出金明細 '!D35 -> 5333765 | J36: ='出金明細 '!M35 -> 6592163 | K36: ='出金明細 '!AD35 -> 581159
B37: 45109 | C37: =SUM(C36+D37-H37) -> 10935856 | D37: =E37+F37+G37 -> 0 | E37: ='入金明細 '!D36 -> 0 | F37: ='入金明細 '!M36 -> 0 | G37: ='入金明細 '!T36 -> 0 | H37: =I37+J37+K37 -> 208552 | I37: ='出金明細 '!D36 -> 0 | J37: ='出金明細 '!M36 -> 0 | K37: ='出金明細 '!AD36 -> 208552
B38: 45110 | C38: =SUM(C37+D38-H38) -> 10935856 | D38: =E38+F38+G38 -> 0 | E38: ='入金明細 '!D37 -> 0 | F38: ='入金明細 '!M37 -> 0 | G38: ='入金明細 '!T37 -> 0 | H38: =I38+J38+K38 -> 0 | I38: ='出金明細 '!D37 -> 0 | J38: ='出金明細 '!M37 -> 0 | K38: ='出金明細 '!AD37 -> 0
B39: 45111 | C39: =SUM(C38+D39-H39) -> 10563352 | D39: =E39+F39+G39 -> 0 | E39: ='入金明細 '!D38 -> 0 | F39: ='入金明細 '!M38 -> 0 | G39: ='入金明細 '!T38 -> 0 | H39: =I39+J39+K39 -> 372504 | I39: ='出金明細 '!D38 -> 0 | J39: ='出金明細 '!M38 -> 0 | K39: ='出金明細 '!AD38 -> 372504
B40: 45112 | C40: =SUM(C39+D40-H40) -> 6677925 | D40: =E40+F40+G40 -> 42837 | E40: ='入金明細 '!D39 -> 0 | F40: ='入金明細 '!M39 -> 0 | G40: ='入金明細 '!T39 -> 42837 | H40: =I40+J40+K40 -> 3928264 | I40: ='出金明細 '!D39 -> 0 | J40: ='出金明細 '!M39 -> 3928264 | K40: ='出金明細 '!AD39 -> 0
B41: 45113 | C41: =SUM(C40+D41-H41) -> 6677925 | D41: =E41+F41+G41 -> 0 | E41: ='入金明細 '!D40 -> 0 | F41: ='入金明細 '!M40 -> 0 | G41: ='入金明細 '!T40 -> 0 | H41: =I41+J41+K41 -> 0 | I41: ='出金明細 '!D40 -> 0 | J41: ='出金明細 '!M40 -> 0 | K41: ='出金明細 '!AD40 -> 0
B42: 45114 | C42: =SUM(C41+D42-H42) -> 6677925 | D42: =E42+F42+G42 -> 0 | E42: ='入金明細 '!D41 -> 0 | F42: ='入金明細 '!M41 -> 0 | G42: ='入金明細 '!T41 -> 0 | H42: =I42+J42+K42 -> 0 | I42: ='出金明細 '!D41 -> 0 | J42: ='出金明細 '!M41 -> 0 | K42: ='出金明細 '!AD41 -> 0
B43: 45115 | C43: =SUM(C42+D43-H43) -> 7014855 | D43: =E43+F43+G43 -> 345960 | E43: ='入金明細 '!D42 -> 0 | F43: ='入金明細 '!M42 -> 0 | G43: ='入金明細 '!T42 -> 345960 | H43: =I43+J43+K43 -> 9030 | I43: ='出金明細 '!D42 -> 1210 | J43: ='出金明細 '!M42 -> 0 | K43: ='出金明細 '!AD42 -> 7820
B44: 45116 | C44: =SUM(C43+D44-H44) -> 19463595 | D44: =E44+F44+G44 -> 12448740 | E44: ='入金明細 '!D43 -> 0 | F44: ='入金明細 '!M43 -> 0 | G44: ='入金明細 '!T43 -> 12448740 | H44: =I44+J44+K44 -> 0 | I44: ='出金明細 '!D43 -> 0 | J44: ='出金明細 '!M43 -> 0 | K44: ='出金明細 '!AD43 -> 0
B45: 45117 | C45: =SUM(C44+D45-H45) -> 19966254 | D45: =E45+F45+G45 -> 5258343 | E45: ='入金明細 '!D44 -> 0 | F45: ='入金明細 '!M44 -> 17520 | G45: ='入金明細 '!T44 -> 5240823 | H45: =I45+J45+K45 -> 4755684 | I45: ='出金明細 '!D44 -> 1526400 | J45: ='出金明細 '!M44 -> 0 | K45: ='出金明細 '!AD44 -> 3229284
B46: 45118 | C46: =SUM(C45+D46-H46) -> 19932812 | D46: =E46+F46+G46 -> 79008 | E46: ='入金明細 '!D45 -> 0 | F46: ='入金明細 '!M45 -> 79008 | G46: ='入金明細 '!T45 -> 0 | H46: =I46+J46+K46 -> 112450 | I46: ='出金明細 '!D45 -> 0 | J46: ='出金明細 '!M45 -> 0 | K46: ='出金明細 '!AD45 -> 112450
B47: 45119 | C47: =SUM(C46+D47-H47) -> 38282233 | D47: =E47+F47+G47 -> 18349421 | E47: ='入金明細 '!D46 -> 0 | F47: ='入金明細 '!M46 -> 0 | G47: ='入金明細 '!T46 -> 18349421 | H47: =I47+J47+K47 -> 0 | I47: ='出金明細 '!D46 -> 0 | J47: ='出金明細 '!M46 -> 0 | K47: ='出金明細 '!AD46 -> 0
B48: 45120 | C48: =SUM(C47+D48-H48) -> 38282233 | D48: =E48+F48+G48 -> 0 | E48: ='入金明細 '!D47 -> 0 | F48: ='入金明細 '!M47 -> 0 | G48: ='入金明細 '!T47 -> 0 | H48: =I48+J48+K48 -> 0 | I48: ='出金明細 '!D47 -> 0 | J48: ='出金明細 '!M47 -> 0 | K48: ='出金明細 '!AD47 -> 0
... B66: 45138 | C66: =SUM(C65+D66-H66) -> 29251272 | D66: =E66+F66+G66 -> 73113464 | E66: ='入金明細 '!D65 -> 50000000 | F66: ='入金明細 '!M65 -> 0 | G66: ='入金明細 '!T65 -> 23113464 | H66: =I66+J66+K66 -> 65457689 | I66: ='出金明細 '!D65 -> 55379383 | J66: ='出金明細 '!M65 -> 8506826 | K66: ='出金明細 '!AD65 -> 1571480
B67: 7月合計 | C67: =SUM(D67-H67) -> 16387317 | D67: =SUM(D36:D66) -> 174311873 | E67: =SUM(E36:E66) -> 54844200 | F67: =SUM(F36:F66) -> 2269699 | G67: =SUM(G36:G66) -> 117197974 | H67: =SUM(H36:H66) -> 157924556 | I67: =SUM(I36:I66) -> 81391853 | J67: =SUM(J36:J66) -> 64406112 | K67: =SUM(K36:K66) -> 12126591
B68: 累計 | C68: =SUM(D68-H68) -> 5479201 | D68: =D35+D67 -> 292388694 | E68: =E35+E67 -> 128318238 | F68: =F35+F67 -> 5079181 | G68: =G35+G67 -> 158991275 | H68: =H35+H67 -> 286909493 | I68: =I35+I67 -> 144668411 | J68: =J35+J67 -> 122318174 | K68: =K35+K67 -> 19922908
B69: 45139 | C69: =SUM(C66+D69-H69) -> 29504422 | D69: =E69+F69+G69 -> 269065 | E69: ='入金明細 '!D68 -> 0 | F69: ='入金明細 '!M68 | G69: ='入金明細 '!T68 -> 269065 | H69: =I69+J69+K69 -> 15915 | I69: ='出金明細 '!D68 -> 0 | J69: ='出金明細 '!M68 -> 0 | K69: ='出金明細 '!AD68 -> 15915
B70: 45140 | C70: =SUM(C69+D70-H70) -> 29459388 | D70: =E70+F70+G70 -> 0 | E70: ='入金明細 '!D69 -> 0 | F70: ='入金明細 '!M69 | G70: ='入金明細 '!T69 -> 0 | H70: =I70+J70+K70 -> 45034 | I70: ='出金明細 '!D69 -> 0 | J70: ='出金明細 '!M69 -> 0 | K70: ='出金明細 '!AD69 -> 45034
B71: 45141 | C71: =SUM(C70+D71-H71) -> 29459388 | D71: =E71+F71+G71 -> 0 | E71: ='入金明細 '!D70 -> 0 | F71: ='入金明細 '!M70 | G71: ='入金明細 '!T70 -> 0 | H71: =I71+J71+K71 -> 0 | I71: ='出金明細 '!D70 -> 0 | J71: ='出金明細 '!M70 -> 0 | K71: ='出金明細 '!AD70 -> 0
B72: 45142 | C72: =SUM(C71+D72-H72) -> 29459388 | D72: =E72+F72+G72 -> 0 | E72: ='入金明細 '!D71 -> 0 | F72: ='入金明細 '!M71 | G72: ='入金明細 '!T71 -> 0 | H72: =I72+J72+K72 -> 0 | I72: ='出金明細 '!D71 -> 0 | J72: ='出金明細 '!M71 -> 0 | K72: ='出金明細 '!AD71 -> 0
B73: 45143 | C73: =SUM(C72+D73-H73) -> 28703141 | D73: =E73+F73+G73 -> 42837 | E73: ='入金明細 '!D72 -> 0 | F73: ='入金明細 '!M72 -> 0 | G73: ='入金明細 '!T72 -> 42837 | H73: =I73+J73+K73 -> 799084 | I73: ='出金明細 '!D72 -> 0 | J73: ='出金明細 '!M72 -> 0 | K73: ='出金明細 '!AD72 -> 799084
B74: 45144 | C74: =SUM(C73+D74-H74) -> 28640566 | D74: =E74+F74+G74 -> 55000 | E74: ='入金明細 '!D73 -> 0 | F74: ='入金明細 '!M73 -> 0 | G74: ='入金明細 '!T73 -> 55000 | H74: =I74+J74+K74 -> 117575 | I74: ='出金明細 '!D73 -> 0 | J74: ='出金明細 '!M73 -> 0 | K74: ='出金明細 '!AD73 -> 117575
B75: 45145 | C75: =SUM(C74+D75-H75) -> 28639356 | D75: =E75+F75+G75 -> 0 | E75: ='入金明細 '!D74 -> 0 | F75: ='入金明細 '!M74 -> 0 | G75: ='入金明細 '!T74 -> 0 | H75: =I75+J75+K75 -> 1210 | I75: ='出金明細 '!D74 -> 1210 | J75: ='出金明細 '!M74 -> 0 | K75: ='出金明細 '!AD74 -> 0
B76: 45146 | C76: =SUM(C75+D76-H76) -> 28639356 | D76: =E76+F76+G76 -> 0 | E76: ='入金明細 '!D75 -> 0 | F76: ='入金明細 '!M75 -> 0 | G76: ='入金明細 '!T75 -> 0 | H76: =I76+J76+K76 -> 0 | I76: ='出金明細 '!D75 -> 0 | J76: ='出金明細 '!M75 -> 0 | K76: ='出金明細 '!AD75 -> 0
B77: 45147 | C77: =SUM(C76+D77-H77) -> 28604419 | D77: =E77+F77+G77 -> 146768 | E77: ='入金明細 '!D76 -> 0 | F77: ='入金明細 '!M76 -> 0 | G77: ='入金明細 '!T76 -> 146768 | H77: =I77+J77+K77 -> 181705 | I77: ='出金明細 '!D76 -> 110 | J77: ='出金明細 '!M76 -> 0 | K77: ='出金明細 '!AD76 -> 181595
B78: 45148 | C78: =SUM(C77+D78-H78) -> 28604419 | D78: =E78+F78+G78 -> 0 | E78: ='入金明細 '!D77 -> 0 | F78: ='入金明細 '!M77 -> 0 | G78: ='入金明細 '!T77 -> 0 | H78: =I78+J78+K78 -> 0 | I78: ='出金明細 '!D77 -> 0 | J78: ='出金明細 '!M77 -> 0 | K78: ='出金明細 '!AD77 -> 0
B79: 45149 | C79: =SUM(C78+D79-H79) -> 28303979 | D79: =E79+F79+G79 -> 0 | E79: ='入金明細 '!D78 -> 0 | F79: ='入金明細 '!M78 -> 0 | G79: ='入金明細 '!T78 -> 0 | H79: =I79+J79+K79 -> 300440 | I79: ='出金明細 '!D78 -> 300440 | J79: ='出金明細 '!M78 -> 0 | K79: ='出金明細 '!AD78 -> 0
B80: 45150 | C80: =SUM(C79+D80-H80) -> 28303979 | D80: =E80+F80+G80 -> 0 | E80: ='入金明細 '!D79 -> 0 | F80: ='入金明細 '!M79 -> 0 | G80: ='入金明細 '!T79 -> 0 | H80: =I80+J80+K80 -> 0 | I80: ='出金明細 '!D79 -> 0 | J80: ='出金明細 '!M79 -> 0 | K80: ='出金明細 '!AD79 -> 0
B81: 45151 | C81: =SUM(C80+D81-H81) -> 24533958 | D81: =E81+F81+G81 -> 0 | E81: ='入金明細 '!D80 -> 0 | F81: ='入金明細 '!M80 -> 0 | G81: ='入金明細 '!T80 -> 0 | H81: =I81+J81+K81 -> 3770021 | I81: ='出金明細 '!D80 -> 29777 | J81: ='出金明細 '!M80 -> 351600 | K81: ='出金明細 '!AD80 -> 3388644
... B99: 45169 | C99: =SUM(C98+D99-H99) -> 27094367 | D99: =E99+F99+G99 -> 0 | E99: ='入金明細 '!D98 -> 0 | F99: ='入金明細 '!M98 -> 0 | G99: ='入金明細 '!T98 -> 0 | H99: =I99+J99+K99 -> 0 | I99: ='出金明細 '!D98 -> 0 | J99: ='出金明細 '!M98 -> 0 | K99: ='出金明細 '!AD98 -> 0
B100: 8月合計 | C100: =SUM(D100-H100) -> -2156905 | D100: =SUM(D69:D99) -> 26644509 | E100: =SUM(E69:E99) -> 14841099 | F100: =SUM(F69:F99) -> 229328 | G100: =SUM(G69:G99) -> 11574082 | H100: =SUM(H69:H99) -> 28801414 | I100: =SUM(I69:I99) -> 15697495 | J100: =SUM(J69:J99) -> 1601742 | K100: =SUM(K69:K99) -> 11502177
B101: 累計 | C101: =SUM(D101-H101) -> 3322296 | D101: =D68+D100 -> 319033203 | E101: =E68+E100 -> 143159337 | F101: =F68+F100 -> 5308509 | G101: =G68+G100 -> 170565357 | H101: =H68+H100 -> 315710907 | I101: =I68+I100 -> 160365906 | J101: =J68+J100 -> 123919916 | K101: =K68+K100 -> 31425085
B102: 44440 | C102: =SUM(C99+D102-H102) -> 27094367 | D102: =E102+F102+G102 -> 0 | E102: ='入金明細 '!D101 -> 0 | F102: ='入金明細 '!M101 -> 0 | G102: ='入金明細 '!T101 -> 0 | H102: =I102+J102+K102 -> 0 | I102: ='出金明細 '!D101 -> 0 | J102: ='出金明細 '!M101 -> 0 | K102: ='出金明細 '!AD101 -> 0
B103: 44441 | C103: =SUM(C102+D103-H103) -> 19931055 | D103: =E103+F103+G103 -> 1032287 | E103: ='入金明細 '!D102 -> 0 | F103: ='入金明細 '!M102 -> 932287 | G103: ='入金明細 '!T102 -> 100000 | H103: =I103+J103+K103 -> 8195599 | I103: ='出金明細 '!D102 -> 4823596 | J103: ='出金明細 '!M102 -> 1371695 | K103: ='出金明細 '!AD102 -> 2000308
B104: 44442 | C104: =SUM(C103+D104-H104) -> 39835151 | D104: =E104+F104+G104 -> 20000000 | E104: ='入金明細 '!D103 -> 0 | F104: ='入金明細 '!M103 -> 0 | G104: ='入金明細 '!T103 -> 20000000 | H104: =I104+J104+K104 -> 95904 | I104: ='出金明細 '!D103 -> 0 | J104: ='出金明細 '!M103 -> 0 | K104: ='出金明細 '!AD103 -> 95904
B105: 44443 | C105: =SUM(C104+D105-H105) -> 39856151 | D105: =E105+F105+G105 -> 176100 | E105: ='入金明細 '!D104 -> 0 | F105: ='入金明細 '!M104 -> 87000 | G105: ='入金明細 '!T104 -> 89100 | H105: =I105+J105+K105 -> 155100 | I105: ='出金明細 '!D104 -> 0 | J105: ='出金明細 '!M104 -> 0 | K105: ='出金明細 '!AD104 -> 155100
B106: 44444 | C106: =SUM(C105+D106-H106) -> 43129403 | D106: =E106+F106+G106 -> 33207345 | E106: ='入金明細 '!D105 -> 0 | F106: ='入金明細 '!M105 -> 75075 | G106: ='入金明細 '!T105 -> 33132270 | H106: =I106+J106+K106 -> 29934093 | I106: ='出金明細 '!D105 -> 22000 | J106: ='出金明細 '!M105 -> 29880373 | K106: ='出金明細 '!AD105 -> 31720
B107: 44445 | C107: =SUM(C106+D107-H107) -> 22491565 | D107: =E107+F107+G107 -> 97837 | E107: ='入金明細 '!D106 -> 0 | F107: ='入金明細 '!M106 -> 0 | G107: ='入金明細 '!T106 -> 97837 | H107: =I107+J107+K107 -> 20735675 | I107: ='出金明細 '!D106 -> 0 | J107: ='出金明細 '!M106 -> 0 | K107: ='出金明細 '!AD106 -> 20735675
B108: 44446 | C108: =SUM(C107+D108-H108) -> 22491565 | D108: =E108+F108+G108 -> 0 | E108: ='入金明細 '!D107 -> 0 | F108: ='入金明細 '!M107 -> 0 | G108: ='入金明細 '!T107 -> 0 | H108: =I108+J108+K108 -> 0 | I108: ='出金明細 '!D107 -> 0 | J108: ='出金明細 '!M107 -> 0 | K108: ='出金明細 '!AD107 -> 0
B109: 44447 | C109: =SUM(C108+D109-H109) -> 22491565 | D109: =E109+F109+G109 -> 0 | E109: ='入金明細 '!D108 -> 0 | F109: ='入金明細 '!M108 -> 0 | G109: ='入金明細 '!T108 -> 0 | H109: =I109+J109+K109 -> 0 | I109: ='出金明細 '!D108 -> 0 | J109: ='出金明細 '!M108 -> 0 | K109: ='出金明細 '!AD108 -> 0
B110: 44448 | C110: =SUM(C109+D110-H110) -> 23181456 | D110: =E110+F110+G110 -> 691431 | E110: ='入金明細 '!D109 -> 1591 | F110: ='入金明細 '!M109 -> 525000 | G110: ='入金明細 '!T109 -> 164840 | H110: =I110+J110+K110 -> 1540 | I110: ='出金明細 '!D109 -> 1540 | J110: ='出金明細 '!M109 -> 0 | K110: ='出金明細 '!AD109 -> 0
B111: 44449 | C111: =SUM(C110+D111-H111) -> 13965072 | D111: =E111+F111+G111 -> 224655 | E111: ='入金明細 '!D110 -> 0 | F111: ='入金明細 '!M110 -> 0 | G111: ='入金明細 '!T110 -> 224655 | H111: =I111+J111+K111 -> 9441039 | I111: ='出金明細 '!D110 -> 21164 | J111: ='出金明細 '!M110 -> 6140351 | K111: ='出金明細 '!AD110 -> 3279524
B112: 44450 | C112: =SUM(C111+D112-H112) -> 13965072 | D112: =E112+F112+G112 -> 0 | E112: ='入金明細 '!D111 -> 0 | F112: ='入金明細 '!M111 -> 0 | G112: ='入金明細 '!T111 -> 0 | H112: =I112+J112+K112 -> 0 | I112: ='出金明細 '!D111 -> 0 | J112: ='出金明細 '!M111 -> 0 | K112: ='出金明細 '!AD111 -> 0
B113: 44451 | C113: =SUM(C112+D113-H113) -> 15088637 | D113: =E113+F113+G113 -> 3576960 | E113: ='入金明細 '!D112 -> 0 | F113: ='入金明細 '!M112 -> 0 | G113: ='入金明細 '!T112 -> 3576960 | H113: =I113+J113+K113 -> 2453395 | I113: ='出金明細 '!D112 -> 0 | J113: ='出金明細 '!M112 -> 2411770 | K113: ='出金明細 '!AD112 -> 41625
B114: 44452 | C114: =SUM(C113+D114-H114) -> 15084727 | D114: =E114+F114+G114 -> 0 | E114: ='入金明細 '!D113 -> 0 | F114: ='入金明細 '!M113 -> 0 | G114: ='入金明細 '!T113 -> 0 | H114: =I114+J114+K114 -> 3910 | I114: ='出金明細 '!D113 -> 0 | J114: ='出金明細 '!M113 -> 0 | K114: ='出金明細 '!AD113 -> 3910
... B131: 44469 | C131: =SUM(C130+D131-H131) -> 4898517 | D131: =E131+F131+G131 -> 33505166 | E131: ='入金明細 '!D130 -> 30000000 | F131: ='入金明細 '!M130 -> 0 | G131: ='入金明細 '!T130 -> 3505166 | H131: =I131+J131+K131 -> 37932184 | I131: ='出金明細 '!D130 -> 34586673 | J131: ='出金明細 '!M130 -> 1461321 | K131: ='出金明細 '!AD130 -> 1884190
B132: 9月合計 | C132: =SUM(D132-H132) -> -22195850 | D132: =SUM(D102:D131) -> 136426937 | E132: =SUM(E102:E131) -> 68354742 | F132: =SUM(F102:F131) -> 2905693 | G132: =SUM(G102:G131) -> 65166502 | H132: =SUM(H102:H131) -> 158622787 | I132: =SUM(I102:I131) -> 60362053 | J132: =SUM(J102:J131) -> 68536015 | K132: =SUM(K102:K131) -> 29724719
B133: 累計 | C133: =SUM(D133-H133) -> -18873554 | D133: =D101+D132 -> 455460140 | E133: =E101+E132 -> 211514079 | F133: =F101+F132 -> 8214202 | G133: =G101+G132 -> 235731859 | H133: =H101+H132 -> 474333694 | I133: =I101+I132 -> 220727959 | J133: =J101+J132 -> 192455931 | K133: =K101+K132 -> 61149804
B134: 44470 | C134: =SUM(C131+D134-H134) -> 4811592 | D134: =E134+F134+G134 -> 0 | E134: ='入金明細 '!D133 -> 0 | F134: ='入金明細 '!M133 | G134: ='入金明細 '!T133 -> 0 | H134: =I134+J134+K134 -> 86925 | I134: ='出金明細 '!D133 -> 0 | J134: ='出金明細 '!M133 -> 0 | K134: ='出金明細 '!AD133 -> 86925
B135: 44471 | C135: =SUM(C134+D135-H135) -> 4609644 | D135: =E135+F135+G135 -> 0 | E135: ='入金明細 '!D134 -> 0 | F135: ='入金明細 '!M134 | G135: ='入金明細 '!T134 -> 0 | H135: =I135+J135+K135 -> 201948 | J135: ='出金明細 '!M134 -> 0 | K135: ='出金明細 '!AD134 -> 201948
B136: 44472 | C136: =SUM(C135+D136-H136) -> 6411382 | D136: =E136+F136+G136 -> 1833568 | E136: ='入金明細 '!D135 -> 0 | F136: ='入金明細 '!M135 -> 1833568 | G136: ='入金明細 '!T135 -> 0 | H136: =I136+J136+K136 -> 31830 | I136: ='出金明細 '!D135 -> 0 | J136: ='出金明細 '!M135 -> 0 | K136: ='出金明細 '!AD135 -> 31830
B137: 44473 | C137: =SUM(C136+D137-H137) -> 6103536 | D137: =E137+F137+G137 -> 267030 | E137: ='入金明細 '!D136 -> 0 | F137: ='入金明細 '!M136 -> 0 | G137: ='入金明細 '!T136 -> 267030 | H137: =I137+J137+K137 -> 574876 | I137: ='出金明細 '!D136 -> 200000 | J137: ='出金明細 '!M136 -> 0 | K137: ='出金明細 '!AD136 -> 374876
B138: 44474 | C138: =SUM(C137+D138-H138) -> 6103536 | D138: =E138+F138+G138 -> 0 | E138: ='入金明細 '!D137 -> 0 | F138: ='入金明細 '!M137 -> 0 | G138: ='入金明細 '!T137 -> 0 | H138: =I138+J138+K138 -> 0 | I138: ='出金明細 '!D137 -> 0 | J138: ='出金明細 '!M137 -> 0 | K138: ='出金明細 '!AD137 -> 0
B139: 44475 | C139: =SUM(C138+D139-H139) -> 5903316 | D139: =E139+F139+G139 -> 0 | E139: ='入金明細 '!D138 -> 0 | F139: ='入金明細 '!M138 -> 0 | G139: ='入金明細 '!T138 -> 0 | H139: =I139+J139+K139 -> 200220 | I139: ='出金明細 '!D138 -> 200220 | J139: ='出金明細 '!M138 -> 0 | K139: ='出金明細 '!AD138 -> 0
B140: 44476 | C140: =SUM(C139+D140-H140) -> 4905106 | D140: =E140+F140+G140 -> 0 | E140: ='入金明細 '!D139 -> 0 | F140: ='入金明細 '!M139 -> 0 | G140: ='入金明細 '!T139 -> 0 | H140: =I140+J140+K140 -> 998210 | I140: ='出金明細 '!D139 -> 0 | J140: ='出金明細 '!M139 -> 997000 | K140: ='出金明細 '!AD139 -> 1210
B141: 44477 | C141: =SUM(C140+D141-H141) -> 4905106 | D141: =E141+F141+G141 -> 0 | E141: ='入金明細 '!D140 -> 0 | F141: ='入金明細 '!M140 -> 0 | G141: ='入金明細 '!T140 -> 0 | H141: =I141+J141+K141 -> 0 | I141: ='出金明細 '!D140 -> 0 | J141: ='出金明細 '!M140 -> 0 | K141: ='出金明細 '!AD140 -> 0
B142: 44478 | C142: =SUM(C141+D142-H142) -> 4947943 | D142: =E142+F142+G142 -> 42837 | E142: ='入金明細 '!D141 -> 0 | F142: ='入金明細 '!M141 -> 0 | G142: ='入金明細 '!T141 -> 42837 | H142: =I142+J142+K142 -> 0 | I142: ='出金明細 '!D141 -> 0 | J142: ='出金明細 '!M141 -> 0 | K142: ='出金明細 '!AD141 -> 0
B143: 44479 | C143: =SUM(C142+D143-H143) -> 21086360 | D143: =E143+F143+G143 -> 19999450 | E143: ='入金明細 '!D142 -> 0 | F143: ='入金明細 '!M142 -> 0 | G143: ='入金明細 '!T142 -> 19999450 | H143: =I143+J143+K143 -> 3861033 | I143: ='出金明細 '!D142 -> 0 | J143: ='出金明細 '!M142 -> 0 | K143: ='出金明細 '!AD142 -> 3861033
B144: 44480 | C144: =SUM(C143+D144-H144) -> 21252462 | D144: =E144+F144+G144 -> 2000000 | E144: ='入金明細 '!D143 -> 2000000 | F144: ='入金明細 '!M143 -> 0 | G144: ='入金明細 '!T143 -> 0 | H144: =I144+J144+K144 -> 1833898 | I144: ='出金明細 '!D143 -> 330 | J144: ='出金明細 '!M143 -> 0 | K144: ='出金明細 '!AD143 -> 1833568
B145: 44481 | C145: =SUM(C144+D145-H145) -> 21318242 | D145: =E145+F145+G145 -> 65780 | E145: ='入金明細 '!D144 -> 0 | F145: ='入金明細 '!M144 -> 0 | G145: ='入金明細 '!T144 -> 65780 | H145: =I145+J145+K145 -> 0 | I145: ='出金明細 '!D144 -> 0 | J145: ='出金明細 '!M144 -> 0 | K145: ='出金明細 '!AD144 -> 0
B146: 44482 | C146: =SUM(C145+D146-H146) -> 21318242 | D146: =E146+F146+G146 -> 0 | E146: ='入金明細 '!D145 -> 0 | F146: ='入金明細 '!M145 -> 0 | G146: ='入金明細 '!T145 -> 0 | H146: =I146+J146+K146 -> 0 | I146: ='出金明細 '!D145 -> 0 | J146: ='出金明細 '!M145 -> 0 | K146: ='出金明細 '!AD145 -> 0
B147: 44483 | C147: =SUM(C146+D147-H147) -> 21318242 | D147: =E147+F147+G147 -> 0 | E147: ='入金明細 '!D146 -> 0 | F147: ='入金明細 '!M146 -> 0 | G147: ='入金明細 '!T146 -> 0 | H147: =I147+J147+K147 -> 0 | I147: ='出金明細 '!D146 -> 0 | J147: ='出金明細 '!M146 -> 0 | K147: ='出金明細 '!AD146 -> 0
... B164: 44500 | C164: =SUM(C163+D164-H164) -> 21505321 | D164: =E164+F164+G164 -> 9043667 | E164: ='入金明細 '!D163 -> 0 | F164: ='入金明細 '!M163 -> 15000 | G164: ='入金明細 '!T163 -> 9028667 | H164: =I164+J164+K164 -> 4426519 | I164: ='出金明細 '!D163 -> 1173651 | J164: ='出金明細 '!M163 -> 790118 | K164: ='出金明細 '!AD163 -> 2462750
B165: 10月合計 | C165: =SUM(D165-H165) -> 16606804 | D165: =SUM(D134:D164) -> 60929035 | H165: =SUM(H134:H164) -> 44322231
B166: 累計 | C166: =SUM(D166-H166) -> -2266750 | D166: =D133+D165 -> 516389175 | H166: =H133+H165 -> 518655925
B167: 44501 | C167: =SUM(C164+D167-H167) -> 21504991 | D167: =E167+F167+G167 -> 0 | E167: ='入金明細 '!D165 -> 0 | F167: ='入金明細 '!M165 -> 0 | G167: ='入金明細 '!T165 -> 0 | H167: =I167+J167+K167 -> 330 | I167: ='出金明細 '!D165 -> 330 | J167: ='出金明細 '!M165 -> 0 | K167: ='出金明細 '!AD165 -> 0
B168: 44502 | C168: =SUM(C167+D168-H168) -> 21588316 | D168: =E168+F168+G168 -> 83325 | E168: ='入金明細 '!D166 -> 0 | F168: ='入金明細 '!M166 -> 0 | G168: ='入金明細 '!T166 -> 83325 | H168: =I168+J168+K168 -> 0 | I168: ='出金明細 '!D166 -> 0 | J168: ='出金明細 '!M166 -> 0 | K168: ='出金明細 '!AD166 -> 0
B169: 44503 | C169: =SUM(C168+D169-H169) -> 21588316 | D169: =E169+F169+G169 -> 0 | E169: ='入金明細 '!D167 -> 0 | F169: ='入金明細 '!M167 -> 0 | G169: ='入金明細 '!T167 -> 0 | H169: =I169+J169+K169 -> 0 | I169: ='出金明細 '!D167 -> 0 | J169: ='出金明細 '!M167 -> 0 | K169: ='出金明細 '!AD167 -> 0
B170: 44504 | C170: =SUM(C169+D170-H170) -> 21588316 | D170: =E170+F170+G170 -> 0 | E170: ='入金明細 '!D168 -> 0 | F170: ='入金明細 '!M168 -> 0 | G170: ='入金明細 '!T168 -> 0 | H170: =I170+J170+K170 -> 0 | I170: ='出金明細 '!D168 -> 0 | J170: ='出金明細 '!M168 -> 0 | K170: ='出金明細 '!AD168 -> 0
B171: 44505 | C171: =SUM(C170+D171-H171) -> 14767458 | D171: =E171+F171+G171 -> 1976828 | E171: ='入金明細 '!D169 -> 1047968 | F171: ='入金明細 '!M169 -> 100000 | G171: ='入金明細 '!T169 -> 828860 | H171: =I171+J171+K171 -> 8797686 | I171: ='出金明細 '!D169 -> 8250000 | J171: ='出金明細 '!M169 -> 0 | K171: ='出金明細 '!AD169 -> 547686
B172: 44506 | C172: =SUM(C171+D172-H172) -> 14767458 | D172: =E172+F172+G172 -> 0 | E172: ='入金明細 '!D170 -> 0 | F172: ='入金明細 '!M170 -> 0 | G172: ='入金明細 '!T170 -> 0 | H172: =I172+J172+K172 -> 0 | I172: ='出金明細 '!D170 -> 0 | J172: ='出金明細 '!M170 -> 0 | K172: ='出金明細 '!AD170 -> 0
B173: 44507 | C173: =SUM(C172+D173-H173) -> 14718503 | D173: =E173+F173+G173 -> 0 | E173: ='入金明細 '!D171 -> 0 | F173: ='入金明細 '!M171 -> 0 | G173: ='入金明細 '!T171 -> 0 | H173: =I173+J173+K173 -> 48955 | I173: ='出金明細 '!D171 -> 1210 | J173: ='出金明細 '!M171 -> 0 | K173: ='出金明細 '!AD171 -> 47745
B174: 44508 | C174: =SUM(C173+D174-H174) -> 14754033 | D174: =E174+F174+G174 -> 36080 | E174: ='入金明細 '!D172 -> 0 | F174: ='入金明細 '!M172 -> 0 | G174: ='入金明細 '!T172 -> 36080 | H174: =I174+J174+K174 -> 550 | I174: ='出金明細 '!D172 -> 550 | J174: ='出金明細 '!M172 -> 0 | K174: ='出金明細 '!AD172 -> 0
B175: 44509 | C175: =SUM(C174+D175-H175) -> 14754033 | D175: =E175+F175+G175 -> 0 | E175: ='入金明細 '!D173 -> 0 | F175: ='入金明細 '!M173 -> 0 | G175: ='入金明細 '!T173 -> 0 | H175: =I175+J175+K175 -> 0 | I175: ='出金明細 '!D173 -> 0 | J175: ='出金明細 '!M173 -> 0 | K175: ='出金明細 '!AD173 -> 0
B176: 44510 | C176: =SUM(C175+D176-H176) -> 14817833 | D176: =E176+F176+G176 -> 63800 | E176: ='入金明細 '!D174 -> 0 | F176: ='入金明細 '!M174 -> 0 | G176: ='入金明細 '!T174 -> 63800 | H176: =I176+J176+K176 -> 0 | I176: ='出金明細 '!D174 -> 0 | J176: ='出金明細 '!M174 -> 0 | K176: ='出金明細 '!AD174 -> 0
B177: 44511 | C177: =SUM(C176+D177-H177) -> 11772407 | D177: =E177+F177+G177 -> 457537 | E177: ='入金明細 '!D175 -> 0 | F177: ='入金明細 '!M175 -> 0 | G177: ='入金明細 '!T175 -> 457537 | H177: =I177+J177+K177 -> 3502963 | I177: ='出金明細 '!D175 -> 24695 | J177: ='出金明細 '!M175 -> 0 | K177: ='出金明細 '!AD175 -> 3478268
B178: 44512 | C178: =SUM(C177+D178-H178) -> 11572407 | D178: =E178+F178+G178 -> 0 | E178: ='入金明細 '!D176 -> 0 | F178: ='入金明細 '!M176 -> 0 | G178: ='入金明細 '!T176 -> 0 | H178: =I178+J178+K178 -> 200000 | I178: ='出金明細 '!D176 -> 0 | J178: ='出金明細 '!M176 -> 0 | K178: ='出金明細 '!AD176 -> 200000
B179: 44513 | C179: =SUM(C178+D179-H179) -> 11622407 | D179: =E179+F179+G179 -> 50000 | E179: ='入金明細 '!D177 -> 0 | F179: ='入金明細 '!M177 -> 0 | G179: ='入金明細 '!T177 -> 50000 | H179: =I179+J179+K179 -> 0 | I179: ='出金明細 '!D177 -> 0 | J179: ='出金明細 '!M177 -> 0 | K179: ='出金明細 '!AD177 -> 0
... B196: 44530 | C196: =SUM(C195+D196-H196) -> 25174574 | D196: =E196+F196+G196 -> 17600 | E196: ='入金明細 '!D194 -> 0 | F196: ='入金明細 '!M194 -> 0 | G196: ='入金明細 '!T194 -> 17600 | H196: =I196+J196+K196 -> 0 | I196: ='出金明細 '!D194 -> 0 | J196: ='出金明細 '!M194 -> 0 | K196: ='出金明細 '!AD194 -> 0
B197: 1１月合計 | C197: =SUM(D197-H197) -> 3669253 | D197: =SUM(D167:D196) -> 26160887 | H197: =SUM(H167:H196) -> 22491634
B198: 累計 | C198: =SUM(D198-H198) -> 1402503 | D198: =D166+D197 -> 542550062 | H198: =H166+H197 -> 541147559
...

Sheet 入金明細 
C1: ２０２4年６月‐２０２5年５月入金
C2: 入金日次 | D2: 金融小計 | E2: 金融機関関連 | M2: 保険小計 | N2: 保険関連 | T2: お客様小計 | U2: お客様関連
B3: 44348 | C3: =D3+M3+T3 -> 0 | D3: =F3+H3+J3+L3 -> 0 | M3: =O3 | T3: =V3+X3+Z3+AB3+AD3+AF3+AH3+AJ3+AV3 -> 0
B4: 44349 | C4: =D4+M4+T4 -> 0 | D4: =F4+H4+J4+L4 -> 0 | M4: =O4 | T4: =V4+X4+Z4+AB4+AD4+AF4+AH4+AJ4+AV4 -> 0
B5: 45446 | C5: =D5+M5+T5 -> 258940 | D5: =F5+H5+J5+L5 -> 0 | M5: =O5 | T5: =V5+X5+Z5+AB5+AD5+AF5+AH5+AJ5+AV5 -> 258940 | U5: 今川建築設計様 | V5: 258940
B6: 44351 | C6: =D6+M6+T6 -> 364708 | D6: =F6+H6+J6+L6 -> 0 | M6: =O6 | T6: =V6+X6+Z6+AB6+AD6+AF6+AH6+AJ6+AV6 -> 364708 | U6: 小林歯科医院様 | V6: 262575 | W6: 出雲ﾓｰﾀｰ商会様 | X6: 102133
B7: 44352 | C7: =D7+M7+T7 -> 5234760 | D7: =F7+H7+J7+L7 -> 0 | M7: =O7+Q7 -> 0 | T7: =V7+X7+Z7+AB7+AD7+AF7+AH7+AJ7+AV7 -> 5234760 | U7: USS名古屋ﾍﾞﾝﾃGｸﾗｽ | V7: 4943400 | W7: ｻﾝｴｽﾎｰﾙﾃﾞｨﾝｸﾞｽ様 | X7: 291360
B8: 44353 | C8: =D8+M8+T8 -> 0 | D8: =F8+H8+J8+L8 -> 0 | M8: =O8+Q8 -> 0 | T8: =V8+X8+Z8+AB8+AD8+AF8+AH8+AJ8+AV8 -> 0
B9: 44354 | C9: =D9+M9+T9 -> 43848730 | D9: =F9+H9+J9+L9 -> 43463220 | E9: 笠信ﾌｪﾗｰﾘ・ﾎﾟﾙｼｪ残債支払いの為 | F9: 43434453 | G9: 笠信 | H9: 5178 | I9: 笠信 | J9: 23589 | M9: =O9+Q9 -> 150000 | N9: AIG損害保険 | O9: 150000 | T9: =V9+X9+Z9+AB9+AD9+AF9+AH9+AJ9+AV9 -> 235510 | U9: ﾌﾟﾚﾐｱﾜﾗﾝﾃｨｻｰﾋﾞｽ様 | V9: 148610 | W9: ｺﾊﾞﾀｹｺｳｻﾝ様 | X9: 31900 | Y9: 吉元ﾄﾓﾋﾛ様 | Z9: 55000
B10: 44355 | C10: =D10+M10+T10 -> 0 | D10: =F10+H10+J10+L10 -> 0 | M10: =O10+Q10 -> 0 | T10: =V10+X10+Z10+AB10+AD10+AF10+AH10+AJ10+AV10 -> 0
B11: 44356 | C11: =D11+M11+T11 -> 0 | D11: =F11+H11+J11+L11 -> 0 | M11: =O11+Q11 -> 0 | T11: =V11+X11+Z11+AB11+AD11+AF11+AH11+AJ11+AV11 -> 0
B12: 44357 | C12: =D12+M12+T12 -> 82137 | D12: =F12+H12+J12+L12 -> 0 | M12: =O12+Q12 -> 25000 | N12: 東京海上 | O12: 25000 | T12: =V12+X12+Z12+AB12+AD12+AF12+AH12+AJ12+AV12 -> 57137 | U12: 森田和也様2024.9月まで | V12: 42837 | W12: ﾙｯｸ様 | X12: 14300
B13: 44358 | C13: =D13+M13+T13 -> 345009 | D13: =F13+H13+J13+L13 -> 0 | M13: =O13+Q13 -> 0 | T13: =V13+X13+Z13+AB13+AD13+AF13+AH13+AJ13+AV13 -> 345009 | U13: ｻｻﾀﾞﾋﾛｱｷ様 | V13: 345009
B14: 44359 | C14: =D14+M14+T14 -> 0 | D14: =F14+H14+J14+L14 -> 0 | M14: =O14+Q14 -> 0 | T14: =V14+X14+Z14+AB14+AD14+AF14+AH14+AJ14+AV14 -> 0
B15: 44360 | C15: =D15+M15+T15 -> 110000 | D15: =F15+H15+J15+L15 -> 0 | M15: =O15+Q15 -> 110000 | N15: 東海 | O15: 110000 | T15: =V15+X15+Z15+AB15+AD15+AF15+AH15+AJ15+AV15 -> 0
B16: 44361 | C16: =D16+M16+T16 -> 102790 | D16: =F16+H16+J16+L16 -> 0 | M16: =O16+Q16 -> 0 | T16: =V16+X16+Z16+AB16+AD16+AF16+AH16+AJ16+AV16 -> 102790 | U16: ｷﾑﾗﾕﾆﾃｨ様 | V16: 52190 | W16: 井上一成様 | X16: 50600
B17: 44362 | C17: =D17+M17+T17 -> 0 | D17: =F17+H17+J17+L17 -> 0 | M17: =O17+Q17 -> 0 | T17: =V17+X17+Z17+AB17+AD17+AF17+AH17+AJ17+AV17 -> 0
B18: 44363 | C18: =D18+M18+T18 -> 0 | D18: =F18+H18+J18+L18 -> 0 | M18: =O18+Q18 -> 0 | T18: =V18+X18+Z18+AB18+AD18+AF18+AH18+AJ18+AV18 -> 0
B19: 44364 | C19: =D19+M19+T19 -> 591838 | D19: =F19+H19+J19+L19 -> 0 | M19: =O19+Q19 -> 65118 | N19: 三井代理店手数料 | O19: 65118 | T19: =V19+X19+Z19+AB19+AD19+AF19+AH19+AJ19+AV19 -> 526720 | U19: 中銀ｶｰﾄﾞVISA | V19: 7241 | W19: 中銀ｶｰﾄﾞJCB | X19: 4257 | Y19: 平田紙管様 | Z19: 130200 | AA19: ｷｮｳｴｲ商事様 | AB19: 249832 | AC19: ｼﾞｭﾝｱｷﾔﾏｸﾘｴｲﾃｨﾌﾞ様 | AD19: 135190
B20: 44365 | C20: =D20+M20+T20 -> 200514 | D20: =F20+H20+J20+L20 -> 0 | M20: =O20+Q20 -> 200514 | N20: 東京海上代理店手数料 | O20: 200514 | T20: =V20+X20+Z20+AB20+AD20+AF20+AH20+AJ20+AV20 -> 0
B21: 44366 | C21: =D21+M21+T21 -> 6367 | D21: =F21+H21+J21+L21 -> 6367 | E21: 広信配当金 | F21: 1592 | G21: 笠信出資配当金 | H21: 4775 | M21: =O21+Q21 -> 0 | T21: =V21+X21+Z21+AB21+AD21+AF21+AH21+AJ21+AV21 -> 0
B22: 44367 | C22: =D22+M22+T22 -> 32351163 | D22: =F22+H22+J22+L22 -> 0 | M22: =O22+Q22 -> 0 | T22: =V22+X22+Z22+AB22+AD22+AF22+AH22+AJ22+AV22 -> 32351163 | U22: ｵﾘｺ勝栄建工様分ﾌｪﾗｰﾘ | V22: 32255148 | W22: ｵﾘｺ | X22: 74015 | Y22: 安保ﾏｻﾌﾐ様 | Z22: 22000
B23: 44368 | C23: =D23+M23+T23 -> 268256 | D23: =F23+H23+J23+L23 -> 0 | M23: =O23+Q23 -> 0 | T23: =V23+X23+Z23+AB23+AD23+AF23+AH23+AJ23+AV23 -> 268256 | U23: 藤田勲様ｷﾞﾌﾞﾘ車両代 | V23: 268256
B24: 44369 | C24: =D24+M24+T24 -> 0 | D24: =F24+H24+J24+L24 -> 0 | M24: =O24+Q24 -> 0 | T24: =V24+X24+Z24+AB24+AD24+AF24+AH24+AJ24+AV24 -> 0
B25: 44370 | C25: =D25+M25+T25 -> 0 | D25: =F25+H25+J25+L25 -> 0 | M25: =O25+Q25 -> 0 | T25: =V25+X25+Z25+AB25+AD25+AF25+AH25+AJ25+AV25 -> 0
B26: 44371 | C26: =D26+M26+T26 -> 353039 | D26: =F26+H26+J26+L26 -> 0 | M26: =O26+Q26 -> 0 | T26: =V26+X26+Z26+AB26+AD26+AF26+AH26+AJ26+AV26 -> 353039 | U26: USS名古屋ﾍﾞﾝﾃGｸﾗｽ自動車税返金 | V26: 8030 | W26: 佐々田ﾋﾛｱｷ様 | X26: 345009
B27: 44372 | C27: =D27+M27+T27 -> 4109 | D27: =F27+H27+J27+L27 -> 4109 | E27: 笠信支払利息返金 | F27: 4109 | M27: =O27+Q27 -> 0 | T27: =V27+X27+Z27+AB27+AD27+AF27+AH27+AJ27+AV27 -> 0
B28: 44373 | C28: =D28+M28+T28 -> 50450 | D28: =F28+H28+J28+L28 -> 0 | M28: =O28+Q28 -> 0 | T28: =V28+X28+Z28+AB28+AD28+AF28+AH28+AJ28+AV28 -> 50450 | U28: ﾅﾙﾈｯﾄｺﾐｭﾆｹｰｼｮﾝｽﾞ様 | V28: 50450
B29: 44374 | C29: =D29+M29+T29 -> 2259192 | D29: =F29+H29+J29+L29 -> 342 | E29: 笠信 | F29: 342 | M29: =O29+Q29 -> 2258850 | N29: 東海 | O29: 2258850 | T29: =V29+X29+Z29+AB29+AD29+AF29+AH29+AJ29+AV29 -> 0
B30: 44375 | C30: =D30+M30+T30 -> 31644819 | D30: =F30+H30+J30+L30 -> 30000000 | E30: もみじ短期 | F30: 30000000 | M30: =O30+Q30 -> 0 | T30: =V30+X30+Z30+AB30+AD30+AF30+AH30+AJ30+AV30 -> 1644819 | U30: NPO | V30: 907296 | W30: 中銀ｶｰﾄﾞJCB | X30: 20222 | Y30: ﾕﾅｲﾃｯﾄﾞｸﾛｰﾊﾞｰ様 | Z30: 134640 | AA30: 一心ｸﾞﾙｰﾌﾟ様 | AB30: 376411 | AC30: 今川建築設計様 | AD30: 206250
B31: 44376 | C31: =D31+M31+T31 -> 0 | D31: =F31+H31+J31+L31 -> 0 | M31: =O31+Q31 -> 0 | T31: =V31+X31+Z31+AB31+AD31+AF31+AH31+AJ31+AV31 -> 0
B32: 44377 | C32: =D32+M32+T32 -> 0 | D32: =F32+H32+J32+L32 -> 0 | M32: =O32+Q32 -> 0 | T32: =V32+X32+Z32+AB32+AD32+AF32+AH32+AJ32+AV32 -> 0
B33: ６月合計 | C33: =D33+M33+T33 -> 118076821 | D33: =SUM(D2:D32) -> 73474038 | M33: =SUM(M2:M32) -> 2809482 | T33: =SUM(T3:T32) -> 41793301
B34: 未確定 | C34: =D34+M34+T34 -> 0 | T34: =V34+X34+Z34+AB34+AD34+AF34+AH34+AJ34+AV34 -> 0
B35: 44378 | C35: =D35+M35+T35 -> 10787540 | D35: =F35+H35+J35+L35 -> 0 | M35: =O35+Q35 -> 0 | T35: =V35+X35+Z35+AB35+AD35+AF35+AH35+AJ35+AV35 -> 10787540 | U35: ｺﾝｸｴｽﾄ様経費 | V35: 3140808 | W35: ｺﾝｸｴｽﾄ様J&R | X35: 99006 | Y35: ｺﾝｸｴｽﾄ様ｱｳﾃﾞｨ広島分 | Z35: 9075 | AA35: ｺﾝｸｴｽﾄ様紹介料 | AB35: 3555851 | AC35: ｸﾞｰﾈｯﾄｴｸｽﾁｪﾝｼﾞ様ｲｳﾞｫｰｸﾞ | AD35: 3982800
B36: 45109 | C36: =D36+M36+T36 -> 0 | D36: =F36+H36+J36+L36 -> 0 | M36: =O36+Q36 -> 0 | T36: =V36+X36+Z36+AB36+AD36+AF36+AH36+AJ36+AV36 -> 0
B37: 45110 | C37: =D37+M37+T37 -> 0 | D37: =F37+H37+J37+L37 -> 0 | M37: =O37+Q37 -> 0 | T37: =V37+X37+Z37+AB37+AD37+AF37+AH37+AJ37+AV37 -> 0
B38: 45111 | C38: =D38+M38+T38 -> 0 | D38: =F38+H38+J38+L38 -> 0 | M38: =O38+Q38 -> 0 | T38: =V38+X38+Z38+AB38+AD38+AF38+AH38+AJ38+AV38 -> 0
B39: 45112 | C39: =D39+M39+T39 -> 42837 | D39: =F39+H39+J39+L39 -> 0 | M39: =O39+Q39 -> 0 | T39: =V39+X39+Z39+AB39+AD39+AF39+AH39+AJ39+AV39 -> 42837 | U39: 森田和也様2024.9月まで | V39: 42837
B40: 45113 | C40: =D40+M40+T40 -> 0 | D40: =F40+H40+J40+L40 -> 0 | M40: =O40+Q40 -> 0 | T40: =V40+X40+Z40+AB40+AD40+AF40+AH40+AJ40+AV40 -> 0
B41: 45114 | C41: =D41+M41+T41 -> 0 | D41: =F41+H41+J41+L41 -> 0 | M41: =O41+Q41 -> 0 | T41: =V41+X41+Z41+AB41+AD41+AF41+AH41+AJ41+AV41 -> 0
B42: 45115 | C42: =D42+M42+T42 -> 345960 | D42: =F42+H42+J42+L42 -> 0 | M42: =O42+Q42 -> 0 | T42: =V42+X42+Z42+AB42+AD42+AF42+AH42+AJ42+AV42 -> 345960 | U42: 皿海ﾓｰﾀｰｽ様 | V42: 36080 | W42: ｺﾝｸｴｽﾄ様 | X42: 154880 | Y42: 土肥良太郎様2025年2月まで | Z42: 100000 | AA42: 吉元様A３ | AB42: 55000
B43: 45116 | C43: =D43+M43+T43 -> 12448740 | D43: =F43+H43+J43+L43 -> 0 | M43: =O43+Q43+S43 -> 0 | T43: =V43+X43+Z43+AB43+AD43+AF43+AH43+AJ43+AV43 -> 12448740 | U43: ｸﾚｽﾄ不動産様 ﾍﾞﾝﾂ車両代 | V43: 12448740
B44: 45117 | C44: =D44+M44+T44 -> 5258343 | D44: =F44+H44+J44+L44 -> 0 | M44: =O44+Q44+S44 -> 17520 | N44: 東海間違いの返金 | O44: 17520 | T44: =V44+X44+Z44+AB44+AD44+AF44+AH44+AJ44+AV44 -> 5240823 | U44: ﾌﾟﾚﾐｱ谷口様ｷﾞﾌﾞﾘ車両代（中山雅裕様買取分） | V44: 4932863 | W44: 西日本自動車共済協同様 | X44: 150000 | Y44: 荒木ﾐﾂﾉﾘ様 | Z44: 157960
B45: 45118 | C45: =D45+M45+T45 -> 79008 | D45: =F45+H45+J45+L45 -> 0 | M45: =O45+Q45 -> 79008 | N45: 東海 | O45: 79008 | T45: =V45+X45+Z45+AB45+AD45+AF45+AH45+AJ45+AV45 -> 0
B46: 45119 | C46: =D46+M46+T46 -> 18349421 | D46: =F46+H46+J46+L46 -> 0 | M46: =O46+Q46 -> 0 | T46: =V46+X46+Z46+AB46+AD46+AF46+AH46+AJ46+AV46 -> 18349421 | U46: ｵﾘｺ合同会社Solel 松尾優子様ﾎﾟﾙｼｪ(ﾋﾞｯｸﾞﾊﾟｲﾝ様分23.212.120円 | V46: 18349421
B47: 45120 | C47: =D47+M47+T47 -> 0 | D47: =F47+H47+J47+L47 -> 0 | M47: =O47+Q47 -> 0 | T47: =V47+X47+Z47+AB47+AD47+AF47+AH47+AJ47+AV47 -> 0
B48: 45121 | C48: =D48+M48+T48 -> 0 | D48: =F48+H48+J48+L48 -> 0 | M48: =O48+Q48 -> 0 | T48: =V48+X48+Z48+AB48+AD48+AF48+AH48+AJ48+AV48 -> 0
B49: 45122 | C49: =D49+M49+T49 -> 262120 | D49: =F49+H49+J49+L49 -> 0 | M49: =O49+Q49 -> 262120 | N49: 7/16三井 | O49: 262120 | T49: =V49+X49+Z49+AB49+AD49+AF49+AH49+AJ49+AV49 -> 0
B50: 45123 | C50: =D50+M50+T50 -> 1157715 | D50: =F50+H50+J50+L50 -> 0 | M50: =O50+Q50+S50 -> 521751 | N50: 三井代理店手数料 | O50: 92136 | P50: 東海代理店手数料 | Q50: 219615 | R50: 三井住友海上 | S50: 210000 | T50: =V50+X50+Z50+AB50+AD50+AF50+AH50+AJ50+AV50 -> 635964 | U50: 中銀ｶｰﾄﾞJCB | V50: 196550 | W50: 中銀ｶｰﾄﾞVISA | X50: 186205 | Y50: ｷﾑﾗﾕﾆﾃｨ様 | Z50: 80442 | AA50: 三菱ｵｰﾄﾘｰｽ | AB50: 44503 | AC50: 中山ﾏｻﾋﾛ様 | AD50: 128264
B51: 45124 | C51: =D51+M51+T51 -> 0 | D51: =F51+H51+J51+L51 -> 0 | M51: =O51+Q51+S51 -> 0 | T51: =V51+X51+Z51+AB51+AD51+AF51+AH51+AJ51+AV51 -> 0
B52: 45125 | C52: =D52+M52+T52 -> 0 | D52: =F52+H52+J52+L52 -> 0 | M52: =O52+Q52+S52 -> 0 | T52: =V52+X52+Z52+AB52+AD52+AF52+AH52+AJ52+AV52 -> 0
B53: 45126 | C53: =D53+M53+T53 -> 11427597 | D53: =F53+H53+J53+L53 -> 0 | M53: =O53+Q53+S53 -> 0 | T53: =V53+X53+Z53+AB53+AD53+AF53+AH53+AJ53+AV53 -> 11427597 | U53: 松尾様（ｿﾚｲﾕ様）4.862.149円 | V53: 4863392 | W53: おもてちょう不動産様 | X53: 6564205
B54: 45127 | C54: =D54+M54+T54 -> 0 | D54: =F54+H54+J54+L54 -> 0 | M54: =O54+Q54+S54 -> 0 | T54: =V54+X54+Z54+AB54+AD54+AF54+AH54+AJ54+AV54 -> 0
B55: 45128 | C55: =D55+M55+T55 -> 17696590 | D55: =F55+H55+J55+L55 -> 0 | M55: =O55+Q55+S55 -> 0 | T55: =V55+X55+Z55+AB55+AD55+AF55+AH55+AJ55+AV55 -> 17696590 | U55: ｱﾙﾌｧ | V55: 17696590
B56: 45129 | C56: =D56+M56+T56 -> 307090 | D56: =F56+H56+J56+L56 -> 0 | M56: =O56+Q56+S56 -> 0 | T56: =V56+X56+Z56+AB56+AD56+AF56+AH56+AJ56+AV56 -> 307090 | U56: ｵﾘｺﾊﾞｯｸﾏｰｼﾞﾝ | V56: 111202 | W56: ｵﾘｺﾊﾞｯｸﾏｰｼﾞﾝ | X56: 195888
B57: 45130 | C57: =D57+M57+T57 -> 0 | D57: =F57+H57+J57+L57 -> 0 | M57: =O57+Q57+S57 -> 0 | T57: =V57+X57+Z57+AB57+AD57+AF57+AH57+AJ57+AV57 -> 0
B58: 45131 | C58: =D58+M58+T58 -> 1389300 | D58: =F58+H58+J58+L58 -> 0 | M58: =O58+Q58+S58 -> 1389300 | N58: 西日本自動車共済協同組合 | O58: 1389300 | T58: =V58+X58+Z58+AB58+AD58+AF58+AH58+AJ58+AV58 -> 0
B59: 45132 | C59: =D59+M59+T59 -> 291581 | D59: =F59+H59+J59+L59 -> 0 | M59: =O59+Q59+S59 -> 0 | T59: =V59+X59+Z59+AB59+AD59+AF59+AH59+AJ59+AV59 -> 291581 | U59: 労働保険料還付 | V59: 48381 | W59: ｻﾝｴｽ様 | X59: 32450 | Y59: 藤田勲様 | Z59: 50000 | AA59: 一条工務店様 | AB59: 160750
B60: 45133 | C60: =D60+M60+T60 -> 15517167 | D60: =F60+H60+J60+L60 -> 0 | M60: =O60+Q60+S60 -> 0 | T60: =V60+X60+Z60+AB60+AD60+AF60+AH60+AJ60+AV60 -> 15517167 | U60: ﾌﾟﾚﾐｱ麻田様ｶﾚﾗ11.674.983円 | V60: 11521058 | W60: ﾀｳ様ﾚﾝｿﾞﾛｰﾊﾞｰｽﾎﾟｰﾂ | X60: 3213590 | Y60: ｲﾀﾘｱﾝ料理煉天地様BME１ | Z60: 782519
B61: 45134 | C61: =D61+M61+T61 -> 0 | D61: =F61+H61+J61+L61 -> 0 | M61: =O61+Q61+S61 -> 0 | T61: =V61+X61+Z61+AB61+AD61+AF61+AH61+AJ61+AV61 -> 0
B62: 45135 | C62: =D62+M62+T62 -> 0 | D62: =F62+H62+J62+L62 -> 0 | M62: =O62+Q62+S62 -> 0 | T62: =V62+X62+Z62+AB62+AD62+AF62+AH62+AJ62+AV62 -> 0
B63: 45136 | C63: =D63+M63+T63 -> 249260 | D63: =F63+H63+J63+L63 -> 0 | M63: =O63+Q63+S63 -> 0 | T63: =V63+X63+Z63+AB63+AD63+AF63+AH63+AJ63+AV63 -> 249260 | U63: ﾕﾅｲﾃｯﾄﾞｸﾛｰ | V63: 249260
B64: 45137 | C64: =D64+M64+T64 -> 5588140 | D64: =F64+H64+J64+L64 -> 4844200 | E64: 現金 | F64: 4844200 | M64: =O64+Q64+S64 -> 0 | T64: =V64+X64+Z64+AB64+AD64+AF64+AH64+AJ64+AV64 -> 743940 | U64: はなまる様XE猪口様下取り | V64: 650000 | W64: ｱﾄﾘｴﾋﾟｭｱ様 | X64: 93940
B65: 45138 | C65: =D65+M65+T65 -> 73113464 | D65: =F65+H65+J65+L65 -> 50000000 | E65: 笠信短期 | F65: 50000000 | M65: =O65+Q65+S65 -> 0 | T65: =V65+X65+Z65+AB65+AD65+AF65+AH65+AJ65+AV65+AL65+AN65+AP65+AT65+AR65 -> 23113464 | U65: 土肥良太郎様2025年2月まで | V65: 100000 | W65: 7/31ﾃｸﾆｶﾙｱｰｸ様 | X65: 420180 | Y65: ｺﾝｸｴｽﾄ様紹介料 | Z65: 1724768 | AA65: ｺﾝｸｴｽﾄ様経費 | AB65: 3349806 | AC65: 中銀ｶｰﾄﾞVISAﾎﾞｰﾅｽ | AD65: 40090 | AE65: 中銀ｶｰﾄﾞJCB | AF65: 29430 | AG65: J&LR | AH65: 344667 | AI65: ﾋﾛｷﾞﾝﾘｰｽﾗﾝﾄﾞｸﾙｰｻﾞｰ松永ﾀｲｶﾞｰ様分8.990.280円 | AJ65: 8536950 | AK65: ｺﾝｸｴｽﾄ様ﾚﾝｼﾞﾛｰﾊﾞｰ | AL65: 6473670 | AM65: 中銀VISA | AN65: 183833 | AO65: USS岡山 | AP65: 1520160 | AQ65: 三愛運輸様 | AR65: 149450 | AS65: 福山電業様 | AT65: 152680 | AU65: 一心ｸﾞﾙｰﾌﾟ様 | AV65: 87780
B66: ７月合計 | C66: =D66+M66+T66 -> 174311873 | D66: =SUM(D35:D65) -> 54844200 | M66: =SUM(M35:M65) -> 2269699 | T66: =SUM(T35:T65) -> 117197974
B67: 未確定 | C67: =D67+M67+T67 -> 0 | T67: =V67+X67+Z67+AB67+AD67+AF67+AH67+AJ67+AV67 -> 0
B68: 45139 | C68: =D68+M68+T68 -> 269065 | D68: =F68+H68+J68+L68 -> 0 | M68: =O68 | T68: =V68+X68+Z68+AB68+AD68+AF68+AH68+AJ68+AV68 -> 269065 | U68: 田辺ﾃﾂﾛｳ様 | V68: 269065
B69: 45140 | C69: =D69+M69+T69 -> 0 | D69: =F69+H69+J69+L69 -> 0 | M69: =O69 | T69: =V69+X69+Z69+AB69+AD69+AF69+AH69+AJ69+AV69 -> 0
B70: 45141 | C70: =D70+M70+T70 -> 0 | D70: =F70+H70+J70+L70 -> 0 | M70: =O70 | T70: =V70+X70+Z70+AB70+AD70+AF70+AH70+AJ70+AV70 -> 0
B71: 45142 | C71: =D71+M71+T71 -> 0 | D71: =F71+H71+J71+L71 -> 0 | M71: =O71 | T71: =V71+X71+Z71+AB71+AD71+AF71+AH71+AJ71+AV71 -> 0
B72: 45143 | C72: =D72+M72+T72 -> 42837 | D72: =F72+H72+J72+L72 -> 0 | M72: =O72+Q72 -> 0 | T72: =V72+X72+Z72+AB72+AD72+AF72+AH72+AJ72+AV72 -> 42837 | U72: 森田和也様2024.9月まで | V72: 42837
B73: 45144 | C73: =D73+M73+T73 -> 55000 | D73: =F73+H73+J73+L73 -> 0 | M73: =O73+Q73 -> 0 | T73: =V73+X73+Z73+AB73+AD73+AF73+AH73+AJ73+AV73 -> 55000 | U73: 吉元様A３ | V73: 55000
B74: 45145 | C74: =D74+M74+T74 -> 0 | D74: =F74+H74+J74+L74 -> 0 | M74: =O74+Q74 -> 0 | T74: =V74+X74+Z74+AB74+AD74+AF74+AH74+AJ74+AV74 -> 0
B75: 45146 | C75: =D75+M75+T75 -> 0 | D75: =F75+H75+J75+L75 -> 0 | M75: =O75+Q75 -> 0 | T75: =V75+X75+Z75+AB75+AD75+AF75+AH75+AJ75+AV75 -> 0
B76: 45147 | C76: =D76+M76+T76 -> 146768 | D76: =F76+H76+J76+L76 -> 0 | M76: =O76+Q76 -> 0 | T76: =V76+X76+Z76+AB76+AD76+AF76+AH76+AJ76+AV76 -> 146768 | U76: 麻田ﾋﾛｷ様 | V76: 146768
B77: 45148 | C77: =D77+M77+T77 -> 0 | D77: =F77+H77+J77+L77 -> 0 | M77: =O77+Q77 -> 0 | T77: =V77+X77+Z77+AB77+AD77+AF77+AH77+AJ77+AV77 -> 0
B78: 45149 | C78: =D78+M78+T78 -> 0 | D78: =F78+H78+J78+L78 -> 0 | M78: =O78+Q78 -> 0 | T78: =V78+X78+Z78+AB78+AD78+AF78+AH78+AJ78+AV78 -> 0
B79: 45150 | C79: =D79+M79+T79 -> 0 | D79: =F79+H79+J79+L79 -> 0 | M79: =O79+Q79 -> 0 | T79: =V79+X79+Z79+AB79+AD79+AF79+AH79+AJ79+AV79 -> 0
B80: 45151 | C80: =D80+M80+T80 -> 0 | D80: =F80+H80+J80+L80 -> 0 | M80: =O80+Q80 -> 0 | T80: =V80+X80+Z80+AB80+AD80+AF80+AH80+AJ80+AV80 -> 0
B81: 45152 | C81: =D81+M81+T81 -> 0 | D81: =F81+H81+J81+L81 -> 0 | M81: =O81+Q81 -> 0 | T81: =V81+X81+Z81+AB81+AD81+AF81+AH81+AJ81+AV81 -> 0
B82: 45153 | C82: =D82+M82+T82 -> 64857 | D82: =F82+H82+J82+L82 -> 0 | M82: =O82+Q82 -> 0 | T82: =V82+X82+Z82+AB82+AD82+AF82+AH82+AJ82+AV82 -> 64857 | U82: 中銀ｶｰﾄﾞJCB | V82: 3725 | W82: 中銀ｶｰﾄﾞVISA | X82: 40172 | Y82: ｷﾑﾗﾕﾆﾃｨ様 | Z82: 12160 | AA82: ﾜﾀﾞ ﾀｲｷ様 | AB82: 8800
B83: 45154 | C83: =D83+M83+T83 -> 229328 | D83: =F83+H83+J83+L83 -> 0 | M83: =O83+Q83 -> 229328 | N83: 三井代理店手数料 | O83: 143467 | P83: 東京海上代理店手数料 | Q83: 85861 | T83: =V83+X83+Z83+AB83+AD83+AF83+AH83+AJ83+AV83 -> 0
B84: 45155 | C84: =D84+M84+T84 -> 0 | D84: =F84+H84+J84+L84 -> 0 | M84: =O84+Q84 -> 0 | T84: =V84+X84+Z84+AB84+AD84+AF84+AH84+AJ84+AV84 -> 0
B85: 45156 | C85: =D85+M85+T85 -> 0 | D85: =F85+H85+J85+L85 -> 0 | M85: =O85+Q85 -> 0 | T85: =V85+X85+Z85+AB85+AD85+AF85+AH85+AJ85+AV85 -> 0
B86: 45157 | C86: =D86+M86+T86 -> 511 | D86: =F86+H86+J86+L86 -> 511 | E86: 広信受取利息 | F86: 6 | G86: 中銀受取利息 | H86: 122 | I86: もみじ受取利息 | J86: 383 | M86: =O86+Q86 -> 0 | T86: =V86+X86+Z86+AB86+AD86+AF86+AH86+AJ86+AV86 -> 0
B87: 45158 | C87: =D87+M87+T87 -> 0 | D87: =F87+H87+J87+L87 -> 0 | M87: =O87+Q87 -> 0 | T87: =V87+X87+Z87+AB87+AD87+AF87+AH87+AJ87+AV87 -> 0
B88: 45159 | C88: =D88+M88+T88 -> 0 | D88: =F88+H88+J88+L88 -> 0 | M88: =O88+Q88 -> 0 | T88: =V88+X88+Z88+AB88+AD88+AF88+AH88+AJ88+AV88 -> 0
B89: 45160 | C89: =D89+M89+T89 -> 2427078 | D89: =F89+H89+J89+L89 -> 0 | M89: =O89+Q89 -> 0 | T89: =V89+X89+Z89+AB89+AD89+AF89+AH89+AJ89+AV89 -> 2427078 | U89: ﾀｵ様ｲｳﾞｫｰｸﾞ | V89: 789360 | W89: ﾀｳ様Fﾍﾟｰｽ | X89: 1561590 | Y89: 調整 | Z89: 76128
B90: 45161 | C90: =D90+M90+T90 -> 50000 | D90: =F90+H90+J90+L90 -> 0 | M90: =O90+Q90 -> 0 | T90: =V90+X90+Z90+AB90+AD90+AF90+AH90+AJ90+AV90 -> 50000 | U90: 藤田勲様 | V90: 50000
B91: 45162 | C91: =D91+M91+T91 -> 0 | D91: =F91+H91+J91+L91 -> 0 | M91: =O91+Q91 -> 0 | T91: =V91+X91+Z91+AB91+AD91+AF91+AH91+AJ91+AV91 -> 0
B92: 45163 | C92: =D92+M92+T92 -> 0 | D92: =F92+H92+J92+L92 -> 0 | M92: =O92+Q92 -> 0 | T92: =V92+X92+Z92+AB92+AD92+AF92+AH92+AJ92+AV92 -> 0
B93: 45164 | C93: =D93+M93+T93 -> 9570 | D93: =F93+H93+J93+L93 -> 0 | M93: =O93+Q93 -> 0 | T93: =V93+X93+Z93+AB93+AD93+AF93+AH93+AJ93+AV93 -> 9570 | U93: ﾒﾃﾞｨｱﾃｨｯｸ一心様 | V93: 9570
B94: 45165 | C94: =D94+M94+T94 -> 4652750 | D94: =F94+H94+J94+L94 -> 0 | M94: =O94+Q94 -> 0 | T94: =V94+X94+Z94+AB94+AD94+AF94+AH94+AJ94+AV94 -> 4652750 | U94: USS岡山 | V94: 2750 | W94: ｼｭﾃﾙﾝ世田谷様ﾍﾞﾝﾂCｸﾗｽ | X94: 4650000
B95: 45166 | C95: =D95+M95+T95 -> 14840588 | D95: =F95+H95+J95+L95 -> 14840588 | E95: 笠信短期借入れ1.500万円 | F95: 14838699 | G95: 笠信 | H95: 1369 | I95: 笠信 | J95: 520 | M95: =O95+Q95 -> 0 | T95: =V95+X95+Z95+AB95+AD95+AF95+AH95+AJ95+AV95 -> 0
B96: 45167 | C96: =D96+M96+T96 -> 33000 | D96: =F96+H96+J96+L96 -> 0 | M96: =O96+Q96 -> 0 | T96: =V96+X96+Z96+AB96+AD96+AF96+AH96+AJ96+AV96 -> 33000 | U96: 三須磨ﾕｷｴ様 | V96: 33000
B97: 45168 | C97: =D97+M97+T97 -> 3823157 | D97: =F97+H97+J97+L97 -> 0 | M97: =O97+Q97 -> 0 | T97: =V97+X97+Z97+AB97+AD97+AF97+AH97+AJ97+AV97 -> 3823157 | U97: ｺﾝｸｴｽﾄ様経費 | V97: 3530453 | W97: ｺﾝｸｴｽﾄ様J&R | X97: 54984 | Y97: ﾕﾅｲﾃｯﾄﾞｸﾛｰﾊﾞｰ様 | Z97: 23320 | AA97: 中古車自動車JU | AB97: 1000 | AC97: 一心ｸﾞﾙｰﾌﾟ様 | AD97: 213400
B98: 45169 | C98: =D98+M98+T98 -> 0 | D98: =F98+H98+J98+L98 -> 0 | M98: =O98+Q98 -> 0 | T98: =V98+X98+Z98+AB98+AD98+AF98+AH98+AJ98+AV98 -> 0
B99: ８月合計 | C99: =D99+M99+T99 -> 26644509 | D99: =SUM(D68:D98) -> 14841099 | M99: =SUM(M68:M98) -> 229328 | T99: =SUM(T68:T98) -> 11574082
B100: 未確定
...

Sheet 出金明細 
C1: ２０２4年６月‐２０２5年５月出金
C2: 出金日次 | D2: 金融小計 | M2: 買掛小計 | AD2: 経費小計
B3: 44348 | C3: =D3+M3+AD3 -> 0 | D3: =F3+H3+J3+L3 -> 0 | M3: =O3+Q3+S3+U3 -> 0 | AD3: =AF3+AH3+AJ3+AL3+AN3+AP3+AR3+AT3+AV3+AX3+AZ3+BB3+BD3+BF3+BH3+BJ3+BL3+BN3+BP3+BR3+BT3+BV3+BX3+BZ3+CB3+CD3 -> 0
B4: 44349 | C4: =D4+M4+AD4 -> 0 | D4: =F4+H4+J4+L4 -> 0 | M4: =O4+Q4+S4+U4 -> 0 | AD4: =AF4+AH4+AJ4+AL4+AN4+AP4+AR4+AT4+AV4+AX4+AZ4+BB4+BD4+BF4+BH4+BJ4+BL4+BN4+BP4+BR4+BT4+BV4+BX4+BZ4+CB4+CD4 -> 0
B5: 45446 | C5: =D5+M5+AD5 -> 934278 | D5: =F5+H5+J5+L5 -> 0 | E5: 笠信 | M5: =O5+Q5+S5+U5 -> 0 | AD5: =AF5+AH5+AJ5+AL5+AN5+AP5+AR5+AT5+AV5+AX5+AZ5+BB5+BD5+BF5+BH5+BJ5+BL5+BN5+BP5+BR5+BT5+BV5+BX5+BZ5+CB5+CD5 -> 934278 | AE5: も）ﾄﾖﾀﾌｧｲﾅﾝｽ | AF5: 64774 | AG5: 自動車税 | AH5: 540600 | AI5: 自動車税軽 | AJ5: 33000 | AK5: 現金へ資金移動 | AL5: 200000 | AM5: も）日本GE ｺﾝﾌﾟﾚｯｻｰ等ﾘｰｽ料SVLｷｬﾋﾟﾀﾙ | AN5: 95904
B6: 44351 | C6: =D6+M6+AD6 -> 67100 | D6: =F6+H6+J6+L6 -> 0 | M6: =O6+Q6+S6+U6 -> 0 | AD6: =AF6+AH6+AJ6+AL6+AN6+AP6+AR6+AT6+AV6+AX6+AZ6+BB6+BD6+BF6+BH6+BJ6+BL6+BN6+BP6+BR6+BT6+BV6+BX6+BZ6+CB6+CD6 -> 67100 | AE6: ﾘｺｰPCﾘｰｽ | AF6: 67100
B7: 44352 | C7: =D7+M7+AD7 -> 0 | D7: =F7+H7+J7+L7 -> 0 | M7: =O7+Q7+S7+U7 -> 0 | AD7: =AF7+AH7+AJ7+AL7+AN7+AP7+AR7+AT7+AV7+AX7+AZ7+BB7+BD7+BF7+BH7+BJ7+BL7+BN7+BP7+BR7+BT7+BV7+BX7+BZ7+CB7+CD7 -> 0
B8: 44353 | C8: =D8+M8+AD8 -> 10550 | D8: =F8+H8+J8+L8 -> 10550 | E8: 笠信収入印紙 | F8: 10000 | G8: 笠信手数料 | H8: 550 | M8: =O8+Q8+S8+U8 -> 0 | AD8: =AF8+AH8+AJ8+AL8+AN8+AP8+AR8+AT8+AV8+AX8+AZ8+BB8+BD8+BF8+BH8+BJ8+BL8+BN8+BP8+BR8+BT8+BV8+BX8+BZ8+CB8+CD8 -> 0 | AE8: 自賠責 | AF8: 0
B9: 44354 | C9: =D9+M9+AD9 -> 35283893 | D9: =F9+H9+J9+L9 -> 5002750 | E9: 笠信借入れ短期返済 | F9: 5000000 | G9: 広信 | H9: 1210 | I9: 笠信手数料 | J9: 990 | L9: 550 | M9: =O9+Q9+S9+U9 -> 30085813 | N9: ｼﾞｬｯｸｽ残一括ﾌｪﾗｰﾘ | O9: 30085813 | AD9: =AF9+AH9+AJ9+AL9+AN9+AP9+AR9+AT9+AV9+AX9+AZ9+BB9+BD9+BF9+BH9+BJ9+BL9+BN9+BP9+BR9+BT9+BV9+BX9+BZ9+CB9+CD9 -> 195330 | AE9: 住民税、所得税支払い | AF9: 195330
B10: 44355 | C10: =D10+M10+AD10 -> 0 | D10: =F10+H10+J10+L10 -> 0 | M10: =O10+Q10+S10+U10 -> 0 | AD10: =AF10+AH10+AJ10+AL10+AN10+AP10+AR10+AT10+AV10+AX10+AZ10+BB10+BD10+BF10+BH10+BJ10+BL10+BN10+BP10+BR10+BT10+BV10+BX10+BZ10+CB10+CD10 -> 0
B11: 44356 | C11: =D11+M11+AD11 -> 0 | D11: =F11+H11+J11+L11 -> 0 | M11: =O11+Q11+S11+U11 -> 0 | AD11: =AF11+AH11+AJ11+AL11+AN11+AP11+AR11+AT11+AV11+AX11+AZ11+BB11+BD11+BF11+BH11+BJ11+BL11+BN11+BP11+BR11+BT11+BV11+BX11+BZ11+CB11+CD11 -> 0
B12: 44357 | C12: =D12+M12+AD12 -> 2982483 | D12: =F12+H12+J12+L12 -> 26026 | E12: 広銀手数料 | F12: 16346 | G12: 笠信手数料 | H12: 330 | I12: 中銀手数料 | J12: 4730 | K12: もみじ手数料 | L12: 4620 | M12: =O12+Q12+S12+U12 -> 0 | AD12: =AF12+AH12+AJ12+AL12+AN12+AP12+AR12+AT12+AV12+AX12+AZ12+BB12+BD12+BF12+BH12+BJ12+BL12+BN12+BP12+BR12+BT12+BV12+BX12+BZ12+CB12+CD12 -> 2956457 | AE12: 田中賢治様 | AF12: 14600 | AG12: も）ｶｰﾄﾞ引落 | AH12: 240123 | AI12: 給与 | AJ12: 1683320 | AK12: 伊賀上社長役員報酬60万円車手当20万円 | AL12: 200000 | AM12: 高田自動車 | AN12: 485168 | AO12: 銚子さん | AP12: 170000 | AQ12: 自賠責 | AR12: 92655 | AS12: ｽｽﾞｷﾌﾛﾝﾃ福山 | AT12: 50000 | AU12: ｱｽｸﾙ | AV12: 20591
B13: 44358 | C13: =D13+M13+AD13 -> 0 | D13: =F13+H13+J13+L13 -> 0 | M13: =O13+Q13+S13+U13 -> 0 | AD13: =AF13+AH13+AJ13+AL13+AN13+AP13+AR13+AT13+AV13+AX13+AZ13+BB13+BD13+BF13+BH13+BJ13+BL13+BN13+BP13+BR13+BT13+BV13+BX13+BZ13+CB13+CD13 -> 0
B14: 44359 | C14: =D14+M14+AD14 -> 13314936 | D14: =F14+H14+J14+L14 -> 0 | M14: =O14+Q14+S14+U14 -> 13314936 | N14: ｼﾞｬｯｸｽﾎﾟﾙｼｪ残一括 | O14: 13314936 | AD14: =AF14+AH14+AJ14+AL14+AN14+AP14+AR14+AT14+AV14+AX14+AZ14+BB14+BD14+BF14+BH14+BJ14+BL14+BN14+BP14+BR14+BT14+BV14+BX14+BZ14+CB14+CD14 -> 0
B15: 44360 | C15: =D15+M15+AD15 -> 0 | D15: =F15+H15+J15+L15 -> 0 | M15: =O15+Q15+S15+U15 -> 0 | AD15: =AF15+AH15+AJ15+AL15+AN15+AP15+AR15+AT15+AV15+AX15+AZ15+BB15+BD15+BF15+BH15+BJ15+BL15+BN15+BP15+BR15+BT15+BV15+BX15+BZ15+CB15+CD15 -> 0
B16: 44361 | C16: =D16+M16+AD16 -> 0 | D16: =F16+H16+J16+L16 -> 0 | M16: =O16+Q16+S16+U16 -> 0 | AD16: =AF16+AH16+AJ16+AL16+AN16+AP16+AR16+AT16+AV16+AX16+AZ16+BB16+BD16+BF16+BH16+BJ16+BL16+BN16+BP16+BR16+BT16+BV16+BX16+BZ16+CB16+CD16 -> 0
